Workbook
Name LISTA_D: DB!$AC$2:$AC$190
Name LISTA_P: DB!$AB$2:$AB$65
Name LISTA_A: DB!$AE$2:$AE$90
Name LISTA_C: DB!$AD$2:$AD$194

Sheet Guida
A1: FANTACALCIO CLASSIC - SERIE A 2026/27
A2: Listone, priorita, abbinamenti di calendario e foglio d'asta. Dati: Fantacalcio.it, aggiornati al 1 settembre 2026. Solo giocatori nelle rose ufficiali di Serie A.
A4: PARAMETRI DELLA LEGA - compila solo le celle gialle
A5: Budget per squadra (crediti) | B5: 500 | C5: Il monte crediti di ogni fantallenatore.
A6: Numero di squadre nella lega | B6: 10 | C6: Serve a sapere quanti giocatori vengono davvero assegnati.
A7: Giocatori per rosa | B7: =SUM(B11:B14) -> 25 | C7: 3 portieri + 8 difensori + 8 centrocampisti + 6 attaccanti.
A8: Crediti totali in gioco | B8: =B5*B6 -> 5000 | C8: Budget x numero squadre: la torta che vi dividete all'asta.
A10: Reparto | B10: Slot in rosa | C10: % del budget | D10: Crediti del reparto | E10: Giocatori assegnati nella lega | F10: Fattore prezzo (K)
A11: Portieri | B11: 3 | C11: 0.06 | D11: =ROUND($B$5*C11,0) -> 30 | E11: =$B$6*B11 -> 30 | F11: =IFERROR(D11*$B$6/SUMPRODUCT((Portieri!$AH$4:$AH$67<=E11)*(Portieri!$H$4:$H$67^$B$18)),0) -> 1.3619827
A12: Difensori | B12: 8 | C12: 0.15 | D12: =ROUND($B$5*C12,0) -> 75 | E12: =$B$6*B12 -> 80 | F12: =IFERROR(D12*$B$6/SUMPRODUCT((Difensori!$AH$4:$AH$192<=E12)*(Difensori!$H$4:$H$192^$B$18)),0) -> 1.2703247
A13: Centrocampisti | B13: 8 | C13: 0.29 | D13: =ROUND($B$5*C13,0) -> 145 | E13: =$B$6*B13 -> 80 | F13: =IFERROR(D13*$B$6/SUMPRODUCT((Centrocampisti!$AH$4:$AH$196<=E13)*(Centrocampisti!$H$4:$H$196^$B$18)),0) -> 1.8113619
A14: Attaccanti | B14: 6 | C14: 0.5 | D14: =ROUND($B$5*C14,0) -> 250 | E14: =$B$6*B14 -> 60 | F14: =IFERROR(D14*$B$6/SUMPRODUCT((Attaccanti!$AH$4:$AH$92<=E14)*(Attaccanti!$H$4:$H$92^$B$18)),0) -> 3.4056009
A15: Totale | B15: =SUM(B11:B14) -> 25 | C15: =SUM(C11:C14) -> 1 | D15: =SUM(D11:D14) -> 500 | E15: =SUM(E11:E14) -> 250
A17: CURVA DEI PREZZI
A18: Compressione della curva (0,5 - 1,0) | B18: 0.6 | C18: 1,00 = prezzi proporzionali al FVM (top carissimi). 0,50 = curva molto piatta. 0,60 e la taratura consigliata: il miglior attaccante vale circa il 26% del budget.
A19: Prezzo consigliato = | B19: FVM^compressione x K | C19: K e calcolato per reparto in modo che la somma dei prezzi consigliati usi esattamente i crediti del reparto.
A21: PESI DELL'INDICE DI PRIORITA (totale 100)
A22: Peso valore di mercato (FVM) | B22: 60 | C22: Quanto pesa la valutazione di mercato del giocatore.
A23: Peso rendimento (fantamedia ponderata) | B23: 25 | C23: Fantamedia 2025/26 corretta per le presenze.
A24: Peso rigorista | B24: 10 | C24: 1o rigorista = 1,00 | 2o = 0,60 | 3o = 0,35 | 4o = 0,20.
A25: Peso calci piazzati | B25: 5 | C25: 1o tiratore = 1,00 | 2o = 0,60 | 3o = 0,35.
A27: VALORI DI RIFERIMENTO (calcolati)
A28: FVM massimo - Portieri | B28: =MAX(Portieri!$H$4:$H$67) -> 85
A29: FVM massimo - Difensori | B29: =MAX(Difensori!$H$4:$H$192) -> 240
A30: FVM massimo - Centrocampisti | B30: =MAX(Centrocampisti!$H$4:$H$196) -> 245
A31: FVM massimo - Attaccanti | B31: =MAX(Attaccanti!$H$4:$H$92) -> 450
A34: COME SI USA
A35: 1. | B35: Fogli Portieri / Difensori / Centrocampisti / Attaccanti: il listone completo (587 giocatori), gia ordinato per priorita. Ogni foglio ha i filtri attivi sull'intestazione.
A36: 2. | B36: Cambia i parametri qui sopra (celle gialle): budget, numero squadre, percentuali di reparto, pesi e compressione. Tutti i prezzi consigliati e le priorita si ricalcolano.
A37: 3. | B37: Foglio Abbinamenti: la matrice del calendario 2026/27. Il numero dice quante volte due squadre giocano in trasferta nella stessa giornata: piu basso = si coprono meglio. Sotto trovi le migliori coppie e i migliori terzetti di portieri.
A38: 4. | B38: Foglio Asta: scegli i giocatori dai menu a tendina e scrivi il prezzo pagato. I crediti scalano riga per riga a partire da 500 e il controllo abbinamento portieri si aggiorna da solo.
A39: 5. | B39: Foglio Statistiche 25-26: i dati grezzi della scorsa stagione, filtrabili.
A41: LEGENDA COLORI
A42: Giallo | B42: Celle da compilare o parametri modificabili.
A43: Verde | B43: Situazione favorevole: buon affare, abbinamento ottimo, budget in linea, titolare.
A44: Rosso | B44: Attenzione: prezzo sopra il consigliato, abbinamento sfavorevole, budget sforato, riserva.
A45: Arancione | B45: Titolare sulla carta ma zero presenze nelle prime due giornate: rischia il posto. Nel foglio Asta segnala anche un giocatore inserito due volte.
A47: LA COLONNA NOTA (aggiornata al 01/09/2026, dopo 2 giornate)
A48: INFORTUNATO (lungo stop) | B48: Rientro previsto da ottobre in poi: all'asta vale molto meno del prezzo consigliato, oppure e' un investimento a scadenza.
A49: Infortunato | B49: Fuori adesso ma con rientro atteso entro settembre: si prende scontato.
A50: In dubbio / da valutare | B50: Acciaccato, convocazione a rischio per la prossima giornata.
A51: RISCHIA il posto (0/2) | B51: Sulla carta titolare per quotazione, ma non ha ancora giocato un minuto nelle prime due giornate.
A52: Rischia il posto (1/2) | B52: Una presenza su due: gerarchia non ancora chiara.
A53: Titolare confermato (2/2) | B53: Ha giocato entrambe le partite: il posto ce l'ha.
A54: In ballottaggio / Riserva | B54: Non e' il titolare designato secondo le quotazioni; fra parentesi le presenze nelle prime due.
A55: Nuovo | B55: Cambia squadra rispetto al 2025/26 oppure arriva da fuori Serie A: nessuno storico italiano su cui basarsi.
A57: NOTE SUL METODO
A58: Indice di priorita | B58: Combina valore di mercato (FVM di Fantacalcio.it), rendimento 2025/26 ponderato sulle presenze, ruolo di rigorista e di tiratore da calci piazzati. E' un ordinamento ragionato, non una verita assoluta: usalo come punto di partenza.
A59: Fantamedia ponderata | B59: FM 2025/26 x (PG/25, massimo 1) + 5,50 x (1 - PG/25). Chi ha giocato poco viene riportato verso la media di riferimento 5,50, cosi tre partite fortunate non lo mandano in cima alla lista.
A60: Giocatori senza storico | B60: Nuovi acquisti dall'estero o dalla Serie B: presenze = 0 e fantamedia stimata 5,50. Per loro pesa quasi solo il FVM. Sono segnalati nella colonna Nuovo/Trasf.
A61: Gerarchia stimata | B61: Derivata dalla quotazione all'interno della stessa squadra e ruolo (titolare / ballottaggio / riserva). Da rileggere a ridosso dell'asta: il mercato e ancora aperto.
A62: Prezzo consigliato | B62: Il FVM di Fantacalcio.it (che vale per aste da 1.000 crediti) viene compresso e riscalato sui crediti realmente in gioco nella tua lega, reparto per reparto. Somma FVM dei primi 250 giocatori: 11862 punti.
A63: Prezzo massimo | B63: Prezzo consigliato + 20%: oltre questa cifra stai pagando il giocatore piu di quanto valga per la tua rosa.
A65: Chi c'e' nel listone | B65: Solo i 535 calciatori presenti nelle rose ufficiali delle 20 squadre di Serie A 2026/27 su Fantacalcio.it. Le quotazioni includono anche giocatori nel frattempo ceduti all'estero (Leao, Lukaku, Nkunku, David, Gimenez, Morata, Di Gregorio, Suzuki e altri): sono stati tolti uno per uno incrociando il listone con la rosa di ogni squadra.
A67: FONTI | B67: Quotazioni ufficiali Classic e Mantra, rose delle 20 squadre, statistiche 2025/26 e 2026/27, rigoristi e tiratori da fermo, indisponibili, griglia portieri: Fantacalcio.it, consultati il 01/09/2026. Calendario Serie A 2026/27 (20 squadre, neopromosse Frosinone, Monza e Venezia).

Sheet Portieri
A1: PORTIERI - Listone Fantacalcio Classic 2026/27
A2: 64 giocatori, solo quelli presenti nelle rose ufficiali di Serie A 2026/27. Ordinati per indice di priorita. Colonna NOTA: infortuni, rischio titolarita e nuovi acquisti (dati al 01/09/2026, dopo 2 giornate).
A3: Prio | B3: Indice | C3: Giocatore | D3: Squadra | E3: Ruolo Mantra | F3: Qt.I | G3: Qt.A | H3: FVM | I3: Prezzo consigliato | J3: Prezzo max | K3: Fascia | L3: Gerarchia stimata | M3: NOTA | N3: Rigorista | O3: Calci piazzati | P3: PG 25/26 | Q3: MV 25/26 | R3: FM 25/26 | S3: Gol 25/26 | T3: Assist 25/26 | U3: Rig. segnati 25/26 | V3: Amm. 25/26 | W3: Esp. 25/26 | X3: PG 26/27 (su 2) | Y3: MV 26/27 | Z3: FM 26/27 | AA3: Gol 26/27 | AB3: Assist 26/27 | AC3: Squadra 25/26 | AD3: Nuovo/Trasf. | AE3: FM ponderata | AF3: Miglior abbinamento (calendario) | AG3: Trasferte in comune | AH3: Rank FVM di ruolo | AI3: Dettaglio infortunio / stato
A4: =RANK(B4,$B$4:$B$67) -> 1 | B4: =ROUND(Guida!$B$22*H4/Guida!$B$28+Guida!$B$23*MAX(0,MIN(1,(AE4-5.4)/1.6))+Guida!$B$24*0+Guida!$B$25*0,1) -> 60.8 | C4: Svilar | D4: Roma | E4: Portiere | F4: 18 | G4: 19 | H4: 85 | I4: =MAX(1,ROUND(H4^Guida!$B$18*Guida!$F$11,0)) -> 20 | J4: =MAX(2,ROUND(I4*1.2,0)) -> 24 | K4: =IF(I4>=60,"Top",IF(I4>=30,"1a fascia",IF(I4>=15,"2a fascia",IF(I4>=7,"3a fascia",IF(I4>=3,"4a fascia","Scommessa"))))) -> 2a fascia | L4: Titolare | M4: Titolare confermato (2/2) | N4: - | O4: - | P4: 38 | Q4: 6.26 | R4: 5.45 | S4: 0 | T4: 0 | U4: 0/0 | V4: 0 | W4: 0 | X4: 2 | Y4: 6.25 | Z4: 6.25 | AA4: 0 | AB4: 0 | AC4: Roma | AD4: No | AE4: =ROUND(IF(P4="",5.5,R4*MIN(1,P4/25)+5.5*(1-MIN(1,P4/25))),2) -> 5.45 | AF4: Meret (NAP) | AG4: 3 | AH4: =RANK(H4,$H$4:$H$67) -> 1
A5: =RANK(B5,$B$4:$B$67) -> 2 | B5: =ROUND(Guida!$B$22*H5/Guida!$B$28+Guida!$B$23*MAX(0,MIN(1,(AE5-5.4)/1.6))+Guida!$B$24*0+Guida!$B$25*0,1) -> 51 | C5: Vicario | D5: Juventus | E5: Portiere | F5: 16 | G5: 17 | H5: 70 | I5: =MAX(1,ROUND(H5^Guida!$B$18*Guida!$F$11,0)) -> 17 | J5: =MAX(2,ROUND(I5*1.2,0)) -> 20 | K5: =IF(I5>=60,"Top",IF(I5>=30,"1a fascia",IF(I5>=15,"2a fascia",IF(I5>=7,"3a fascia",IF(I5>=3,"4a fascia","Scommessa"))))) -> 2a fascia | L5: Titolare | M5: Nuovo - Titolare confermato (2/2) | N5: - | O5: - | X5: 2 | Y5: 6.25 | Z5: 6.25 | AA5: 0 | AB5: 0 | AC5: - | AD5: Si | AE5: =ROUND(IF(P5="",5.5,R5*MIN(1,P5/25)+5.5*(1-MIN(1,P5/25))),2) -> 5.5 | AF5: Svilar (ROM) | AG5: 6 | AH5: =RANK(H5,$H$4:$H$67) -> 2
A6: =RANK(B6,$B$4:$B$67) -> 3 | B6: =ROUND(Guida!$B$22*H6/Guida!$B$28+Guida!$B$23*MAX(0,MIN(1,(AE6-5.4)/1.6))+Guida!$B$24*0+Guida!$B$25*0,1) -> 48.6 | C6: Martinez Jo. | D6: Inter | E6: Portiere | F6: 17 | G6: 17 | H6: 68 | I6: =MAX(1,ROUND(H6^Guida!$B$18*Guida!$F$11,0)) -> 17 | J6: =MAX(2,ROUND(I6*1.2,0)) -> 20 | K6: =IF(I6>=60,"Top",IF(I6>=30,"1a fascia",IF(I6>=15,"2a fascia",IF(I6>=7,"3a fascia",IF(I6>=3,"4a fascia","Scommessa"))))) -> 2a fascia | L6: Titolare | M6: Titolare confermato (2/2) | N6: - | O6: - | P6: 5 | Q6: 6 | R6: 5.2 | S6: 0 | T6: 0 | U6: 0/0 | V6: 0 | W6: 0 | X6: 2 | Y6: 6 | Z6: 5.5 | AA6: 0 | AB6: 0 | AC6: Inter | AD6: No | AE6: =ROUND(IF(P6="",5.5,R6*MIN(1,P6/25)+5.5*(1-MIN(1,P6/25))),2) -> 5.44 | AF6: Maignan (MIL) | AG6: 0 | AH6: =RANK(H6,$H$4:$H$67) -> 3
A7: =RANK(B7,$B$4:$B$67) -> 4 | B7: =ROUND(Guida!$B$22*H7/Guida!$B$28+Guida!$B$23*MAX(0,MIN(1,(AE7-5.4)/1.6))+Guida!$B$24*0+Guida!$B$25*0,1) -> 41.6 | C7: Carnesecchi | D7: Atalanta | E7: Portiere | F7: 16 | G7: 17 | H7: 55 | I7: =MAX(1,ROUND(H7^Guida!$B$18*Guida!$F$11,0)) -> 15 | J7: =MAX(2,ROUND(I7*1.2,0)) -> 18 | K7: =IF(I7>=60,"Top",IF(I7>=30,"1a fascia",IF(I7>=15,"2a fascia",IF(I7>=7,"3a fascia",IF(I7>=3,"4a fascia","Scommessa"))))) -> 2a fascia | L7: Titolare | M7: Titolare confermato (2/2) | N7: - | O7: - | P7: 37 | Q7: 6.36 | R7: 5.58 | S7: 0 | T7: 0 | U7: 0/0 | V7: 0 | W7: 0 | X7: 2 | Y7: 6.75 | Z7: 6.75 | AA7: 0 | AB7: 1 | AC7: Atalanta | AD7: No | AE7: =ROUND(IF(P7="",5.5,R7*MIN(1,P7/25)+5.5*(1-MIN(1,P7/25))),2) -> 5.58 | AF7: Svilar (ROM) | AG7: 7 | AH7: =RANK(H7,$H$4:$H$67) -> 4
A8: =RANK(B8,$B$4:$B$67) -> 5 | B8: =ROUND(Guida!$B$22*H8/Guida!$B$28+Guida!$B$23*MAX(0,MIN(1,(AE8-5.4)/1.6))+Guida!$B$24*0+Guida!$B$25*0,1) -> 37 | C8: Maignan | D8: Milan | E8: Portiere | F8: 15 | G8: 15 | H8: 52 | I8: =MAX(1,ROUND(H8^Guida!$B$18*Guida!$F$11,0)) -> 15 | J8: =MAX(2,ROUND(I8*1.2,0)) -> 18 | K8: =IF(I8>=60,"Top",IF(I8>=30,"1a fascia",IF(I8>=15,"2a fascia",IF(I8>=7,"3a fascia",IF(I8>=3,"4a fascia","Scommessa"))))) -> 2a fascia | L8: Titolare | M8: Titolare confermato (2/2) | N8: - | O8: - | P8: 37 | Q8: 6.26 | R8: 5.42 | S8: 0 | T8: 0 | U8: 0/0 | V8: 4 | W8: 0 | X8: 2 | Y8: 6 | Z8: 5.5 | AA8: 0 | AB8: 0 | AC8: Milan | AD8: No | AE8: =ROUND(IF(P8="",5.5,R8*MIN(1,P8/25)+5.5*(1-MIN(1,P8/25))),2) -> 5.42 | AF8: Martinez Jo. (INT) | AG8: 0 | AH8: =RANK(H8,$H$4:$H$67) -> 5
A9: =RANK(B9,$B$4:$B$67) -> 6 | B9: =ROUND(Guida!$B$22*H9/Guida!$B$28+Guida!$B$23*MAX(0,MIN(1,(AE9-5.4)/1.6))+Guida!$B$24*0+Guida!$B$25*0,1) -> 35.3 | C9: Butez | D9: Como | E9: Portiere | F9: 16 | G9: 15 | H9: 50 | I9: =MAX(1,ROUND(H9^Guida!$B$18*Guida!$F$11,0)) -> 14 | J9: =MAX(2,ROUND(I9*1.2,0)) -> 17 | K9: =IF(I9>=60,"Top",IF(I9>=30,"1a fascia",IF(I9>=15,"2a fascia",IF(I9>=7,"3a fascia",IF(I9>=3,"4a fascia","Scommessa"))))) -> 3a fascia | L9: Titolare | M9: Titolare confermato (2/2) | N9: - | O9: - | P9: 38 | Q9: 6.07 | R9: 5.37 | S9: 0 | T9: 1 | U9: 0/0 | V9: 3 | W9: 0 | X9: 2 | Y9: 5.75 | Z9: 4.75 | AA9: 0 | AB9: 0 | AC9: Como | AD9: No | AE9: =ROUND(IF(P9="",5.5,R9*MIN(1,P9/25)+5.5*(1-MIN(1,P9/25))),2) -> 5.37 | AF9: De Gea (FIO) | AG9: 6 | AH9: =RANK(H9,$H$4:$H$67) -> 6
A10: =RANK(B10,$B$4:$B$67) -> 7 | B10: =ROUND(Guida!$B$22*H10/Guida!$B$28+Guida!$B$23*MAX(0,MIN(1,(AE10-5.4)/1.6))+Guida!$B$24*0+Guida!$B$25*0,1) -> 33.9 | C10: Meret | D10: Napoli | E10: Portiere | F10: 11 | G10: 11 | H10: 48 | I10: =MAX(1,ROUND(H10^Guida!$B$18*Guida!$F$11,0)) -> 14 | J10: =MAX(2,ROUND(I10*1.2,0)) -> 17 | K10: =IF(I10>=60,"Top",IF(I10>=30,"1a fascia",IF(I10>=15,"2a fascia",IF(I10>=7,"3a fascia",IF(I10>=3,"4a fascia","Scommessa"))))) -> 3a fascia | L10: Titolare | M10: Titolare confermato (2/2) | N10: - | O10: - | P10: 11 | Q10: 6.23 | R10: 5.18 | S10: 0 | T10: 1 | U10: 0/0 | V10: 1 | W10: 0 | X10: 2 | Y10: 6 | Z10: 5 | AA10: 0 | AB10: 0 | AC10: Napoli | AD10: No | AE10: =ROUND(IF(P10="",5.5,R10*MIN(1,P10/25)+5.5*(1-MIN(1,P10/25))),2) -> 5.36 | AF10: Svilar (ROM) | AG10: 3 | AH10: =RANK(H10,$H$4:$H$67) -> 7
A11: =RANK(B11,$B$4:$B$67) -> 8 | B11: =ROUND(Guida!$B$22*H11/Guida!$B$28+Guida!$B$23*MAX(0,MIN(1,(AE11-5.4)/1.6))+Guida!$B$24*0+Guida!$B$25*0,1) -> 27 | C11: Mandas | D11: Lazio | E11: Portiere | F11: 9 | G11: 10 | H11: 36 | I11: =MAX(1,ROUND(H11^Guida!$B$18*Guida!$F$11,0)) -> 12 | J11: =MAX(2,ROUND(I11*1.2,0)) -> 14 | K11: =IF(I11>=60,"Top",IF(I11>=30,"1a fascia",IF(I11>=15,"2a fascia",IF(I11>=7,"3a fascia",IF(I11>=3,"4a fascia","Scommessa"))))) -> 3a fascia | L11: Titolare | M11: Titolare confermato (2/2) | N11: - | O11: - | X11: 2 | Y11: 6.25 | Z11: 6.25 | AA11: 0 | AB11: 0 | AC11: Lazio | AD11: No | AE11: =ROUND(IF(P11="",5.5,R11*MIN(1,P11/25)+5.5*(1-MIN(1,P11/25))),2) -> 5.5 | AF11: Svilar (ROM) | AG11: 0 | AH11: =RANK(H11,$H$4:$H$67) -> 8
A12: =RANK(B12,$B$4:$B$67) -> 9 | B12: =ROUND(Guida!$B$22*H12/Guida!$B$28+Guida!$B$23*MAX(0,MIN(1,(AE12-5.4)/1.6))+Guida!$B$24*0+Guida!$B$25*0,1) -> 22.6 | C12: Skorupski | D12: Bologna | E12: Portiere | F12: 10 | G12: 10 | H12: 32 | I12: =MAX(1,ROUND(H12^Guida!$B$18*Guida!$F$11,0)) -> 11 | J12: =MAX(2,ROUND(I12*1.2,0)) -> 13 | K12: =IF(I12>=60,"Top",IF(I12>=30,"1a fascia",IF(I12>=15,"2a fascia",IF(I12>=7,"3a fascia",IF(I12>=3,"4a fascia","Scommessa"))))) -> 3a fascia | L12: Titolare | M12: Titolare confermato (2/2) | N12: - | O12: - | P12: 18 | Q12: 6.19 | R12: 5.28 | S12: 0 | T12: 0 | U12: 0/0 | V12: 1 | W12: 1 | X12: 2 | Y12: 5.5 | Z12: 4.5 | AA12: 0 | AB12: 0 | AC12: Bologna | AD12: No | AE12: =ROUND(IF(P12="",5.5,R12*MIN(1,P12/25)+5.5*(1-MIN(1,P12/25))),2) -> 5.34 | AF12: Carnesecchi (ATA) | AG12: 6 | AH12: =RANK(H12,$H$4:$H$67) -> 9
A13: =RANK(B13,$B$4:$B$67) -> 10 | B13: =ROUND(Guida!$B$22*H13/Guida!$B$28+Guida!$B$23*MAX(0,MIN(1,(AE13-5.4)/1.6))+Guida!$B$24*0+Guida!$B$25*0,1) -> 21.2 | C13: De Gea | D13: Fiorentina | E13: Portiere | F13: 13 | G13: 11 | H13: 30 | I13: =MAX(1,ROUND(H13^Guida!$B$18*Guida!$F$11,0)) -> 10 | J13: =MAX(2,ROUND(I13*1.2,0)) -> 12 | K13: =IF(I13>=60,"Top",IF(I13>=30,"1a fascia",IF(I13>=15,"2a fascia",IF(I13>=7,"3a fascia",IF(I13>=3,"4a fascia","Scommessa"))))) -> 3a fascia | L13: Titolare | M13: Titolare confermato (2/2) | N13: - | O13: - | P13: 37 | Q13: 6.24 | R13: 5 | S13: 0 | T13: 0 | U13: 0/0 | V13: 0 | W13: 0 | X13: 2 | Y13: 5.25 | Z13: 1.75 | AA13: 0 | AB13: 0 | AC13: Fiorentina | AD13: No | AE13: =ROUND(IF(P13="",5.5,R13*MIN(1,P13/25)+5.5*(1-MIN(1,P13/25))),2) -> 5 | AF13: Butez (COM) | AG13: 6 | AH13: =RANK(H13,$H$4:$H$67) -> 10
A14: =RANK(B14,$B$4:$B$67) -> 11 | B14: =ROUND(Guida!$B$22*H14/Guida!$B$28+Guida!$B$23*MAX(0,MIN(1,(AE14-5.4)/1.6))+Guida!$B$24*0+Guida!$B$25*0,1) -> 19.9 | C14: Perri | D14: Torino | E14: Portiere | F14: 9 | G14: 9 | H14: 26 | I14: =MAX(1,ROUND(H14^Guida!$B$18*Guida!$F$11,0)) -> 10 | J14: =MAX(2,ROUND(I14*1.2,0)) -> 12 | K14: =IF(I14>=60,"Top",IF(I14>=30,"1a fascia",IF(I14>=15,"2a fascia",IF(I14>=7,"3a fascia",IF(I14>=3,"4a fascia","Scommessa"))))) -> 3a fascia | L14: Titolare | M14: Nuovo - RISCHIA il posto (0/2) | N14: - | O14: - | X14: 0 | AC14: - | AD14: Si | AE14: =ROUND(IF(P14="",5.5,R14*MIN(1,P14/25)+5.5*(1-MIN(1,P14/25))),2) -> 5.5 | AF14: Vicario (JUV) | AG14: 0 | AH14: =RANK(H14,$H$4:$H$67) -> 12
A15: =RANK(B15,$B$4:$B$67) -> 12 | B15: =ROUND(Guida!$B$22*H15/Guida!$B$28+Guida!$B$23*MAX(0,MIN(1,(AE15-5.4)/1.6))+Guida!$B$24*0+Guida!$B$25*0,1) -> 19.8 | C15: Okoye | D15: Udinese | E15: Portiere | F15: 9 | G15: 9 | H15: 28 | I15: =MAX(1,ROUND(H15^Guida!$B$18*Guida!$F$11,0)) -> 10 | J15: =MAX(2,ROUND(I15*1.2,0)) -> 12 | K15: =IF(I15>=60,"Top",IF(I15>=30,"1a fascia",IF(I15>=15,"2a fascia",IF(I15>=7,"3a fascia",IF(I15>=3,"4a fascia","Scommessa"))))) -> 3a fascia | L15: Titolare | M15: Titolare confermato (2/2) | N15: - | O15: - | P15: 30 | Q15: 6.07 | R15: 5.08 | S15: 0 | T15: 1 | U15: 0/0 | V15: 1 | W15: 1 | X15: 2 | Y15: 6.25 | Z15: 4.75 | AA15: 0 | AB15: 0 | AC15: Udinese | AD15: No | AE15: =ROUND(IF(P15="",5.5,R15*MIN(1,P15/25)+5.5*(1-MIN(1,P15/25))),2) -> 5.08 | AF15: Maignan (MIL) | AG15: 7 | AH15: =RANK(H15,$H$4:$H$67) -> 11
A16: =RANK(B16,$B$4:$B$67) -> 13 | B16: =ROUND(Guida!$B$22*H16/Guida!$B$28+Guida!$B$23*MAX(0,MIN(1,(AE16-5.4)/1.6))+Guida!$B$24*0+Guida!$B$25*0,1) -> 19.2 | C16: Sanchez Ro. | D16: Como | E16: Portiere | F16: 8 | G16: 8 | H16: 25 | I16: =MAX(1,ROUND(H16^Guida!$B$18*Guida!$F$11,0)) -> 9 | J16: =MAX(2,ROUND(I16*1.2,0)) -> 11 | K16: =IF(I16>=60,"Top",IF(I16>=30,"1a fascia",IF(I16>=15,"2a fascia",IF(I16>=7,"3a fascia",IF(I16>=3,"4a fascia","Scommessa"))))) -> 3a fascia | L16: Ballottaggio | M16: Nuovo - In ballottaggio (0/2) | N16: - | O16: - | X16: 0 | AC16: - | AD16: Si | AE16: =ROUND(IF(P16="",5.5,R16*MIN(1,P16/25)+5.5*(1-MIN(1,P16/25))),2) -> 5.5 | AF16: De Gea (FIO) | AG16: 6 | AH16: =RANK(H16,$H$4:$H$67) -> 14
A17: =RANK(B17,$B$4:$B$67) -> 14 | B17: =ROUND(Guida!$B$22*H17/Guida!$B$28+Guida!$B$23*MAX(0,MIN(1,(AE17-5.4)/1.6))+Guida!$B$24*0+Guida!$B$25*0,1) -> 18.4 | C17: Falcone | D17: Lecce | E17: Portiere | F17: 8 | G17: 8 | H17: 26 | I17: =MAX(1,ROUND(H17^Guida!$B$18*Guida!$F$11,0)) -> 10 | J17: =MAX(2,ROUND(I17*1.2,0)) -> 12 | K17: =IF(I17>=60,"Top",IF(I17>=30,"1a fascia",IF(I17>=15,"2a fascia",IF(I17>=7,"3a fascia",IF(I17>=3,"4a fascia","Scommessa"))))) -> 3a fascia | L17: Titolare | M17: Titolare confermato (2/2) | N17: - | O17: - | P17: 38 | Q17: 6.41 | R17: 5.22 | S17: 0 | T17: 0 | U17: 0/0 | V17: 2 | W17: 0 | X17: 2 | Y17: 6.25 | Z17: 4.25 | AA17: 0 | AB17: 0 | AC17: Lecce | AD17: No | AE17: =ROUND(IF(P17="",5.5,R17*MIN(1,P17/25)+5.5*(1-MIN(1,P17/25))),2) -> 5.22 | AF17: Skorupski (BOL) | AG17: 6 | AH17: =RANK(H17,$H$4:$H$67) -> 12
A18: =RANK(B18,$B$4:$B$67) -> 15 | B18: =ROUND(Guida!$B$22*H18/Guida!$B$28+Guida!$B$23*MAX(0,MIN(1,(AE18-5.4)/1.6))+Guida!$B$24*0+Guida!$B$25*0,1) -> 17.6 | C18: Caprile | D18: Cagliari | E18: Portiere | F18: 9 | G18: 10 | H18: 25 | I18: =MAX(1,ROUND(H18^Guida!$B$18*Guida!$F$11,0)) -> 9 | J18: =MAX(2,ROUND(I18*1.2,0)) -> 11 | K18: =IF(I18>=60,"Top",IF(I18>=30,"1a fascia",IF(I18>=15,"2a fascia",IF(I18>=7,"3a fascia",IF(I18>=3,"4a fascia","Scommessa"))))) -> 3a fascia | L18: Titolare | M18: Titolare confermato (2/2) | N18: - | O18: - | P18: 38 | Q18: 6.29 | R18: 4.87 | S18: 0 | T18: 0 | U18: 0/0 | V18: 2 | W18: 0 | X18: 2 | Y18: 6.5 | Z18: 6 | AA18: 0 | AB18: 0 | AC18: Cagliari | AD18: No | AE18: =ROUND(IF(P18="",5.5,R18*MIN(1,P18/25)+5.5*(1-MIN(1,P18/25))),2) -> 4.87 | AF18: Carnesecchi (ATA) | AG18: 6 | AH18: =RANK(H18,$H$4:$H$67) -> 14
A19: =RANK(B19,$B$4:$B$67) -> 16 | B19: =ROUND(Guida!$B$22*H19/Guida!$B$28+Guida!$B$23*MAX(0,MIN(1,(AE19-5.4)/1.6))+Guida!$B$24*0+Guida!$B$25*0,1) -> 10.6 | C19: Bijlow | D19: Genoa | E19: Portiere | F19: 8 | G19: 8 | H19: 15 | I19: =MAX(1,ROUND(H19^Guida!$B$18*Guida!$F$11,0)) -> 7 | J19: =MAX(2,ROUND(I19*1.2,0)) -> 8 | K19: =IF(I19>=60,"Top",IF(I19>=30,"1a fascia",IF(I19>=15,"2a fascia",IF(I19>=7,"3a fascia",IF(I19>=3,"4a fascia","Scommessa"))))) -> 3a fascia | L19: Titolare | M19: Titolare confermato (2/2) | N19: - | O19: - | P19: 16 | Q19: 6.06 | R19: 4.78 | S19: 0 | T19: 0 | U19: 0/0 | V19: 1 | W19: 0 | X19: 2 | Y19: 5.5 | Z19: 4 | AA19: 0 | AB19: 0 | AC19: Genoa | AD19: No | AE19: =ROUND(IF(P19="",5.5,R19*MIN(1,P19/25)+5.5*(1-MIN(1,P19/25))),2) -> 5.04 | AF19: Maignan (MIL) | AG19: 7 | AH19: =RANK(H19,$H$4:$H$67) -> 16
A20: =RANK(B20,$B$4:$B$67) -> 16 | B20: =ROUND(Guida!$B$22*H20/Guida!$B$28+Guida!$B$23*MAX(0,MIN(1,(AE20-5.4)/1.6))+Guida!$B$24*0+Guida!$B$25*0,1) -> 10.6 | C20: Muric | D20: Sassuolo | E20: Portiere | F20: 7 | G20: 7 | H20: 15 | I20: =MAX(1,ROUND(H20^Guida!$B$18*Guida!$F$11,0)) -> 7 | J20: =MAX(2,ROUND(I20*1.2,0)) -> 8 | K20: =IF(I20>=60,"Top",IF(I20>=30,"1a fascia",IF(I20>=15,"2a fascia",IF(I20>=7,"3a fascia",IF(I20>=3,"4a fascia","Scommessa"))))) -> 3a fascia | L20: Titolare | M20: Titolare confermato (2/2) | N20: - | O20: - | P20: 32 | Q20: 6.08 | R20: 4.77 | S20: 0 | T20: 0 | U20: 0/0 | V20: 4 | W20: 0 | X20: 2 | Y20: 6.25 | Z20: 4.75 | AA20: 0 | AB20: 0 | AC20: Sassuolo | AD20: No | AE20: =ROUND(IF(P20="",5.5,R20*MIN(1,P20/25)+5.5*(1-MIN(1,P20/25))),2) -> 4.77 | AF20: Corvi (PAR) | AG20: 4 | AH20: =RANK(H20,$H$4:$H$67) -> 16
A21: =RANK(B21,$B$4:$B$67) -> 18 | B21: =ROUND(Guida!$B$22*H21/Guida!$B$28+Guida!$B$23*MAX(0,MIN(1,(AE21-5.4)/1.6))+Guida!$B$24*0+Guida!$B$25*0,1) -> 10 | C21: Palmisani | D21: Frosinone | E21: Portiere | F21: 4 | G21: 5 | H21: 12 | I21: =MAX(1,ROUND(H21^Guida!$B$18*Guida!$F$11,0)) -> 6 | J21: =MAX(2,ROUND(I21*1.2,0)) -> 7 | K21: =IF(I21>=60,"Top",IF(I21>=30,"1a fascia",IF(I21>=15,"2a fascia",IF(I21>=7,"3a fascia",IF(I21>=3,"4a fascia","Scommessa"))))) -> 4a fascia | L21: Titolare | M21: Nuovo - Titolare confermato (2/2) | N21: - | O21: - | X21: 2 | Y21: 6.25 | Z21: 5.75 | AA21: 0 | AB21: 0 | AC21: - | AD21: Si | AE21: =ROUND(IF(P21="",5.5,R21*MIN(1,P21/25)+5.5*(1-MIN(1,P21/25))),2) -> 5.5 | AF21: Butez (COM) | AG21: 6 | AH21: =RANK(H21,$H$4:$H$67) -> 18
A22: =RANK(B22,$B$4:$B$67) -> 19 | B22: =ROUND(Guida!$B$22*H22/Guida!$B$28+Guida!$B$23*MAX(0,MIN(1,(AE22-5.4)/1.6))+Guida!$B$24*0+Guida!$B$25*0,1) -> 9.3 | C22: Stankovic F. | D22: Venezia | E22: Portiere | F22: 6 | G22: 6 | H22: 11 | I22: =MAX(1,ROUND(H22^Guida!$B$18*Guida!$F$11,0)) -> 6 | J22: =MAX(2,ROUND(I22*1.2,0)) -> 7 | K22: =IF(I22>=60,"Top",IF(I22>=30,"1a fascia",IF(I22>=15,"2a fascia",IF(I22>=7,"3a fascia",IF(I22>=3,"4a fascia","Scommessa"))))) -> 4a fascia | L22: Titolare | M22: Nuovo - Titolare confermato (2/2) | N22: - | O22: - | X22: 2 | Y22: 6 | Z22: 4 | AA22: 0 | AB22: 0 | AC22: - | AD22: Si | AE22: =ROUND(IF(P22="",5.5,R22*MIN(1,P22/25)+5.5*(1-MIN(1,P22/25))),2) -> 5.5 | AF22: Caprile (CAG) | AG22: 6 | AH22: =RANK(H22,$H$4:$H$67) -> 19
A23: =RANK(B23,$B$4:$B$67) -> 20 | B23: =ROUND(Guida!$B$22*H23/Guida!$B$28+Guida!$B$23*MAX(0,MIN(1,(AE23-5.4)/1.6))+Guida!$B$24*0+Guida!$B$25*0,1) -> 8.6 | C23: Tornqvist | D23: Monza | E23: Portiere | F23: 1 | G23: 1 | H23: 10 | I23: =MAX(1,ROUND(H23^Guida!$B$18*Guida!$F$11,0)) -> 5 | J23: =MAX(2,ROUND(I23*1.2,0)) -> 6 | K23: =IF(I23>=60,"Top",IF(I23>=30,"1a fascia",IF(I23>=15,"2a fascia",IF(I23>=7,"3a fascia",IF(I23>=3,"4a fascia","Scommessa"))))) -> 4a fascia | L23: Ballottaggio | M23: Nuovo - In ballottaggio (0/2) | N23: - | O23: - | X23: 0 | AC23: - | AD23: Si | AE23: =ROUND(IF(P23="",5.5,R23*MIN(1,P23/25)+5.5*(1-MIN(1,P23/25))),2) -> 5.5 | AF23: Falcone (LEC) | AG23: 6 | AH23: =RANK(H23,$H$4:$H$67) -> 20
A24: =RANK(B24,$B$4:$B$67) -> 21 | B24: =ROUND(Guida!$B$22*H24/Guida!$B$28+Guida!$B$23*MAX(0,MIN(1,(AE24-5.4)/1.6))+Guida!$B$24*0+Guida!$B$25*0,1) -> 7.4 | C24: Milinkovic-Savic V. | D24: Napoli | E24: Portiere | F24: 5 | G24: 5 | H24: 5 | I24: =MAX(1,ROUND(H24^Guida!$B$18*Guida!$F$11,0)) -> 4 | J24: =MAX(2,ROUND(I24*1.2,0)) -> 5 | K24: =IF(I24>=60,"Top",IF(I24>=30,"1a fascia",IF(I24>=15,"2a fascia",IF(I24>=7,"3a fascia",IF(I24>=3,"4a fascia","Scommessa"))))) -> 4a fascia | L24: Ballottaggio | M24: In ballottaggio (0/2) | N24: - | O24: - | P24: 27 | Q24: 6.2 | R24: 5.65 | S24: 0 | T24: 0 | U24: 0/0 | V24: 0 | W24: 0 | X24: 0 | AC24: Napoli | AD24: No | AE24: =ROUND(IF(P24="",5.5,R24*MIN(1,P24/25)+5.5*(1-MIN(1,P24/25))),2) -> 5.65 | AF24: Skorupski (BOL) | AG24: 6 | AH24: =RANK(H24,$H$4:$H$67) -> 23
A25: =RANK(B25,$B$4:$B$67) -> 22 | B25: =ROUND(Guida!$B$22*H25/Guida!$B$28+Guida!$B$23*MAX(0,MIN(1,(AE25-5.4)/1.6))+Guida!$B$24*0+Guida!$B$25*0,1) -> 7.1 | C25: Corvi | D25: Parma | E25: Portiere | F25: 1 | G25: 2 | H25: 10 | I25: =MAX(1,ROUND(H25^Guida!$B$18*Guida!$F$11,0)) -> 5 | J25: =MAX(2,ROUND(I25*1.2,0)) -> 6 | K25: =IF(I25>=60,"Top",IF(I25>=30,"1a fascia",IF(I25>=15,"2a fascia",IF(I25>=7,"3a fascia",IF(I25>=3,"4a fascia","Scommessa"))))) -> 4a fascia | L25: Ballottaggio | M25: In ballottaggio (2/2) | N25: - | O25: - | P25: 17 | Q25: 6.18 | R25: 5.09 | S25: 0 | T25: 0 | U25: 0/0 | V25: 1 | W25: 0 | X25: 2 | Y25: 5.75 | Z25: 4.25 | AA25: 0 | AB25: 0 | AC25: Parma | AD25: No | AE25: =ROUND(IF(P25="",5.5,R25*MIN(1,P25/25)+5.5*(1-MIN(1,P25/25))),2) -> 5.22 | AF25: Falcone (LEC) | AG25: 4 | AH25: =RANK(H25,$H$4:$H$67) -> 20
A26: =RANK(B26,$B$4:$B$67) -> 23 | B26: =ROUND(Guida!$B$22*H26/Guida!$B$28+Guida!$B$23*MAX(0,MIN(1,(AE26-5.4)/1.6))+Guida!$B$24*0+Guida!$B$25*0,1) -> 6.5 | C26: Daffara | D26: Parma | E26: Portiere | F26: 7 | G26: 6 | H26: 7 | I26: =MAX(1,ROUND(H26^Guida!$B$18*Guida!$F$11,0)) -> 4 | J26: =MAX(2,ROUND(I26*1.2,0)) -> 5 | K26: =IF(I26>=60,"Top",IF(I26>=30,"1a fascia",IF(I26>=15,"2a fascia",IF(I26>=7,"3a fascia",IF(I26>=3,"4a fascia","Scommessa"))))) -> 4a fascia | L26: Titolare | M26: Nuovo - RISCHIA il posto (0/2) | N26: - | O26: - | X26: 0 | AC26: - | AD26: Si | AE26: =ROUND(IF(P26="",5.5,R26*MIN(1,P26/25)+5.5*(1-MIN(1,P26/25))),2) -> 5.5 | AF26: Falcone (LEC) | AG26: 4 | AH26: =RANK(H26,$H$4:$H$67) -> 22
A27: =RANK(B27,$B$4:$B$67) -> 24 | B27: =ROUND(Guida!$B$22*H27/Guida!$B$28+Guida!$B$23*MAX(0,MIN(1,(AE27-5.4)/1.6))+Guida!$B$24*0+Guida!$B$25*0,1) -> 5.1 | C27: Mascardi | D27: Torino | E27: Portiere | F27: 1 | G27: 1 | H27: 5 | I27: =MAX(1,ROUND(H27^Guida!$B$18*Guida!$F$11,0)) -> 4 | J27: =MAX(2,ROUND(I27*1.2,0)) -> 5 | K27: =IF(I27>=60,"Top",IF(I27>=30,"1a fascia",IF(I27>=15,"2a fascia",IF(I27>=7,"3a fascia",IF(I27>=3,"4a fascia","Scommessa"))))) -> 4a fascia | L27: Ballottaggio | M27: Nuovo - In ballottaggio (2/2) | N27: - | O27: - | X27: 2 | Y27: 5.75 | Z27: 3.75 | AA27: 0 | AB27: 0 | AC27: - | AD27: Si | AE27: =ROUND(IF(P27="",5.5,R27*MIN(1,P27/25)+5.5*(1-MIN(1,P27/25))),2) -> 5.5 | AF27: Falcone (LEC) | AG27: 7 | AH27: =RANK(H27,$H$4:$H$67) -> 23
A28: =RANK(B28,$B$4:$B$67) -> 24 | B28: =ROUND(Guida!$B$22*H28/Guida!$B$28+Guida!$B$23*MAX(0,MIN(1,(AE28-5.4)/1.6))+Guida!$B$24*0+Guida!$B$25*0,1) -> 5.1 | C28: Thiam | D28: Monza | E28: Portiere | F28: 5 | G28: 4 | H28: 5 | I28: =MAX(1,ROUND(H28^Guida!$B$18*Guida!$F$11,0)) -> 4 | J28: =MAX(2,ROUND(I28*1.2,0)) -> 5 | K28: =IF(I28>=60,"Top",IF(I28>=30,"1a fascia",IF(I28>=15,"2a fascia",IF(I28>=7,"3a fascia",IF(I28>=3,"4a fascia","Scommessa"))))) -> 4a fascia | L28: Titolare | M28: Nuovo - Rischia il posto (1/2) | N28: - | O28: - | X28: 1 | Y28: 4.5 | Z28: 1.5 | AA28: 0 | AB28: 0 | AC28: - | AD28: Si | AE28: =ROUND(IF(P28="",5.5,R28*MIN(1,P28/25)+5.5*(1-MIN(1,P28/25))),2) -> 5.5 | AF28: Falcone (LEC) | AG28: 6 | AH28: =RANK(H28,$H$4:$H$67) -> 23
A29: =RANK(B29,$B$4:$B$67) -> 26 | B29: =ROUND(Guida!$B$22*H29/Guida!$B$28+Guida!$B$23*MAX(0,MIN(1,(AE29-5.4)/1.6))+Guida!$B$24*0+Guida!$B$25*0,1) -> 3.5 | C29: Provedel | D29: Inter | E29: Portiere | F29: 2 | G29: 2 | H29: 5 | I29: =MAX(1,ROUND(H29^Guida!$B$18*Guida!$F$11,0)) -> 4 | J29: =MAX(2,ROUND(I29*1.2,0)) -> 5 | K29: =IF(I29>=60,"Top",IF(I29>=30,"1a fascia",IF(I29>=15,"2a fascia",IF(I29>=7,"3a fascia",IF(I29>=3,"4a fascia","Scommessa"))))) -> 4a fascia | L29: Ballottaggio | M29: Nuovo - In ballottaggio (0/2) | N29: - | O29: - | P29: 27 | Q29: 6.26 | R29: 5.35 | S29: 0 | T29: 0 | U29: 0/0 | V29: 1 | W29: 0 | X29: 0 | AC29: Lazio | AD29: Si | AE29: =ROUND(IF(P29="",5.5,R29*MIN(1,P29/25)+5.5*(1-MIN(1,P29/25))),2) -> 5.35 | AF29: Muric (SAS) | AG29: 4 | AH29: =RANK(H29,$H$4:$H$67) -> 23
A30: =RANK(B30,$B$4:$B$67) -> 27 | B30: =ROUND(Guida!$B$22*H30/Guida!$B$28+Guida!$B$23*MAX(0,MIN(1,(AE30-5.4)/1.6))+Guida!$B$24*0+Guida!$B$25*0,1) -> 2.9 | C30: Christensen O. | D30: Fiorentina | E30: Portiere | F30: 1 | G30: 1 | H30: 1 | I30: =MAX(1,ROUND(H30^Guida!$B$18*Guida!$F$11,0)) -> 1 | J30: =MAX(2,ROUND(I30*1.2,0)) -> 2 | K30: =IF(I30>=60,"Top",IF(I30>=30,"1a fascia",IF(I30>=15,"2a fascia",IF(I30>=7,"3a fascia",IF(I30>=3,"4a fascia","Scommessa"))))) -> Scommessa | L30: Ballottaggio | M30: In ballottaggio (0/2) | N30: - | O30: - | P30: 1 | Q30: 7.5 | R30: 6.5 | S30: 0 | T30: 0 | U30: 0/0 | V30: 0 | W30: 0 | X30: 0 | AC30: Fiorentina | AD30: No | AE30: =ROUND(IF(P30="",5.5,R30*MIN(1,P30/25)+5.5*(1-MIN(1,P30/25))),2) -> 5.54 | AF30: Caprile (CAG) | AG30: 6 | AH30: =RANK(H30,$H$4:$H$67) -> 27
A31: =RANK(B31,$B$4:$B$67) -> 27 | B31: =ROUND(Guida!$B$22*H31/Guida!$B$28+Guida!$B$23*MAX(0,MIN(1,(AE31-5.4)/1.6))+Guida!$B$24*0+Guida!$B$25*0,1) -> 2.9 | C31: Terracciano | D31: Milan | E31: Portiere | F31: 1 | G31: 1 | H31: 1 | I31: =MAX(1,ROUND(H31^Guida!$B$18*Guida!$F$11,0)) -> 1 | J31: =MAX(2,ROUND(I31*1.2,0)) -> 2 | K31: =IF(I31>=60,"Top",IF(I31>=30,"1a fascia",IF(I31>=15,"2a fascia",IF(I31>=7,"3a fascia",IF(I31>=3,"4a fascia","Scommessa"))))) -> Scommessa | L31: Ballottaggio | M31: In ballottaggio (0/2) | N31: - | O31: - | P31: 2 | Q31: 6 | R31: 6 | S31: 0 | T31: 0 | U31: 0/0 | V31: 0 | W31: 0 | X31: 0 | AC31: Milan | AD31: No | AE31: =ROUND(IF(P31="",5.5,R31*MIN(1,P31/25)+5.5*(1-MIN(1,P31/25))),2) -> 5.54 | AF31: Corvi (PAR) | AG31: 6 | AH31: =RANK(H31,$H$4:$H$67) -> 27
A32: =RANK(B32,$B$4:$B$67) -> 29 | B32: =ROUND(Guida!$B$22*H32/Guida!$B$28+Guida!$B$23*MAX(0,MIN(1,(AE32-5.4)/1.6))+Guida!$B$24*0+Guida!$B$25*0,1) -> 2.6 | C32: Pessina Mas. | D32: Bologna | E32: Portiere | F32: 1 | G32: 1 | H32: 1 | I32: =MAX(1,ROUND(H32^Guida!$B$18*Guida!$F$11,0)) -> 1 | J32: =MAX(2,ROUND(I32*1.2,0)) -> 2 | K32: =IF(I32>=60,"Top",IF(I32>=30,"1a fascia",IF(I32>=15,"2a fascia",IF(I32>=7,"3a fascia",IF(I32>=3,"4a fascia","Scommessa"))))) -> Scommessa | L32: Riserva | M32: Riserva (0/2) | N32: - | O32: - | P32: 4 | Q32: 6.12 | R32: 5.62 | S32: 0 | T32: 0 | U32: 0/0 | V32: 0 | W32: 0 | X32: 0 | AC32: Bologna | AD32: No | AE32: =ROUND(IF(P32="",5.5,R32*MIN(1,P32/25)+5.5*(1-MIN(1,P32/25))),2) -> 5.52 | AF32: Muric (SAS) | AG32: 6 | AH32: =RANK(H32,$H$4:$H$67) -> 27
A33: =RANK(B33,$B$4:$B$67) -> 30 | B33: =ROUND(Guida!$B$22*H33/Guida!$B$28+Guida!$B$23*MAX(0,MIN(1,(AE33-5.4)/1.6))+Guida!$B$24*0+Guida!$B$25*0,1) -> 2.3 | C33: Bleve | D33: Lecce | E33: Portiere | F33: 1 | G33: 1 | H33: 1 | I33: =MAX(1,ROUND(H33^Guida!$B$18*Guida!$F$11,0)) -> 1 | J33: =MAX(2,ROUND(I33*1.2,0)) -> 2 | K33: =IF(I33>=60,"Top",IF(I33>=30,"1a fascia",IF(I33>=15,"2a fascia",IF(I33>=7,"3a fascia",IF(I33>=3,"4a fascia","Scommessa"))))) -> Scommessa | L33: Riserva | M33: Nuovo - Riserva (0/2) | N33: - | O33: - | X33: 0 | AC33: - | AD33: Si | AE33: =ROUND(IF(P33="",5.5,R33*MIN(1,P33/25)+5.5*(1-MIN(1,P33/25))),2) -> 5.5 | AF33: Corvi (PAR) | AG33: 4 | AH33: =RANK(H33,$H$4:$H$67) -> 27
A34: =RANK(B34,$B$4:$B$67) -> 30 | B34: =ROUND(Guida!$B$22*H34/Guida!$B$28+Guida!$B$23*MAX(0,MIN(1,(AE34-5.4)/1.6))+Guida!$B$24*0+Guida!$B$25*0,1) -> 2.3 | C34: Contini | D34: Napoli | E34: Portiere | F34: 1 | G34: 1 | H34: 1 | I34: =MAX(1,ROUND(H34^Guida!$B$18*Guida!$F$11,0)) -> 1 | J34: =MAX(2,ROUND(I34*1.2,0)) -> 2 | K34: =IF(I34>=60,"Top",IF(I34>=30,"1a fascia",IF(I34>=15,"2a fascia",IF(I34>=7,"3a fascia",IF(I34>=3,"4a fascia","Scommessa"))))) -> Scommessa | L34: Riserva | M34: Riserva (0/2) | N34: - | O34: - | X34: 0 | AC34: Napoli | AD34: No | AE34: =ROUND(IF(P34="",5.5,R34*MIN(1,P34/25)+5.5*(1-MIN(1,P34/25))),2) -> 5.5 | AF34: Stankovic F. (VEN) | AG34: 7 | AH34: =RANK(H34,$H$4:$H$67) -> 27
A35: =RANK(B35,$B$4:$B$67) -> 30 | B35: =ROUND(Guida!$B$22*H35/Guida!$B$28+Guida!$B$23*MAX(0,MIN(1,(AE35-5.4)/1.6))+Guida!$B$24*0+Guida!$B$25*0,1) -> 2.3 | C35: De Marzi | D35: Roma | E35: Portiere | F35: 1 | G35: 1 | H35: 1 | I35: =MAX(1,ROUND(H35^Guida!$B$18*Guida!$F$11,0)) -> 1 | J35: =MAX(2,ROUND(I35*1.2,0)) -> 2 | K35: =IF(I35>=60,"Top",IF(I35>=30,"1a fascia",IF(I35>=15,"2a fascia",IF(I35>=7,"3a fascia",IF(I35>=3,"4a fascia","Scommessa"))))) -> Scommessa | L35: Ballottaggio | M35: Nuovo - In ballottaggio (0/2) | N35: - | O35: - | X35: 0 | AC35: - | AD35: Si | AE35: =ROUND(IF(P35="",5.5,R35*MIN(1,P35/25)+5.5*(1-MIN(1,P35/25))),2) -> 5.5 | AF35: Milinkovic-Savic V. (NAP) | AG35: 3 | AH35: =RANK(H35,$H$4:$H$67) -> 27
A36: =RANK(B36,$B$4:$B$67) -> 30 | B36: =ROUND(Guida!$B$22*H36/Guida!$B$28+Guida!$B$23*MAX(0,MIN(1,(AE36-5.4)/1.6))+Guida!$B$24*0+Guida!$B$25*0,1) -> 2.3 | C36: Desplanches | D36: Frosinone | E36: Portiere | F36: 2 | G36: 2 | H36: 1 | I36: =MAX(1,ROUND(H36^Guida!$B$18*Guida!$F$11,0)) -> 1 | J36: =MAX(2,ROUND(I36*1.2,0)) -> 2 | K36: =IF(I36>=60,"Top",IF(I36>=30,"1a fascia",IF(I36>=15,"2a fascia",IF(I36>=7,"3a fascia",IF(I36>=3,"4a fascia","Scommessa"))))) -> Scommessa | L36: Ballottaggio | M36: Nuovo - In ballottaggio (0/2) | N36: - | O36: - | X36: 0 | AC36: - | AD36: Si | AE36: =ROUND(IF(P36="",5.5,R36*MIN(1,P36/25)+5.5*(1-MIN(1,P36/25))),2) -> 5.5 | AF36: Milinkovic-Savic V. (NAP) | AG36: 6 | AH36: =RANK(H36,$H$4:$H$67) -> 27
A37: =RANK(B37,$B$4:$B$67) -> 30 | B37: =ROUND(Guida!$B$22*H37/Guida!$B$28+Guida!$B$23*MAX(0,MIN(1,(AE37-5.4)/1.6))+Guida!$B$24*0+Guida!$B$25*0,1) -> 2.3 | C37: Ghidotti | D37: Parma | E37: Portiere | F37: 1 | G37: 1 | H37: 1 | I37: =MAX(1,ROUND(H37^Guida!$B$18*Guida!$F$11,0)) -> 1 | J37: =MAX(2,ROUND(I37*1.2,0)) -> 2 | K37: =IF(I37>=60,"Top",IF(I37>=30,"1a fascia",IF(I37>=15,"2a fascia",IF(I37>=7,"3a fascia",IF(I37>=3,"4a fascia","Scommessa"))))) -> Scommessa | L37: Riserva | M37: Nuovo - Riserva (0/2) | N37: - | O37: - | X37: 0 | AC37: - | AD37: Si | AE37: =ROUND(IF(P37="",5.5,R37*MIN(1,P37/25)+5.5*(1-MIN(1,P37/25))),2) -> 5.5 | AF37: Mascardi (TOR) | AG37: 9 | AH37: =RANK(H37,$H$4:$H$67) -> 27
A38: =RANK(B38,$B$4:$B$67) -> 30 | B38: =ROUND(Guida!$B$22*H38/Guida!$B$28+Guida!$B$23*MAX(0,MIN(1,(AE38-5.4)/1.6))+Guida!$B$24*0+Guida!$B$25*0,1) -> 2.3 | C38: Gollini | D38: Roma | E38: Portiere | F38: 1 | G38: 1 | H38: 1 | I38: =MAX(1,ROUND(H38^Guida!$B$18*Guida!$F$11,0)) -> 1 | J38: =MAX(2,ROUND(I38*1.2,0)) -> 2 | K38: =IF(I38>=60,"Top",IF(I38>=30,"1a fascia",IF(I38>=15,"2a fascia",IF(I38>=7,"3a fascia",IF(I38>=3,"4a fascia","Scommessa"))))) -> Scommessa | L38: Riserva | M38: Riserva (0/2) | N38: - | O38: - | X38: 0 | AC38: Roma | AD38: No | AE38: =ROUND(IF(P38="",5.5,R38*MIN(1,P38/25)+5.5*(1-MIN(1,P38/25))),2) -> 5.5 | AF38: Daffara (PAR) | AG38: 12 | AH38: =RANK(H38,$H$4:$H$67) -> 27
A39: =RANK(B39,$B$4:$B$67) -> 30 | B39: =ROUND(Guida!$B$22*H39/Guida!$B$28+Guida!$B$23*MAX(0,MIN(1,(AE39-5.4)/1.6))+Guida!$B$24*0+Guida!$B$25*0,1) -> 2.3 | C39: Grabara | D39: Juventus | E39: Portiere | F39: 1 | G39: 1 | H39: 1 | I39: =MAX(1,ROUND(H39^Guida!$B$18*Guida!$F$11,0)) -> 1 | J39: =MAX(2,ROUND(I39*1.2,0)) -> 2 | K39: =IF(I39>=60,"Top",IF(I39>=30,"1a fascia",IF(I39>=15,"2a fascia",IF(I39>=7,"3a fascia",IF(I39>=3,"4a fascia","Scommessa"))))) -> Scommessa | L39: Riserva | M39: Nuovo - Riserva (0/2) | N39: - | O39: - | X39: 0 | AC39: - | AD39: Si | AE39: =ROUND(IF(P39="",5.5,R39*MIN(1,P39/25)+5.5*(1-MIN(1,P39/25))),2) -> 5.5 | AF39: Mascardi (TOR) | AG39: 0 | AH39: =RANK(H39,$H$4:$H$67) -> 27
A40: =RANK(B40,$B$4:$B$67) -> 30 | B40: =ROUND(Guida!$B$22*H40/Guida!$B$28+Guida!$B$23*MAX(0,MIN(1,(AE40-5.4)/1.6))+Guida!$B$24*0+Guida!$B$25*0,1) -> 2.3 | C40: Grandi | D40: Venezia | E40: Portiere | F40: 1 | G40: 1 | H40: 1 | I40: =MAX(1,ROUND(H40^Guida!$B$18*Guida!$F$11,0)) -> 1 | J40: =MAX(2,ROUND(I40*1.2,0)) -> 2 | K40: =IF(I40>=60,"Top",IF(I40>=30,"1a fascia",IF(I40>=15,"2a fascia",IF(I40>=7,"3a fascia",IF(I40>=3,"4a fascia","Scommessa"))))) -> Scommessa | L40: Ballottaggio | M40: Nuovo - In ballottaggio (0/2) | N40: - | O40: - | X40: 0 | AC40: - | AD40: Si | AE40: =ROUND(IF(P40="",5.5,R40*MIN(1,P40/25)+5.5*(1-MIN(1,P40/25))),2) -> 5.5 | AF40: Caprile (CAG) | AG40: 6 | AH40: =RANK(H40,$H$4:$H$67) -> 27
A41: =RANK(B41,$B$4:$B$67) -> 30 | B41: =ROUND(Guida!$B$22*H41/Guida!$B$28+Guida!$B$23*MAX(0,MIN(1,(AE41-5.4)/1.6))+Guida!$B$24*0+Guida!$B$25*0,1) -> 2.3 | C41: Happonen | D41: Bologna | E41: Portiere | F41: 1 | G41: 1 | H41: 1 | I41: =MAX(1,ROUND(H41^Guida!$B$18*Guida!$F$11,0)) -> 1 | J41: =MAX(2,ROUND(I41*1.2,0)) -> 2 | K41: =IF(I41>=60,"Top",IF(I41>=30,"1a fascia",IF(I41>=15,"2a fascia",IF(I41>=7,"3a fascia",IF(I41>=3,"4a fascia","Scommessa"))))) -> Scommessa | L41: Ballottaggio | M41: Nuovo - In ballottaggio (0/2) | N41: - | O41: - | X41: 0 | AC41: - | AD41: Si | AE41: =ROUND(IF(P41="",5.5,R41*MIN(1,P41/25)+5.5*(1-MIN(1,P41/25))),2) -> 5.5 | AF41: Carnesecchi (ATA) | AG41: 6 | AH41: =RANK(H41,$H$4:$H$67) -> 27
A42: =RANK(B42,$B$4:$B$67) -> 30 | B42: =ROUND(Guida!$B$22*H42/Guida!$B$28+Guida!$B$23*MAX(0,MIN(1,(AE42-5.4)/1.6))+Guida!$B$24*0+Guida!$B$25*0,1) -> 2.3 | C42: Lezzerini | D42: Fiorentina | E42: Portiere | F42: 1 | G42: 1 | H42: 1 | I42: =MAX(1,ROUND(H42^Guida!$B$18*Guida!$F$11,0)) -> 1 | J42: =MAX(2,ROUND(I42*1.2,0)) -> 2 | K42: =IF(I42>=60,"Top",IF(I42>=30,"1a fascia",IF(I42>=15,"2a fascia",IF(I42>=7,"3a fascia",IF(I42>=3,"4a fascia","Scommessa"))))) -> Scommessa | L42: Riserva | M42: Riserva (0/2) | N42: - | O42: - | X42: 0 | AC42: Fiorentina | AD42: No | AE42: =ROUND(IF(P42="",5.5,R42*MIN(1,P42/25)+5.5*(1-MIN(1,P42/25))),2) -> 5.5 | AF42: Butez (COM) | AG42: 6 | AH42: =RANK(H42,$H$4:$H$67) -> 27
A43: =RANK(B43,$B$4:$B$67) -> 30 | B43: =ROUND(Guida!$B$22*H43/Guida!$B$28+Guida!$B$23*MAX(0,MIN(1,(AE43-5.4)/1.6))+Guida!$B$24*0+Guida!$B$25*0,1) -> 2.3 | C43: Lolic | D43: Frosinone | E43: Portiere | F43: 1 | G43: 1 | H43: 1 | I43: =MAX(1,ROUND(H43^Guida!$B$18*Guida!$F$11,0)) -> 1 | J43: =MAX(2,ROUND(I43*1.2,0)) -> 2 | K43: =IF(I43>=60,"Top",IF(I43>=30,"1a fascia",IF(I43>=15,"2a fascia",IF(I43>=7,"3a fascia",IF(I43>=3,"4a fascia","Scommessa"))))) -> Scommessa | L43: Riserva | M43: Nuovo - Riserva (0/2) | N43: - | O43: - | X43: 0 | AC43: - | AD43: Si | AE43: =ROUND(IF(P43="",5.5,R43*MIN(1,P43/25)+5.5*(1-MIN(1,P43/25))),2) -> 5.5 | AF43: Carnesecchi (ATA) | AG43: 5 | AH43: =RANK(H43,$H$4:$H$67) -> 27
A44: =RANK(B44,$B$4:$B$67) -> 30 | B44: =ROUND(Guida!$B$22*H44/Guida!$B$28+Guida!$B$23*MAX(0,MIN(1,(AE44-5.4)/1.6))+Guida!$B$24*0+Guida!$B$25*0,1) -> 2.3 | C44: Mrozek | D44: Udinese | E44: Portiere | F44: 1 | G44: 1 | H44: 1 | I44: =MAX(1,ROUND(H44^Guida!$B$18*Guida!$F$11,0)) -> 1 | J44: =MAX(2,ROUND(I44*1.2,0)) -> 2 | K44: =IF(I44>=60,"Top",IF(I44>=30,"1a fascia",IF(I44>=15,"2a fascia",IF(I44>=7,"3a fascia",IF(I44>=3,"4a fascia","Scommessa"))))) -> Scommessa | L44: Riserva | M44: Nuovo - Riserva (0/2) | N44: - | O44: - | X44: 0 | AC44: - | AD44: Si | AE44: =ROUND(IF(P44="",5.5,R44*MIN(1,P44/25)+5.5*(1-MIN(1,P44/25))),2) -> 5.5 | AF44: Maignan (MIL) | AG44: 7 | AH44: =RANK(H44,$H$4:$H$67) -> 27
... A59: =RANK(B59,$B$4:$B$67) -> 30 | B59: =ROUND(Guida!$B$22*H59/Guida!$B$28+Guida!$B$23*MAX(0,MIN(1,(AE59-5.4)/1.6))+Guida!$B$24*0+Guida!$B$25*0,1) -> 2.3 | C59: Vigorito | D59: Como | E59: Portiere | F59: 1 | G59: 1 | H59: 1 | I59: =MAX(1,ROUND(H59^Guida!$B$18*Guida!$F$11,0)) -> 1 | J59: =MAX(2,ROUND(I59*1.2,0)) -> 2 | K59: =IF(I59>=60,"Top",IF(I59>=30,"1a fascia",IF(I59>=15,"2a fascia",IF(I59>=7,"3a fascia",IF(I59>=3,"4a fascia","Scommessa"))))) -> Scommessa | L59: Riserva | M59: Riserva (0/2) | N59: - | O59: - | X59: 0 | AC59: Como | AD59: No | AE59: =ROUND(IF(P59="",5.5,R59*MIN(1,P59/25)+5.5*(1-MIN(1,P59/25))),2) -> 5.5 | AF59: De Gea (FIO) | AG59: 6 | AH59: =RANK(H59,$H$4:$H$67) -> 27
A60: =RANK(B60,$B$4:$B$67) -> 57 | B60: =ROUND(Guida!$B$22*H60/Guida!$B$28+Guida!$B$23*MAX(0,MIN(1,(AE60-5.4)/1.6))+Guida!$B$24*0+Guida!$B$25*0,1) -> 2 | C60: Di Gennaro | D60: Inter | E60: Portiere | F60: 1 | G60: 1 | H60: 1 | I60: =MAX(1,ROUND(H60^Guida!$B$18*Guida!$F$11,0)) -> 1 | J60: =MAX(2,ROUND(I60*1.2,0)) -> 2 | K60: =IF(I60>=60,"Top",IF(I60>=30,"1a fascia",IF(I60>=15,"2a fascia",IF(I60>=7,"3a fascia",IF(I60>=3,"4a fascia","Scommessa"))))) -> Scommessa | L60: Riserva | M60: Riserva (0/2) | N60: - | O60: - | P60: 1 | Q60: 6 | R60: 5 | S60: 0 | T60: 0 | U60: 0/0 | V60: 0 | W60: 0 | X60: 0 | AC60: Inter | AD60: No | AE60: =ROUND(IF(P60="",5.5,R60*MIN(1,P60/25)+5.5*(1-MIN(1,P60/25))),2) -> 5.48 | AF60: Maignan (MIL) | AG60: 0 | AH60: =RANK(H60,$H$4:$H$67) -> 27
A61: =RANK(B61,$B$4:$B$67) -> 57 | B61: =ROUND(Guida!$B$22*H61/Guida!$B$28+Guida!$B$23*MAX(0,MIN(1,(AE61-5.4)/1.6))+Guida!$B$24*0+Guida!$B$25*0,1) -> 2 | C61: Padelli | D61: Udinese | E61: Portiere | F61: 1 | G61: 1 | H61: 1 | I61: =MAX(1,ROUND(H61^Guida!$B$18*Guida!$F$11,0)) -> 1 | J61: =MAX(2,ROUND(I61*1.2,0)) -> 2 | K61: =IF(I61>=60,"Top",IF(I61>=30,"1a fascia",IF(I61>=15,"2a fascia",IF(I61>=7,"3a fascia",IF(I61>=3,"4a fascia","Scommessa"))))) -> Scommessa | L61: Ballottaggio | M61: In ballottaggio (0/2) | N61: - | O61: - | P61: 2 | Q61: 6.25 | R61: 5.25 | S61: 0 | T61: 0 | U61: 0/0 | V61: 0 | W61: 0 | X61: 0 | AC61: Udinese | AD61: No | AE61: =ROUND(IF(P61="",5.5,R61*MIN(1,P61/25)+5.5*(1-MIN(1,P61/25))),2) -> 5.48 | AF61: Maignan (MIL) | AG61: 7 | AH61: =RANK(H61,$H$4:$H$67) -> 27
A62: =RANK(B62,$B$4:$B$67) -> 59 | B62: =ROUND(Guida!$B$22*H62/Guida!$B$28+Guida!$B$23*MAX(0,MIN(1,(AE62-5.4)/1.6))+Guida!$B$24*0+Guida!$B$25*0,1) -> 1.6 | C62: Sportiello | D62: Atalanta | E62: Portiere | F62: 1 | G62: 1 | H62: 1 | I62: =MAX(1,ROUND(H62^Guida!$B$18*Guida!$F$11,0)) -> 1 | J62: =MAX(2,ROUND(I62*1.2,0)) -> 2 | K62: =IF(I62>=60,"Top",IF(I62>=30,"1a fascia",IF(I62>=15,"2a fascia",IF(I62>=7,"3a fascia",IF(I62>=3,"4a fascia","Scommessa"))))) -> Scommessa | L62: Ballottaggio | M62: In ballottaggio (0/2) | N62: - | O62: - | P62: 1 | Q62: 5.5 | R62: 4.5 | S62: 0 | T62: 0 | U62: 0/0 | V62: 0 | W62: 0 | X62: 0 | AC62: Atalanta | AD62: No | AE62: =ROUND(IF(P62="",5.5,R62*MIN(1,P62/25)+5.5*(1-MIN(1,P62/25))),2) -> 5.46 | AF62: Palmisani (FRO) | AG62: 5 | AH62: =RANK(H62,$H$4:$H$67) -> 27
A63: =RANK(B63,$B$4:$B$67) -> 60 | B63: =ROUND(Guida!$B$22*H63/Guida!$B$28+Guida!$B$23*MAX(0,MIN(1,(AE63-5.4)/1.6))+Guida!$B$24*0+Guida!$B$25*0,1) -> 0.7 | C63: Montipò | D63: Venezia | E63: Portiere | F63: 1 | G63: 1 | H63: 1 | I63: =MAX(1,ROUND(H63^Guida!$B$18*Guida!$F$11,0)) -> 1 | J63: =MAX(2,ROUND(I63*1.2,0)) -> 2 | K63: =IF(I63>=60,"Top",IF(I63>=30,"1a fascia",IF(I63>=15,"2a fascia",IF(I63>=7,"3a fascia",IF(I63>=3,"4a fascia","Scommessa"))))) -> Scommessa | L63: Riserva | M63: Nuovo - Riserva (0/2) | N63: - | O63: - | P63: 35 | Q63: 6.2 | R63: 4.94 | S63: 0 | T63: 1 | U63: 0/0 | V63: 0 | W63: 0 | X63: 0 | AC63: Verona | AD63: Si | AE63: =ROUND(IF(P63="",5.5,R63*MIN(1,P63/25)+5.5*(1-MIN(1,P63/25))),2) -> 4.94 | AF63: Caprile (CAG) | AG63: 6 | AH63: =RANK(H63,$H$4:$H$67) -> 27
A64: =RANK(B64,$B$4:$B$67) -> 60 | B64: =ROUND(Guida!$B$22*H64/Guida!$B$28+Guida!$B$23*MAX(0,MIN(1,(AE64-5.4)/1.6))+Guida!$B$24*0+Guida!$B$25*0,1) -> 0.7 | C64: Motta | D64: Lazio | E64: Portiere | F64: 1 | G64: 1 | H64: 1 | I64: =MAX(1,ROUND(H64^Guida!$B$18*Guida!$F$11,0)) -> 1 | J64: =MAX(2,ROUND(I64*1.2,0)) -> 2 | K64: =IF(I64>=60,"Top",IF(I64>=30,"1a fascia",IF(I64>=15,"2a fascia",IF(I64>=7,"3a fascia",IF(I64>=3,"4a fascia","Scommessa"))))) -> Scommessa | L64: Ballottaggio | M64: In ballottaggio (0/2) | N64: - | O64: - | P64: 9 | Q64: 6 | R64: 5.17 | S64: 0 | T64: 0 | U64: 0/0 | V64: 1 | W64: 0 | X64: 0 | AC64: Lazio | AD64: No | AE64: =ROUND(IF(P64="",5.5,R64*MIN(1,P64/25)+5.5*(1-MIN(1,P64/25))),2) -> 5.38 | AF64: Svilar (ROM) | AG64: 0 | AH64: =RANK(H64,$H$4:$H$67) -> 27
A65: =RANK(B65,$B$4:$B$67) -> 60 | B65: =ROUND(Guida!$B$22*H65/Guida!$B$28+Guida!$B$23*MAX(0,MIN(1,(AE65-5.4)/1.6))+Guida!$B$24*0+Guida!$B$25*0,1) -> 0.7 | C65: Paleari | D65: Torino | E65: Portiere | F65: 1 | G65: 1 | H65: 1 | I65: =MAX(1,ROUND(H65^Guida!$B$18*Guida!$F$11,0)) -> 1 | J65: =MAX(2,ROUND(I65*1.2,0)) -> 2 | K65: =IF(I65>=60,"Top",IF(I65>=30,"1a fascia",IF(I65>=15,"2a fascia",IF(I65>=7,"3a fascia",IF(I65>=3,"4a fascia","Scommessa"))))) -> Scommessa | L65: Riserva | M65: Riserva (0/2) | N65: - | O65: - | P65: 29 | Q65: 6.09 | R65: 4.52 | S65: 0 | T65: 0 | U65: 0/0 | V65: 1 | W65: 0 | X65: 0 | AC65: Torino | AD65: No | AE65: =ROUND(IF(P65="",5.5,R65*MIN(1,P65/25)+5.5*(1-MIN(1,P65/25))),2) -> 4.52 | AF65: Vicario (JUV) | AG65: 0 | AH65: =RANK(H65,$H$4:$H$67) -> 27
A66: =RANK(B66,$B$4:$B$67) -> 60 | B66: =ROUND(Guida!$B$22*H66/Guida!$B$28+Guida!$B$23*MAX(0,MIN(1,(AE66-5.4)/1.6))+Guida!$B$24*0+Guida!$B$25*0,1) -> 0.7 | C66: Sommariva | D66: Genoa | E66: Portiere | F66: 1 | G66: 1 | H66: 1 | I66: =MAX(1,ROUND(H66^Guida!$B$18*Guida!$F$11,0)) -> 1 | J66: =MAX(2,ROUND(I66*1.2,0)) -> 2 | K66: =IF(I66>=60,"Top",IF(I66>=30,"1a fascia",IF(I66>=15,"2a fascia",IF(I66>=7,"3a fascia",IF(I66>=3,"4a fascia","Scommessa"))))) -> Scommessa | L66: Ballottaggio | M66: In ballottaggio (0/2) | N66: - | O66: - | P66: 2 | Q66: 5.75 | R66: 3.75 | S66: 0 | T66: 0 | U66: 0/0 | V66: 0 | W66: 0 | X66: 0 | AC66: Genoa | AD66: No | AE66: =ROUND(IF(P66="",5.5,R66*MIN(1,P66/25)+5.5*(1-MIN(1,P66/25))),2) -> 5.36 | AF66: Vicario (JUV) | AG66: 5 | AH66: =RANK(H66,$H$4:$H$67) -> 27
A67: =RANK(B67,$B$4:$B$67) -> 60 | B67: =ROUND(Guida!$B$22*H67/Guida!$B$28+Guida!$B$23*MAX(0,MIN(1,(AE67-5.4)/1.6))+Guida!$B$24*0+Guida!$B$25*0,1) -> 0.7 | C67: Turati | D67: Sassuolo | E67: Portiere | F67: 1 | G67: 1 | H67: 1 | I67: =MAX(1,ROUND(H67^Guida!$B$18*Guida!$F$11,0)) -> 1 | J67: =MAX(2,ROUND(I67*1.2,0)) -> 2 | K67: =IF(I67>=60,"Top",IF(I67>=30,"1a fascia",IF(I67>=15,"2a fascia",IF(I67>=7,"3a fascia",IF(I67>=3,"4a fascia","Scommessa"))))) -> Scommessa | L67: Riserva | M67: Riserva (0/2) | N67: - | O67: - | P67: 6 | Q67: 6.17 | R67: 5 | S67: 0 | T67: 0 | U67: 0/0 | V67: 0 | W67: 0 | X67: 0 | AC67: Sassuolo | AD67: No | AE67: =ROUND(IF(P67="",5.5,R67*MIN(1,P67/25)+5.5*(1-MIN(1,P67/25))),2) -> 5.38 | AF67: Martinez Jo. (INT) | AG67: 4 | AH67: =RANK(H67,$H$4:$H$67) -> 27
A69: NOTA (colonna M): rosso = infortunato, giallo = in dubbio per la prossima giornata, arancione = titolare sulla carta ma zero presenze nelle prime due giornate (rischia il posto), verde = titolare confermato con 2 presenze su 2. 'Nuovo' segnala chi cambia squadra o arriva da fuori Serie A. Il dettaglio dell'infortunio e nell'ultima colonna. Indice = peso FVM x (FVM / FVM max di ruolo) + peso rendimento x fantamedia ponderata normalizzata + peso rigorista + peso calci piazzati; i pesi si cambiano nel foglio Guida (B22:B25). Fonte: Fantacalcio.it, quotazioni, statistiche e indisponibili al 01/09/2026 (2 giornate giocate).

Sheet Difensori
A1: DIFENSORI - Listone Fantacalcio Classic 2026/27
A2: 189 giocatori, solo quelli presenti nelle rose ufficiali di Serie A 2026/27. Ordinati per indice di priorita. Colonna NOTA: infortuni, rischio titolarita e nuovi acquisti (dati al 01/09/2026, dopo 2 giornate).
A3: Prio | B3: Indice | C3: Giocatore | D3: Squadra | E3: Ruolo Mantra | F3: Qt.I | G3: Qt.A | H3: FVM | I3: Prezzo consigliato | J3: Prezzo max | K3: Fascia | L3: Gerarchia stimata | M3: NOTA | N3: Rigorista | O3: Calci piazzati | P3: PG 25/26 | Q3: MV 25/26 | R3: FM 25/26 | S3: Gol 25/26 | T3: Assist 25/26 | U3: Rig. segnati 25/26 | V3: Amm. 25/26 | W3: Esp. 25/26 | X3: PG 26/27 (su 2) | Y3: MV 26/27 | Z3: FM 26/27 | AA3: Gol 26/27 | AB3: Assist 26/27 | AC3: Squadra 25/26 | AD3: Nuovo/Trasf. | AE3: FM ponderata | AF3: Miglior abbinamento (calendario) | AG3: Trasferte in comune | AH3: Rank FVM di ruolo | AI3: Dettaglio infortunio / stato
A4: =RANK(B4,$B$4:$B$192) -> 1 | B4: =ROUND(Guida!$B$22*H4/Guida!$B$29+Guida!$B$23*MAX(0,MIN(1,(AE4-5.4)/1.6))+Guida!$B$24*0+Guida!$B$25*0.6,1) -> 88 | C4: Dimarco | D4: Inter | E4: Esterno basso / Esterno alto | F4: 32 | G4: 31 | H4: 240 | I4: =MAX(1,ROUND(H4^Guida!$B$18*Guida!$F$12,0)) -> 34 | J4: =MAX(2,ROUND(I4*1.2,0)) -> 41 | K4: =IF(I4>=60,"Top",IF(I4>=30,"1a fascia",IF(I4>=15,"2a fascia",IF(I4>=7,"3a fascia",IF(I4>=3,"4a fascia","Scommessa"))))) -> 1a fascia | L4: Titolare | M4: Titolare confermato (2/2) | N4: - | O4: 2o | P4: 35 | Q4: 6.6 | R4: 7.64 | S4: 7 | T4: 17 | U4: 0/0 | V4: 3 | W4: 0 | X4: 2 | Y4: 6.25 | Z4: 6.25 | AA4: 0 | AB4: 0 | AC4: Inter | AD4: No | AE4: =ROUND(IF(P4="",5.5,R4*MIN(1,P4/25)+5.5*(1-MIN(1,P4/25))),2) -> 7.64 | AF4: Pavlovic (MIL) | AG4: 0 | AH4: =RANK(H4,$H$4:$H$192) -> 1
A5: =RANK(B5,$B$4:$B$192) -> 2 | B5: =ROUND(Guida!$B$22*H5/Guida!$B$29+Guida!$B$23*MAX(0,MIN(1,(AE5-5.4)/1.6))+Guida!$B$24*0+Guida!$B$25*0,1) -> 38.5 | C5: Wesley | D5: Roma | E5: Esterno basso | F5: 17 | G5: 18 | H5: 87 | I5: =MAX(1,ROUND(H5^Guida!$B$18*Guida!$F$12,0)) -> 19 | J5: =MAX(2,ROUND(I5*1.2,0)) -> 23 | K5: =IF(I5>=60,"Top",IF(I5>=30,"1a fascia",IF(I5>=15,"2a fascia",IF(I5>=7,"3a fascia",IF(I5>=3,"4a fascia","Scommessa"))))) -> 2a fascia | L5: Titolare | M5: Titolare confermato (2/2) | N5: - | O5: - | P5: 30 | Q5: 6.12 | R5: 6.47 | S5: 5 | T5: 0 | U5: 0/0 | V5: 5 | W5: 2 | X5: 2 | Y5: 6.75 | Z5: 7.25 | AA5: 0 | AB5: 1 | AC5: Roma | AD5: No | AE5: =ROUND(IF(P5="",5.5,R5*MIN(1,P5/25)+5.5*(1-MIN(1,P5/25))),2) -> 6.47 | AF5: Rrahmani (NAP) | AG5: 3 | AH5: =RANK(H5,$H$4:$H$192) -> 2
A6: =RANK(B6,$B$4:$B$192) -> 3 | B6: =ROUND(Guida!$B$22*H6/Guida!$B$29+Guida!$B$23*MAX(0,MIN(1,(AE6-5.4)/1.6))+Guida!$B$24*0+Guida!$B$25*0,1) -> 37 | C6: Bremer | D6: Juventus | E6: Difensore centrale | F6: 15 | G6: 16 | H6: 60 | I6: =MAX(1,ROUND(H6^Guida!$B$18*Guida!$F$12,0)) -> 15 | J6: =MAX(2,ROUND(I6*1.2,0)) -> 18 | K6: =IF(I6>=60,"Top",IF(I6>=30,"1a fascia",IF(I6>=15,"2a fascia",IF(I6>=7,"3a fascia",IF(I6>=3,"4a fascia","Scommessa"))))) -> 2a fascia | L6: Titolare | M6: Titolare confermato (2/2) | N6: - | O6: - | P6: 26 | Q6: 6.33 | R6: 6.81 | S6: 4 | T6: 3 | U6: 0/0 | V6: 5 | W6: 0 | X6: 2 | Y6: 7 | Z6: 8.5 | AA6: 1 | AB6: 0 | AC6: Juventus | AD6: No | AE6: =ROUND(IF(P6="",5.5,R6*MIN(1,P6/25)+5.5*(1-MIN(1,P6/25))),2) -> 6.81 | AF6: Ostigard (GEN) | AG6: 5 | AH6: =RANK(H6,$H$4:$H$192) -> 4
A7: =RANK(B7,$B$4:$B$192) -> 4 | B7: =ROUND(Guida!$B$22*H7/Guida!$B$29+Guida!$B$23*MAX(0,MIN(1,(AE7-5.4)/1.6))+Guida!$B$24*0.6+Guida!$B$25*0,1) -> 33.8 | C7: Ostigard | D7: Genoa | E7: Difensore centrale | F7: 11 | G7: 11 | H7: 41 | I7: =MAX(1,ROUND(H7^Guida!$B$18*Guida!$F$12,0)) -> 12 | J7: =MAX(2,ROUND(I7*1.2,0)) -> 14 | K7: =IF(I7>=60,"Top",IF(I7>=30,"1a fascia",IF(I7>=15,"2a fascia",IF(I7>=7,"3a fascia",IF(I7>=3,"4a fascia","Scommessa"))))) -> 3a fascia | L7: Titolare | M7: Titolare confermato (2/2) | N7: 2o | O7: - | P7: 30 | Q7: 6.13 | R7: 6.52 | S7: 5 | T7: 0 | U7: 0/0 | V7: 7 | W7: 0 | X7: 2 | Y7: 6.5 | Z7: 6 | AA7: 0 | AB7: 0 | AC7: Genoa | AD7: No | AE7: =ROUND(IF(P7="",5.5,R7*MIN(1,P7/25)+5.5*(1-MIN(1,P7/25))),2) -> 6.52 | AF7: Bremer (JUV) | AG7: 5 | AH7: =RANK(H7,$H$4:$H$192) -> 13
A8: =RANK(B8,$B$4:$B$192) -> 5 | B8: =ROUND(Guida!$B$22*H8/Guida!$B$29+Guida!$B$23*MAX(0,MIN(1,(AE8-5.4)/1.6))+Guida!$B$24*0.6+Guida!$B$25*0,1) -> 33.1 | C8: Solet | D8: Udinese | E8: Difensore centrale | F8: 13 | G8: 13 | H8: 46 | I8: =MAX(1,ROUND(H8^Guida!$B$18*Guida!$F$12,0)) -> 13 | J8: =MAX(2,ROUND(I8*1.2,0)) -> 16 | K8: =IF(I8>=60,"Top",IF(I8>=30,"1a fascia",IF(I8>=15,"2a fascia",IF(I8>=7,"3a fascia",IF(I8>=3,"4a fascia","Scommessa"))))) -> 3a fascia | L8: Titolare | M8: Titolare confermato (2/2) | N8: 2o | O8: - | P8: 34 | Q8: 6.18 | R8: 6.4 | S8: 3 | T8: 1 | U8: 1/1 | V8: 1 | W8: 0 | X8: 2 | Y8: 6 | Z8: 6 | AA8: 0 | AB8: 0 | AC8: Udinese | AD8: No | AE8: =ROUND(IF(P8="",5.5,R8*MIN(1,P8/25)+5.5*(1-MIN(1,P8/25))),2) -> 6.4 | AF8: Ostigard (GEN) | AG8: 7 | AH8: =RANK(H8,$H$4:$H$192) -> 10
A9: =RANK(B9,$B$4:$B$192) -> 6 | B9: =ROUND(Guida!$B$22*H9/Guida!$B$29+Guida!$B$23*MAX(0,MIN(1,(AE9-5.4)/1.6))+Guida!$B$24*0+Guida!$B$25*0,1) -> 31.3 | C9: Pavlovic | D9: Milan | E9: Difensore centrale | F9: 14 | G9: 14 | H9: 49 | I9: =MAX(1,ROUND(H9^Guida!$B$18*Guida!$F$12,0)) -> 13 | J9: =MAX(2,ROUND(I9*1.2,0)) -> 16 | K9: =IF(I9>=60,"Top",IF(I9>=30,"1a fascia",IF(I9>=15,"2a fascia",IF(I9>=7,"3a fascia",IF(I9>=3,"4a fascia","Scommessa"))))) -> 3a fascia | L9: Titolare | M9: Titolare confermato (2/2) | N9: - | O9: - | P9: 34 | Q9: 6.24 | R9: 6.62 | S9: 5 | T9: 0 | U9: 0/0 | V9: 4 | W9: 0 | X9: 2 | Y9: 6.25 | Z9: 6 | AA9: 0 | AB9: 0 | AC9: Milan | AD9: No | AE9: =ROUND(IF(P9="",5.5,R9*MIN(1,P9/25)+5.5*(1-MIN(1,P9/25))),2) -> 6.62 | AF9: Dimarco (INT) | AG9: 0 | AH9: =RANK(H9,$H$4:$H$192) -> 7
A10: =RANK(B10,$B$4:$B$192) -> 7 | B10: =ROUND(Guida!$B$22*H10/Guida!$B$29+Guida!$B$23*MAX(0,MIN(1,(AE10-5.4)/1.6))+Guida!$B$24*0+Guida!$B$25*0,1) -> 29.8 | C10: Mancini | D10: Roma | E10: Difensore centrale | F10: 15 | G10: 16 | H10: 50 | I10: =MAX(1,ROUND(H10^Guida!$B$18*Guida!$F$12,0)) -> 13 | J10: =MAX(2,ROUND(I10*1.2,0)) -> 16 | K10: =IF(I10>=60,"Top",IF(I10>=30,"1a fascia",IF(I10>=15,"2a fascia",IF(I10>=7,"3a fascia",IF(I10>=3,"4a fascia","Scommessa"))))) -> 3a fascia | L10: Titolare | M10: Titolare confermato (2/2) | N10: - | O10: - | P10: 36 | Q10: 6.25 | R10: 6.51 | S10: 4 | T10: 2 | U10: 0/0 | V10: 9 | W10: 0 | X10: 2 | Y10: 6.5 | Z10: 7 | AA10: 0 | AB10: 1 | AC10: Roma | AD10: No | AE10: =ROUND(IF(P10="",5.5,R10*MIN(1,P10/25)+5.5*(1-MIN(1,P10/25))),2) -> 6.51 | AF10: Rrahmani (NAP) | AG10: 3 | AH10: =RANK(H10,$H$4:$H$192) -> 6
A11: =RANK(B11,$B$4:$B$192) -> 8 | B11: =ROUND(Guida!$B$22*H11/Guida!$B$29+Guida!$B$23*MAX(0,MIN(1,(AE11-5.4)/1.6))+Guida!$B$24*0+Guida!$B$25*0,1) -> 27.5 | C11: Akanji | D11: Inter | E11: Difensore centrale | F11: 16 | G11: 15 | H11: 47 | I11: =MAX(1,ROUND(H11^Guida!$B$18*Guida!$F$12,0)) -> 13 | J11: =MAX(2,ROUND(I11*1.2,0)) -> 16 | K11: =IF(I11>=60,"Top",IF(I11>=30,"1a fascia",IF(I11>=15,"2a fascia",IF(I11>=7,"3a fascia",IF(I11>=3,"4a fascia","Scommessa"))))) -> 3a fascia | L11: Titolare | M11: Titolare confermato (2/2) | N11: - | O11: - | P11: 32 | Q11: 6.28 | R11: 6.41 | S11: 2 | T11: 0 | U11: 0/0 | V11: 4 | W11: 0 | X11: 2 | Y11: 5.5 | Z11: 5.25 | AA11: 0 | AB11: 0 | AC11: Inter | AD11: No | AE11: =ROUND(IF(P11="",5.5,R11*MIN(1,P11/25)+5.5*(1-MIN(1,P11/25))),2) -> 6.41 | AF11: Pavlovic (MIL) | AG11: 0 | AH11: =RANK(H11,$H$4:$H$192) -> 8
A12: =RANK(B12,$B$4:$B$192) -> 9 | B12: =ROUND(Guida!$B$22*H12/Guida!$B$29+Guida!$B$23*MAX(0,MIN(1,(AE12-5.4)/1.6))+Guida!$B$24*0+Guida!$B$25*0,1) -> 27.1 | C12: Bisseck | D12: Inter | E12: Difensore centrale | F12: 11 | G12: 12 | H12: 36 | I12: =MAX(1,ROUND(H12^Guida!$B$18*Guida!$F$12,0)) -> 11 | J12: =MAX(2,ROUND(I12*1.2,0)) -> 13 | K12: =IF(I12>=60,"Top",IF(I12>=30,"1a fascia",IF(I12>=15,"2a fascia",IF(I12>=7,"3a fascia",IF(I12>=3,"4a fascia","Scommessa"))))) -> 3a fascia | L12: Titolare | M12: Titolare confermato (2/2) | N12: - | O12: - | P12: 23 | Q12: 6.22 | R12: 6.65 | S12: 3 | T12: 2 | U12: 0/0 | V12: 2 | W12: 0 | X12: 2 | Y12: 6.75 | Z12: 8.25 | AA12: 1 | AB12: 0 | AC12: Inter | AD12: No | AE12: =ROUND(IF(P12="",5.5,R12*MIN(1,P12/25)+5.5*(1-MIN(1,P12/25))),2) -> 6.56 | AF12: Pavlovic (MIL) | AG12: 0 | AH12: =RANK(H12,$H$4:$H$192) -> 16
A13: =RANK(B13,$B$4:$B$192) -> 10 | B13: =ROUND(Guida!$B$22*H13/Guida!$B$29+Guida!$B$23*MAX(0,MIN(1,(AE13-5.4)/1.6))+Guida!$B$24*0+Guida!$B$25*0,1) -> 26.8 | C13: Rrahmani | D13: Napoli | E13: Difensore centrale | F13: 14 | G13: 15 | H13: 51 | I13: =MAX(1,ROUND(H13^Guida!$B$18*Guida!$F$12,0)) -> 13 | J13: =MAX(2,ROUND(I13*1.2,0)) -> 16 | K13: =IF(I13>=60,"Top",IF(I13>=30,"1a fascia",IF(I13>=15,"2a fascia",IF(I13>=7,"3a fascia",IF(I13>=3,"4a fascia","Scommessa"))))) -> 3a fascia | L13: Titolare | M13: Titolare confermato (2/2) | N13: - | O13: - | P13: 21 | Q13: 6.24 | R13: 6.45 | S13: 2 | T13: 0 | U13: 0/0 | V13: 3 | W13: 0 | X13: 2 | Y13: 6.25 | Z13: 6.75 | AA13: 0 | AB13: 1 | AC13: Napoli | AD13: No | AE13: =ROUND(IF(P13="",5.5,R13*MIN(1,P13/25)+5.5*(1-MIN(1,P13/25))),2) -> 6.3 | AF13: Wesley (ROM) | AG13: 3 | AH13: =RANK(H13,$H$4:$H$192) -> 5
A14: =RANK(B14,$B$4:$B$192) -> 11 | B14: =ROUND(Guida!$B$22*H14/Guida!$B$29+Guida!$B$23*MAX(0,MIN(1,(AE14-5.4)/1.6))+Guida!$B$24*0+Guida!$B$25*0,1) -> 26.6 | C14: Kalulu | D14: Juventus | E14: Terzino destro / Difensore centrale | F14: 13 | G14: 14 | H14: 47 | I14: =MAX(1,ROUND(H14^Guida!$B$18*Guida!$F$12,0)) -> 13 | J14: =MAX(2,ROUND(I14*1.2,0)) -> 16 | K14: =IF(I14>=60,"Top",IF(I14>=30,"1a fascia",IF(I14>=15,"2a fascia",IF(I14>=7,"3a fascia",IF(I14>=3,"4a fascia","Scommessa"))))) -> 3a fascia | L14: Titolare | M14: Titolare confermato (2/2) | N14: - | O14: - | P14: 37 | Q14: 6.14 | R14: 6.35 | S14: 2 | T14: 4 | U14: 0/0 | V14: 2 | W14: 1 | X14: 2 | Y14: 6.5 | Z14: 6.5 | AA14: 0 | AB14: 0 | AC14: Juventus | AD14: No | AE14: =ROUND(IF(P14="",5.5,R14*MIN(1,P14/25)+5.5*(1-MIN(1,P14/25))),2) -> 6.35 | AF14: Belghali (TOR) | AG14: 0 | AH14: =RANK(H14,$H$4:$H$192) -> 8
A15: =RANK(B15,$B$4:$B$192) -> 12 | B15: =ROUND(Guida!$B$22*H15/Guida!$B$29+Guida!$B$23*MAX(0,MIN(1,(AE15-5.4)/1.6))+Guida!$B$24*0+Guida!$B$25*0,1) -> 25.4 | C15: Bastoni | D15: Inter | E15: Difensore centrale | F15: 14 | G15: 14 | H15: 43 | I15: =MAX(1,ROUND(H15^Guida!$B$18*Guida!$F$12,0)) -> 12 | J15: =MAX(2,ROUND(I15*1.2,0)) -> 14 | K15: =IF(I15>=60,"Top",IF(I15>=30,"1a fascia",IF(I15>=15,"2a fascia",IF(I15>=7,"3a fascia",IF(I15>=3,"4a fascia","Scommessa"))))) -> 3a fascia | L15: Titolare | M15: Titolare confermato (2/2) | N15: - | O15: - | P15: 28 | Q15: 6.2 | R15: 6.34 | S15: 1 | T15: 4 | U15: 0/0 | V15: 6 | W15: 0 | X15: 2 | Y15: 6.25 | Z15: 6.25 | AA15: 0 | AB15: 0 | AC15: Inter | AD15: No | AE15: =ROUND(IF(P15="",5.5,R15*MIN(1,P15/25)+5.5*(1-MIN(1,P15/25))),2) -> 6.34 | AF15: Pavlovic (MIL) | AG15: 0 | AH15: =RANK(H15,$H$4:$H$192) -> 11
A16: =RANK(B16,$B$4:$B$192) -> 13 | B16: =ROUND(Guida!$B$22*H16/Guida!$B$29+Guida!$B$23*MAX(0,MIN(1,(AE16-5.4)/1.6))+Guida!$B$24*0+Guida!$B$25*0,1) -> 24.9 | C16: N'Dicka | D16: Roma | E16: Difensore centrale | F16: 13 | G16: 13 | H16: 42 | I16: =MAX(1,ROUND(H16^Guida!$B$18*Guida!$F$12,0)) -> 12 | J16: =MAX(2,ROUND(I16*1.2,0)) -> 14 | K16: =IF(I16>=60,"Top",IF(I16>=30,"1a fascia",IF(I16>=15,"2a fascia",IF(I16>=7,"3a fascia",IF(I16>=3,"4a fascia","Scommessa"))))) -> 3a fascia | L16: Titolare | M16: In dubbio / da valutare - presenze finora: 1/2 | N16: - | O16: - | P16: 31 | Q16: 6.08 | R16: 6.32 | S16: 3 | T16: 1 | U16: 0/0 | V16: 5 | W16: 0 | X16: 1 | Y16: 6 | Z16: 6 | AA16: 0 | AB16: 0 | AC16: Roma | AD16: No | AE16: =ROUND(IF(P16="",5.5,R16*MIN(1,P16/25)+5.5*(1-MIN(1,P16/25))),2) -> 6.32 | AF16: Marusic (LAZ) | AG16: 0 | AH16: =RANK(H16,$H$4:$H$192) -> 12 | AI16: Fastidio all'adduttore nel riscaldamento a Lecce (31/8). A rischio con l'Atalanta.
A17: =RANK(B17,$B$4:$B$192) -> 14 | B17: =ROUND(Guida!$B$22*H17/Guida!$B$29+Guida!$B$23*MAX(0,MIN(1,(AE17-5.4)/1.6))+Guida!$B$24*0+Guida!$B$25*0,1) -> 24.3 | C17: Di Lorenzo | D17: Napoli | E17: Terzino destro / Esterno basso | F17: 12 | G17: 12 | H17: 39 | I17: =MAX(1,ROUND(H17^Guida!$B$18*Guida!$F$12,0)) -> 11 | J17: =MAX(2,ROUND(I17*1.2,0)) -> 13 | K17: =IF(I17>=60,"Top",IF(I17>=30,"1a fascia",IF(I17>=15,"2a fascia",IF(I17>=7,"3a fascia",IF(I17>=3,"4a fascia","Scommessa"))))) -> 3a fascia | L17: Titolare | M17: Titolare confermato (2/2) | N17: - | O17: - | P17: 26 | Q17: 6.08 | R17: 6.33 | S17: 2 | T17: 1 | U17: 0/0 | V17: 1 | W17: 0 | X17: 2 | Y17: 6 | Z17: 5.75 | AA17: 0 | AB17: 0 | AC17: Napoli | AD17: No | AE17: =ROUND(IF(P17="",5.5,R17*MIN(1,P17/25)+5.5*(1-MIN(1,P17/25))),2) -> 6.33 | AF17: Wesley (ROM) | AG17: 3 | AH17: =RANK(H17,$H$4:$H$192) -> 14
A18: =RANK(B18,$B$4:$B$192) -> 15 | B18: =ROUND(Guida!$B$22*H18/Guida!$B$29+Guida!$B$23*MAX(0,MIN(1,(AE18-5.4)/1.6))+Guida!$B$24*0+Guida!$B$25*0,1) -> 24.2 | C18: Spinazzola | D18: Napoli | E18: Terzino sinistro / Esterno basso | F18: 8 | G18: 8 | H18: 25 | I18: =MAX(1,ROUND(H18^Guida!$B$18*Guida!$F$12,0)) -> 9 | J18: =MAX(2,ROUND(I18*1.2,0)) -> 11 | K18: =IF(I18>=60,"Top",IF(I18>=30,"1a fascia",IF(I18>=15,"2a fascia",IF(I18>=7,"3a fascia",IF(I18>=3,"4a fascia","Scommessa"))))) -> 3a fascia | L18: Titolare | M18: Titolare confermato (2/2) | N18: - | O18: - | P18: 30 | Q18: 6.17 | R18: 6.55 | S18: 3 | T18: 3 | U18: 0/0 | V18: 1 | W18: 0 | X18: 2 | Y18: 5.75 | Z18: 5.75 | AA18: 0 | AB18: 0 | AC18: Napoli | AD18: No | AE18: =ROUND(IF(P18="",5.5,R18*MIN(1,P18/25)+5.5*(1-MIN(1,P18/25))),2) -> 6.55 | AF18: Wesley (ROM) | AG18: 3 | AH18: =RANK(H18,$H$4:$H$192) -> 24
A19: =RANK(B19,$B$4:$B$192) -> 16 | B19: =ROUND(Guida!$B$22*H19/Guida!$B$29+Guida!$B$23*MAX(0,MIN(1,(AE19-5.4)/1.6))+Guida!$B$24*0+Guida!$B$25*0,1) -> 22.6 | C19: Scalvini | D19: Atalanta | E19: Difensore centrale | F19: 10 | G19: 10 | H19: 28 | I19: =MAX(1,ROUND(H19^Guida!$B$18*Guida!$F$12,0)) -> 9 | J19: =MAX(2,ROUND(I19*1.2,0)) -> 11 | K19: =IF(I19>=60,"Top",IF(I19>=30,"1a fascia",IF(I19>=15,"2a fascia",IF(I19>=7,"3a fascia",IF(I19>=3,"4a fascia","Scommessa"))))) -> 3a fascia | L19: Titolare | M19: Titolare confermato (2/2) | N19: - | O19: - | P19: 24 | Q19: 6.06 | R19: 6.44 | S19: 3 | T19: 1 | U19: 0/0 | V19: 2 | W19: 0 | X19: 2 | Y19: 6 | Z19: 6 | AA19: 0 | AB19: 0 | AC19: Atalanta | AD19: No | AE19: =ROUND(IF(P19="",5.5,R19*MIN(1,P19/25)+5.5*(1-MIN(1,P19/25))),2) -> 6.4 | AF19: Mina (CAG) | AG19: 6 | AH19: =RANK(H19,$H$4:$H$192) -> 21
A20: =RANK(B20,$B$4:$B$192) -> 17 | B20: =ROUND(Guida!$B$22*H20/Guida!$B$29+Guida!$B$23*MAX(0,MIN(1,(AE20-5.4)/1.6))+Guida!$B$24*0+Guida!$B$25*0,1) -> 22.3 | C20: Hermoso | D20: Roma | E20: Difensore centrale | F20: 10 | G20: 11 | H20: 26 | I20: =MAX(1,ROUND(H20^Guida!$B$18*Guida!$F$12,0)) -> 9 | J20: =MAX(2,ROUND(I20*1.2,0)) -> 11 | K20: =IF(I20>=60,"Top",IF(I20>=30,"1a fascia",IF(I20>=15,"2a fascia",IF(I20>=7,"3a fascia",IF(I20>=3,"4a fascia","Scommessa"))))) -> 3a fascia | L20: Ballottaggio | M20: In ballottaggio (2/2) | N20: - | O20: - | P20: 27 | Q20: 6.17 | R20: 6.41 | S20: 3 | T20: 2 | U20: 0/0 | V20: 9 | W20: 0 | X20: 2 | Y20: 6.5 | Z20: 6.25 | AA20: 0 | AB20: 0 | AC20: Roma | AD20: No | AE20: =ROUND(IF(P20="",5.5,R20*MIN(1,P20/25)+5.5*(1-MIN(1,P20/25))),2) -> 6.41 | AF20: Marusic (LAZ) | AG20: 0 | AH20: =RANK(H20,$H$4:$H$192) -> 22
A21: =RANK(B21,$B$4:$B$192) -> 18 | B21: =ROUND(Guida!$B$22*H21/Guida!$B$29+Guida!$B$23*MAX(0,MIN(1,(AE21-5.4)/1.6))+Guida!$B$24*0.35+Guida!$B$25*0.35,1) -> 21.5 | C21: Valeri | D21: Parma | E21: Terzino sinistro / Esterno basso | F21: 8 | G21: 8 | H21: 22 | I21: =MAX(1,ROUND(H21^Guida!$B$18*Guida!$F$12,0)) -> 8 | J21: =MAX(2,ROUND(I21*1.2,0)) -> 10 | K21: =IF(I21>=60,"Top",IF(I21>=30,"1a fascia",IF(I21>=15,"2a fascia",IF(I21>=7,"3a fascia",IF(I21>=3,"4a fascia","Scommessa"))))) -> 3a fascia | L21: Titolare | M21: Titolare confermato (2/2) | N21: 3o | O21: 3o | P21: 34 | Q21: 6.06 | R21: 6.09 | S21: 0 | T21: 2 | U21: 0/0 | V21: 2 | W21: 0 | X21: 2 | Y21: 6 | Z21: 6 | AA21: 0 | AB21: 0 | AC21: Parma | AD21: No | AE21: =ROUND(IF(P21="",5.5,R21*MIN(1,P21/25)+5.5*(1-MIN(1,P21/25))),2) -> 6.09 | AF21: Tiago Gabriel (LEC) | AG21: 4 | AH21: =RANK(H21,$H$4:$H$192) -> 29
A22: =RANK(B22,$B$4:$B$192) -> 19 | B22: =ROUND(Guida!$B$22*H22/Guida!$B$29+Guida!$B$23*MAX(0,MIN(1,(AE22-5.4)/1.6))+Guida!$B$24*0+Guida!$B$25*0,1) -> 21.1 | C22: Molina N. | D22: Roma | E22: Esterno basso | F22: 18 | G22: 18 | H22: 78 | I22: =MAX(1,ROUND(H22^Guida!$B$18*Guida!$F$12,0)) -> 17 | J22: =MAX(2,ROUND(I22*1.2,0)) -> 20 | K22: =IF(I22>=60,"Top",IF(I22>=30,"1a fascia",IF(I22>=15,"2a fascia",IF(I22>=7,"3a fascia",IF(I22>=3,"4a fascia","Scommessa"))))) -> 2a fascia | L22: Titolare | M22: Nuovo - Rischia il posto (1/2) | N22: - | O22: - | X22: 1 | Y22: 6 | Z22: 6 | AA22: 0 | AB22: 0 | AC22: - | AD22: Si | AE22: =ROUND(IF(P22="",5.5,R22*MIN(1,P22/25)+5.5*(1-MIN(1,P22/25))),2) -> 5.5 | AF22: Marusic (LAZ) | AG22: 0 | AH22: =RANK(H22,$H$4:$H$192) -> 3
A23: =RANK(B23,$B$4:$B$192) -> 20 | B23: =ROUND(Guida!$B$22*H23/Guida!$B$29+Guida!$B$23*MAX(0,MIN(1,(AE23-5.4)/1.6))+Guida!$B$24*0+Guida!$B$25*0,1) -> 20.8 | C23: Kempf | D23: Como | E23: Difensore centrale | F23: 5 | G23: 5 | H23: 13 | I23: =MAX(1,ROUND(H23^Guida!$B$18*Guida!$F$12,0)) -> 6 | J23: =MAX(2,ROUND(I23*1.2,0)) -> 7 | K23: =IF(I23>=60,"Top",IF(I23>=30,"1a fascia",IF(I23>=15,"2a fascia",IF(I23>=7,"3a fascia",IF(I23>=3,"4a fascia","Scommessa"))))) -> 4a fascia | L23: Ballottaggio | M23: In ballottaggio (1/2) | N23: - | O23: - | P23: 29 | Q23: 6.12 | R23: 6.52 | S23: 4 | T23: 1 | U23: 0/0 | V23: 3 | W23: 0 | X23: 1 | Y23: 6.5 | Z23: 6.5 | AA23: 0 | AB23: 0 | AC23: Como | AD23: No | AE23: =ROUND(IF(P23="",5.5,R23*MIN(1,P23/25)+5.5*(1-MIN(1,P23/25))),2) -> 6.52 | AF23: Dodò (FIO) | AG23: 6 | AH23: =RANK(H23,$H$4:$H$192) -> 76
A24: =RANK(B24,$B$4:$B$192) -> 21 | B24: =ROUND(Guida!$B$22*H24/Guida!$B$29+Guida!$B$23*MAX(0,MIN(1,(AE24-5.4)/1.6))+Guida!$B$24*0.35+Guida!$B$25*0,1) -> 20.5 | C24: Mina | D24: Cagliari | E24: Difensore centrale | F24: 8 | G24: 7 | H24: 20 | I24: =MAX(1,ROUND(H24^Guida!$B$18*Guida!$F$12,0)) -> 8 | J24: =MAX(2,ROUND(I24*1.2,0)) -> 10 | K24: =IF(I24>=60,"Top",IF(I24>=30,"1a fascia",IF(I24>=15,"2a fascia",IF(I24>=7,"3a fascia",IF(I24>=3,"4a fascia","Scommessa"))))) -> 3a fascia | L24: Titolare | M24: In dubbio / da valutare - presenze finora: 0/2 | N24: 3o | O24: - | P24: 26 | Q24: 6 | R24: 6.17 | S24: 2 | T24: 1 | U24: 0/0 | V24: 3 | W24: 1 | X24: 0 | AC24: Cagliari | AD24: No | AE24: =ROUND(IF(P24="",5.5,R24*MIN(1,P24/25)+5.5*(1-MIN(1,P24/25))),2) -> 6.17 | AF24: Scalvini (ATA) | AG24: 6 | AH24: =RANK(H24,$H$4:$H$192) -> 33 | AI24: Affaticamento al polpaccio (29/8). Out con l'Inter, a rischio anche col Lecce.
A25: =RANK(B25,$B$4:$B$192) -> 22 | B25: =ROUND(Guida!$B$22*H25/Guida!$B$29+Guida!$B$23*MAX(0,MIN(1,(AE25-5.4)/1.6))+Guida!$B$24*0+Guida!$B$25*0,1) -> 19.3 | C25: Ramon | D25: Como | E25: Difensore centrale | F25: 10 | G25: 10 | H25: 31 | I25: =MAX(1,ROUND(H25^Guida!$B$18*Guida!$F$12,0)) -> 10 | J25: =MAX(2,ROUND(I25*1.2,0)) -> 12 | K25: =IF(I25>=60,"Top",IF(I25>=30,"1a fascia",IF(I25>=15,"2a fascia",IF(I25>=7,"3a fascia",IF(I25>=3,"4a fascia","Scommessa"))))) -> 3a fascia | L25: Titolare | M25: Titolare confermato (2/2) | N25: - | O25: - | P25: 32 | Q25: 6.16 | R25: 6.14 | S25: 2 | T25: 0 | U25: 0/0 | V25: 11 | W25: 1 | X25: 2 | Y25: 6 | Z25: 6 | AA25: 0 | AB25: 0 | AC25: Como | AD25: No | AE25: =ROUND(IF(P25="",5.5,R25*MIN(1,P25/25)+5.5*(1-MIN(1,P25/25))),2) -> 6.14 | AF25: Dodò (FIO) | AG25: 6 | AH25: =RANK(H25,$H$4:$H$192) -> 18
A26: =RANK(B26,$B$4:$B$192) -> 23 | B26: =ROUND(Guida!$B$22*H26/Guida!$B$29+Guida!$B$23*MAX(0,MIN(1,(AE26-5.4)/1.6))+Guida!$B$24*0+Guida!$B$25*0,1) -> 19.1 | C26: Vasquez | D26: Genoa | E26: Terzino sinistro / Difensore centrale | F26: 9 | G26: 9 | H26: 30 | I26: =MAX(1,ROUND(H26^Guida!$B$18*Guida!$F$12,0)) -> 10 | J26: =MAX(2,ROUND(I26*1.2,0)) -> 12 | K26: =IF(I26>=60,"Top",IF(I26>=30,"1a fascia",IF(I26>=15,"2a fascia",IF(I26>=7,"3a fascia",IF(I26>=3,"4a fascia","Scommessa"))))) -> 3a fascia | L26: Titolare | M26: Titolare confermato (2/2) | N26: - | O26: - | P26: 36 | Q26: 6.08 | R26: 6.14 | S26: 1 | T26: 0 | U26: 0/0 | V26: 2 | W26: 0 | X26: 2 | Y26: 5.75 | Z26: 5.75 | AA26: 0 | AB26: 0 | AC26: Genoa | AD26: No | AE26: =ROUND(IF(P26="",5.5,R26*MIN(1,P26/25)+5.5*(1-MIN(1,P26/25))),2) -> 6.14 | AF26: Bremer (JUV) | AG26: 5 | AH26: =RANK(H26,$H$4:$H$192) -> 20
A27: =RANK(B27,$B$4:$B$192) -> 24 | B27: =ROUND(Guida!$B$22*H27/Guida!$B$29+Guida!$B$23*MAX(0,MIN(1,(AE27-5.4)/1.6))+Guida!$B$24*0+Guida!$B$25*0,1) -> 18.8 | C27: Zappacosta | D27: Atalanta | E27: Terzino destro / Esterno basso | F27: 8 | G27: 8 | H27: 19 | I27: =MAX(1,ROUND(H27^Guida!$B$18*Guida!$F$12,0)) -> 7 | J27: =MAX(2,ROUND(I27*1.2,0)) -> 8 | K27: =IF(I27>=60,"Top",IF(I27>=30,"1a fascia",IF(I27>=15,"2a fascia",IF(I27>=7,"3a fascia",IF(I27>=3,"4a fascia","Scommessa"))))) -> 3a fascia | L27: Titolare | M27: Titolare confermato (2/2) | N27: - | O27: - | P27: 35 | Q27: 6.06 | R27: 6.3 | S27: 3 | T27: 1 | U27: 0/0 | V27: 3 | W27: 0 | X27: 2 | Y27: 6 | Z27: 6 | AA27: 0 | AB27: 0 | AC27: Atalanta | AD27: No | AE27: =ROUND(IF(P27="",5.5,R27*MIN(1,P27/25)+5.5*(1-MIN(1,P27/25))),2) -> 6.3 | AF27: Mina (CAG) | AG27: 6 | AH27: =RANK(H27,$H$4:$H$192) -> 44
A28: =RANK(B28,$B$4:$B$192) -> 25 | B28: =ROUND(Guida!$B$22*H28/Guida!$B$29+Guida!$B$23*MAX(0,MIN(1,(AE28-5.4)/1.6))+Guida!$B$24*0+Guida!$B$25*0.35,1) -> 18.4 | C28: Miranda J. | D28: Bologna | E28: Terzino sinistro / Esterno basso | F28: 8 | G28: 8 | H28: 23 | I28: =MAX(1,ROUND(H28^Guida!$B$18*Guida!$F$12,0)) -> 8 | J28: =MAX(2,ROUND(I28*1.2,0)) -> 10 | K28: =IF(I28>=60,"Top",IF(I28>=30,"1a fascia",IF(I28>=15,"2a fascia",IF(I28>=7,"3a fascia",IF(I28>=3,"4a fascia","Scommessa"))))) -> 3a fascia | L28: Titolare | M28: Rischia il posto (1/2) | N28: - | O28: 3o | P28: 31 | Q28: 6 | R28: 6.1 | S28: 1 | T28: 3 | U28: 0/0 | V28: 6 | W28: 0 | X28: 1 | Y28: 6 | Z28: 6 | AA28: 0 | AB28: 0 | AC28: Bologna | AD28: No | AE28: =ROUND(IF(P28="",5.5,R28*MIN(1,P28/25)+5.5*(1-MIN(1,P28/25))),2) -> 6.1 | AF28: Rrahmani (NAP) | AG28: 6 | AH28: =RANK(H28,$H$4:$H$192) -> 28
A29: =RANK(B29,$B$4:$B$192) -> 26 | B29: =ROUND(Guida!$B$22*H29/Guida!$B$29+Guida!$B$23*MAX(0,MIN(1,(AE29-5.4)/1.6))+Guida!$B$24*0+Guida!$B$25*0,1) -> 18.2 | C29: Valle | D29: Como | E29: Terzino sinistro / Esterno basso | F29: 6 | G29: 6 | H29: 21 | I29: =MAX(1,ROUND(H29^Guida!$B$18*Guida!$F$12,0)) -> 8 | J29: =MAX(2,ROUND(I29*1.2,0)) -> 10 | K29: =IF(I29>=60,"Top",IF(I29>=30,"1a fascia",IF(I29>=15,"2a fascia",IF(I29>=7,"3a fascia",IF(I29>=3,"4a fascia","Scommessa"))))) -> 3a fascia | L29: Titolare | M29: Titolare confermato (2/2) | N29: - | O29: - | P29: 26 | Q29: 6.06 | R29: 6.23 | S29: 1 | T29: 3 | U29: 0/0 | V29: 3 | W29: 0 | X29: 2 | Y29: 6 | Z29: 6 | AA29: 0 | AB29: 0 | AC29: Como | AD29: No | AE29: =ROUND(IF(P29="",5.5,R29*MIN(1,P29/25)+5.5*(1-MIN(1,P29/25))),2) -> 6.23 | AF29: Dodò (FIO) | AG29: 6 | AH29: =RANK(H29,$H$4:$H$192) -> 31
A30: =RANK(B30,$B$4:$B$192) -> 27 | B30: =ROUND(Guida!$B$22*H30/Guida!$B$29+Guida!$B$23*MAX(0,MIN(1,(AE30-5.4)/1.6))+Guida!$B$24*0+Guida!$B$25*0,1) -> 18 | C30: Kristensen T. | D30: Atalanta | E30: Terzino destro / Difensore centrale | F30: 7 | G30: 6 | H30: 20 | I30: =MAX(1,ROUND(H30^Guida!$B$18*Guida!$F$12,0)) -> 8 | J30: =MAX(2,ROUND(I30*1.2,0)) -> 10 | K30: =IF(I30>=60,"Top",IF(I30>=30,"1a fascia",IF(I30>=15,"2a fascia",IF(I30>=7,"3a fascia",IF(I30>=3,"4a fascia","Scommessa"))))) -> 3a fascia | L30: Titolare | M30: In dubbio / da valutare - Nuovo - presenze finora: 0/2 | N30: - | O30: - | P30: 28 | Q30: 5.98 | R30: 6.23 | S30: 3 | T30: 0 | U30: 0/0 | V30: 4 | W30: 0 | X30: 0 | AC30: Udinese | AD30: Si | AE30: =ROUND(IF(P30="",5.5,R30*MIN(1,P30/25)+5.5*(1-MIN(1,P30/25))),2) -> 6.23 | AF30: Mina (CAG) | AG30: 6 | AH30: =RANK(H30,$H$4:$H$192) -> 33 | AI30: Problema alla caviglia: saltate Sassuolo e Bologna, a rischio anche con la Roma.
A31: =RANK(B31,$B$4:$B$192) -> 28 | B31: =ROUND(Guida!$B$22*H31/Guida!$B$29+Guida!$B$23*MAX(0,MIN(1,(AE31-5.4)/1.6))+Guida!$B$24*0+Guida!$B$25*0,1) -> 17.9 | C31: Vojvoda | D31: Udinese | E31: Terzino destro / Esterno basso | F31: 8 | G31: 9 | H31: 19 | I31: =MAX(1,ROUND(H31^Guida!$B$18*Guida!$F$12,0)) -> 7 | J31: =MAX(2,ROUND(I31*1.2,0)) -> 8 | K31: =IF(I31>=60,"Top",IF(I31>=30,"1a fascia",IF(I31>=15,"2a fascia",IF(I31>=7,"3a fascia",IF(I31>=3,"4a fascia","Scommessa"))))) -> 3a fascia | L31: Titolare | M31: Nuovo - Titolare confermato (2/2) | N31: - | O31: - | P31: 27 | Q31: 6.02 | R31: 6.24 | S31: 2 | T31: 1 | U31: 0/0 | V31: 2 | W31: 0 | X31: 2 | Y31: 6.5 | Z31: 6.5 | AA31: 0 | AB31: 0 | AC31: Como | AD31: Si | AE31: =ROUND(IF(P31="",5.5,R31*MIN(1,P31/25)+5.5*(1-MIN(1,P31/25))),2) -> 6.24 | AF31: Ostigard (GEN) | AG31: 7 | AH31: =RANK(H31,$H$4:$H$192) -> 44
A32: =RANK(B32,$B$4:$B$192) -> 29 | B32: =ROUND(Guida!$B$22*H32/Guida!$B$29+Guida!$B$23*MAX(0,MIN(1,(AE32-5.4)/1.6))+Guida!$B$24*0+Guida!$B$25*0,1) -> 17.7 | C32: Belghali | D32: Torino | E32: Terzino destro / Esterno basso | F32: 7 | G32: 7 | H32: 20 | I32: =MAX(1,ROUND(H32^Guida!$B$18*Guida!$F$12,0)) -> 8 | J32: =MAX(2,ROUND(I32*1.2,0)) -> 10 | K32: =IF(I32>=60,"Top",IF(I32>=30,"1a fascia",IF(I32>=15,"2a fascia",IF(I32>=7,"3a fascia",IF(I32>=3,"4a fascia","Scommessa"))))) -> 3a fascia | L32: Titolare | M32: Nuovo - RISCHIA il posto (0/2) | N32: - | O32: - | P32: 26 | Q32: 6.1 | R32: 6.21 | S32: 2 | T32: 0 | U32: 0/0 | V32: 6 | W32: 0 | X32: 0 | AC32: Verona | AD32: Si | AE32: =ROUND(IF(P32="",5.5,R32*MIN(1,P32/25)+5.5*(1-MIN(1,P32/25))),2) -> 6.21 | AF32: Bremer (JUV) | AG32: 0 | AH32: =RANK(H32,$H$4:$H$192) -> 33
A33: =RANK(B33,$B$4:$B$192) -> 30 | B33: =ROUND(Guida!$B$22*H33/Guida!$B$29+Guida!$B$23*MAX(0,MIN(1,(AE33-5.4)/1.6))+Guida!$B$24*0+Guida!$B$25*0,1) -> 17.6 | C33: Celik | D33: Juventus | E33: Braccetto / Terzino destro / Esterno basso | F33: 8 | G33: 8 | H33: 16 | I33: =MAX(1,ROUND(H33^Guida!$B$18*Guida!$F$12,0)) -> 7 | J33: =MAX(2,ROUND(I33*1.2,0)) -> 8 | K33: =IF(I33>=60,"Top",IF(I33>=30,"1a fascia",IF(I33>=15,"2a fascia",IF(I33>=7,"3a fascia",IF(I33>=3,"4a fascia","Scommessa"))))) -> 3a fascia | L33: Titolare | M33: Nuovo - Titolare confermato (2/2) | N33: - | O33: - | P33: 32 | Q33: 6.17 | R33: 6.27 | S33: 1 | T33: 2 | U33: 0/0 | V33: 2 | W33: 1 | X33: 2 | Y33: 6 | Z33: 5.75 | AA33: 0 | AB33: 0 | AC33: Roma | AD33: Si | AE33: =ROUND(IF(P33="",5.5,R33*MIN(1,P33/25)+5.5*(1-MIN(1,P33/25))),2) -> 6.27 | AF33: Belghali (TOR) | AG33: 0 | AH33: =RANK(H33,$H$4:$H$192) -> 55
A34: =RANK(B34,$B$4:$B$192) -> 31 | B34: =ROUND(Guida!$B$22*H34/Guida!$B$29+Guida!$B$23*MAX(0,MIN(1,(AE34-5.4)/1.6))+Guida!$B$24*0+Guida!$B$25*0,1) -> 17.4 | C34: Diego Carlos | D34: Parma | E34: Difensore centrale | F34: 8 | G34: 8 | H34: 26 | I34: =MAX(1,ROUND(H34^Guida!$B$18*Guida!$F$12,0)) -> 9 | J34: =MAX(2,ROUND(I34*1.2,0)) -> 11 | K34: =IF(I34>=60,"Top",IF(I34>=30,"1a fascia",IF(I34>=15,"2a fascia",IF(I34>=7,"3a fascia",IF(I34>=3,"4a fascia","Scommessa"))))) -> 3a fascia | L34: Titolare | M34: Nuovo - RISCHIA il posto (0/2) | N34: - | O34: - | P34: 25 | Q34: 6.14 | R34: 6.1 | S34: 1 | T34: 0 | U34: 0/0 | V34: 8 | W34: 0 | X34: 0 | AC34: Como | AD34: Si | AE34: =ROUND(IF(P34="",5.5,R34*MIN(1,P34/25)+5.5*(1-MIN(1,P34/25))),2) -> 6.1 | AF34: Tiago Gabriel (LEC) | AG34: 4 | AH34: =RANK(H34,$H$4:$H$192) -> 22
A35: =RANK(B35,$B$4:$B$192) -> 32 | B35: =ROUND(Guida!$B$22*H35/Guida!$B$29+Guida!$B$23*MAX(0,MIN(1,(AE35-5.4)/1.6))+Guida!$B$24*0+Guida!$B$25*0,1) -> 16.9 | C35: Carlos Augusto | D35: Inter | E35: Braccetto / Terzino sinistro / Esterno basso | F35: 7 | G35: 6 | H35: 20 | I35: =MAX(1,ROUND(H35^Guida!$B$18*Guida!$F$12,0)) -> 8 | J35: =MAX(2,ROUND(I35*1.2,0)) -> 10 | K35: =IF(I35>=60,"Top",IF(I35>=30,"1a fascia",IF(I35>=15,"2a fascia",IF(I35>=7,"3a fascia",IF(I35>=3,"4a fascia","Scommessa"))))) -> 3a fascia | L35: Riserva | M35: Riserva (0/2) | N35: - | O35: - | P35: 28 | Q35: 6.12 | R35: 6.16 | S35: 1 | T35: 1 | U35: 0/0 | V35: 6 | W35: 0 | X35: 0 | AC35: Inter | AD35: No | AE35: =ROUND(IF(P35="",5.5,R35*MIN(1,P35/25)+5.5*(1-MIN(1,P35/25))),2) -> 6.16 | AF35: Pavlovic (MIL) | AG35: 0 | AH35: =RANK(H35,$H$4:$H$192) -> 33
A36: =RANK(B36,$B$4:$B$192) -> 32 | B36: =ROUND(Guida!$B$22*H36/Guida!$B$29+Guida!$B$23*MAX(0,MIN(1,(AE36-5.4)/1.6))+Guida!$B$24*0+Guida!$B$25*0,1) -> 16.9 | C36: Rensch | D36: Roma | E36: Braccetto / Terzino destro / Esterno basso | F36: 5 | G36: 4 | H36: 14 | I36: =MAX(1,ROUND(H36^Guida!$B$18*Guida!$F$12,0)) -> 6 | J36: =MAX(2,ROUND(I36*1.2,0)) -> 7 | K36: =IF(I36>=60,"Top",IF(I36>=30,"1a fascia",IF(I36>=15,"2a fascia",IF(I36>=7,"3a fascia",IF(I36>=3,"4a fascia","Scommessa"))))) -> 4a fascia | L36: Riserva | M36: In dubbio / da valutare - presenze finora: 0/2 | N36: - | O36: - | P36: 19 | Q36: 6.16 | R36: 6.5 | S36: 1 | T36: 4 | U36: 0/0 | V36: 1 | W36: 0 | X36: 0 | AC36: Roma | AD36: No | AE36: =ROUND(IF(P36="",5.5,R36*MIN(1,P36/25)+5.5*(1-MIN(1,P36/25))),2) -> 6.26 | AF36: Marusic (LAZ) | AG36: 0 | AH36: =RANK(H36,$H$4:$H$192) -> 68 | AI36: Risentimento al flessore sinistro: fuori con Fiorentina e Lecce. Da valutare.
A37: =RANK(B37,$B$4:$B$192) -> 34 | B37: =ROUND(Guida!$B$22*H37/Guida!$B$29+Guida!$B$23*MAX(0,MIN(1,(AE37-5.4)/1.6))+Guida!$B$24*0+Guida!$B$25*0,1) -> 16.3 | C37: Gila | D37: Milan | E37: Difensore centrale | F37: 12 | G37: 13 | H37: 31 | I37: =MAX(1,ROUND(H37^Guida!$B$18*Guida!$F$12,0)) -> 10 | J37: =MAX(2,ROUND(I37*1.2,0)) -> 12 | K37: =IF(I37>=60,"Top",IF(I37>=30,"1a fascia",IF(I37>=15,"2a fascia",IF(I37>=7,"3a fascia",IF(I37>=3,"4a fascia","Scommessa"))))) -> 3a fascia | L37: Titolare | M37: Nuovo - Titolare confermato (2/2) | N37: - | O37: - | P37: 31 | Q37: 6.03 | R37: 5.95 | S37: 0 | T37: 0 | U37: 0/0 | V37: 3 | W37: 1 | X37: 2 | Y37: 6.5 | Z37: 6.5 | AA37: 0 | AB37: 0 | AC37: Lazio | AD37: Si | AE37: =ROUND(IF(P37="",5.5,R37*MIN(1,P37/25)+5.5*(1-MIN(1,P37/25))),2) -> 5.95 | AF37: Dimarco (INT) | AG37: 0 | AH37: =RANK(H37,$H$4:$H$192) -> 18
A38: =RANK(B38,$B$4:$B$192) -> 35 | B38: =ROUND(Guida!$B$22*H38/Guida!$B$29+Guida!$B$23*MAX(0,MIN(1,(AE38-5.4)/1.6))+Guida!$B$24*0+Guida!$B$25*0,1) -> 15.7 | C38: Bartesaghi | D38: Milan | E38: Terzino sinistro / Esterno basso | F38: 8 | G38: 8 | H38: 22 | I38: =MAX(1,ROUND(H38^Guida!$B$18*Guida!$F$12,0)) -> 8 | J38: =MAX(2,ROUND(I38*1.2,0)) -> 10 | K38: =IF(I38>=60,"Top",IF(I38>=30,"1a fascia",IF(I38>=15,"2a fascia",IF(I38>=7,"3a fascia",IF(I38>=3,"4a fascia","Scommessa"))))) -> 3a fascia | L38: Titolare | M38: Titolare confermato (2/2) | N38: - | O38: - | P38: 31 | Q38: 5.97 | R38: 6.05 | S38: 2 | T38: 0 | U38: 0/0 | V38: 3 | W38: 0 | X38: 2 | Y38: 6 | Z38: 6 | AA38: 0 | AB38: 0 | AC38: Milan | AD38: No | AE38: =ROUND(IF(P38="",5.5,R38*MIN(1,P38/25)+5.5*(1-MIN(1,P38/25))),2) -> 6.05 | AF38: Dimarco (INT) | AG38: 0 | AH38: =RANK(H38,$H$4:$H$192) -> 29
A39: =RANK(B39,$B$4:$B$192) -> 36 | B39: =ROUND(Guida!$B$22*H39/Guida!$B$29+Guida!$B$23*MAX(0,MIN(1,(AE39-5.4)/1.6))+Guida!$B$24*0+Guida!$B$25*0,1) -> 15.2 | C39: Kabasele | D39: Udinese | E39: Difensore centrale | F39: 4 | G39: 4 | H39: 12 | I39: =MAX(1,ROUND(H39^Guida!$B$18*Guida!$F$12,0)) -> 6 | J39: =MAX(2,ROUND(I39*1.2,0)) -> 7 | K39: =IF(I39>=60,"Top",IF(I39>=30,"1a fascia",IF(I39>=15,"2a fascia",IF(I39>=7,"3a fascia",IF(I39>=3,"4a fascia","Scommessa"))))) -> 4a fascia | L39: Titolare | M39: RISCHIA il posto (0/2) | N39: - | O39: - | P39: 28 | Q39: 5.98 | R39: 6.18 | S39: 3 | T39: 0 | U39: 0/0 | V39: 5 | W39: 1 | X39: 0 | AC39: Udinese | AD39: No | AE39: =ROUND(IF(P39="",5.5,R39*MIN(1,P39/25)+5.5*(1-MIN(1,P39/25))),2) -> 6.18 | AF39: Ostigard (GEN) | AG39: 7 | AH39: =RANK(H39,$H$4:$H$192) -> 89
A40: =RANK(B40,$B$4:$B$192) -> 37 | B40: =ROUND(Guida!$B$22*H40/Guida!$B$29+Guida!$B$23*MAX(0,MIN(1,(AE40-5.4)/1.6))+Guida!$B$24*0+Guida!$B$25*0,1) -> 15.1 | C40: Bernasconi | D40: Atalanta | E40: Terzino sinistro / Esterno basso | F40: 6 | G40: 6 | H40: 18 | I40: =MAX(1,ROUND(H40^Guida!$B$18*Guida!$F$12,0)) -> 7 | J40: =MAX(2,ROUND(I40*1.2,0)) -> 8 | K40: =IF(I40>=60,"Top",IF(I40>=30,"1a fascia",IF(I40>=15,"2a fascia",IF(I40>=7,"3a fascia",IF(I40>=3,"4a fascia","Scommessa"))))) -> 3a fascia | L40: Ballottaggio | M40: In ballottaggio (1/2) | N40: - | O40: - | P40: 22 | Q40: 6.09 | R40: 6.16 | S40: 0 | T40: 3 | U40: 0/0 | V40: 3 | W40: 0 | X40: 1 | Y40: 5.5 | Z40: 5.5 | AA40: 0 | AB40: 0 | AC40: Atalanta | AD40: No | AE40: =ROUND(IF(P40="",5.5,R40*MIN(1,P40/25)+5.5*(1-MIN(1,P40/25))),2) -> 6.08 | AF40: Mina (CAG) | AG40: 6 | AH40: =RANK(H40,$H$4:$H$192) -> 49
A41: =RANK(B41,$B$4:$B$192) -> 38 | B41: =ROUND(Guida!$B$22*H41/Guida!$B$29+Guida!$B$23*MAX(0,MIN(1,(AE41-5.4)/1.6))+Guida!$B$24*0+Guida!$B$25*0,1) -> 14.8 | C41: Delprato | D41: Parma | E41: Braccetto / Terzino destro / Esterno basso | F41: 8 | G41: 8 | H41: 21 | I41: =MAX(1,ROUND(H41^Guida!$B$18*Guida!$F$12,0)) -> 8 | J41: =MAX(2,ROUND(I41*1.2,0)) -> 10 | K41: =IF(I41>=60,"Top",IF(I41>=30,"1a fascia",IF(I41>=15,"2a fascia",IF(I41>=7,"3a fascia",IF(I41>=3,"4a fascia","Scommessa"))))) -> 3a fascia | L41: Titolare | M41: Titolare confermato (2/2) | N41: - | O41: - | P41: 35 | Q41: 5.91 | R41: 6.01 | S41: 2 | T41: 0 | U41: 0/0 | V41: 5 | W41: 0 | X41: 2 | Y41: 6 | Z41: 5.75 | AA41: 0 | AB41: 0 | AC41: Parma | AD41: No | AE41: =ROUND(IF(P41="",5.5,R41*MIN(1,P41/25)+5.5*(1-MIN(1,P41/25))),2) -> 6.01 | AF41: Tiago Gabriel (LEC) | AG41: 4 | AH41: =RANK(H41,$H$4:$H$192) -> 31
A42: =RANK(B42,$B$4:$B$192) -> 38 | B42: =ROUND(Guida!$B$22*H42/Guida!$B$29+Guida!$B$23*MAX(0,MIN(1,(AE42-5.4)/1.6))+Guida!$B$24*0+Guida!$B$25*0,1) -> 14.8 | C42: Dodò | D42: Fiorentina | E42: Terzino destro / Esterno basso | F42: 10 | G42: 9 | H42: 20 | I42: =MAX(1,ROUND(H42^Guida!$B$18*Guida!$F$12,0)) -> 8 | J42: =MAX(2,ROUND(I42*1.2,0)) -> 10 | K42: =IF(I42>=60,"Top",IF(I42>=30,"1a fascia",IF(I42>=15,"2a fascia",IF(I42>=7,"3a fascia",IF(I42>=3,"4a fascia","Scommessa"))))) -> 3a fascia | L42: Titolare | M42: Rischia il posto (1/2) | N42: - | O42: - | P42: 36 | Q42: 5.99 | R42: 6.03 | S42: 1 | T42: 2 | U42: 0/0 | V42: 7 | W42: 0 | X42: 1 | Y42: 5 | Z42: 5 | AA42: 0 | AB42: 0 | AC42: Fiorentina | AD42: No | AE42: =ROUND(IF(P42="",5.5,R42*MIN(1,P42/25)+5.5*(1-MIN(1,P42/25))),2) -> 6.03 | AF42: Kempf (COM) | AG42: 6 | AH42: =RANK(H42,$H$4:$H$192) -> 33
A43: =RANK(B43,$B$4:$B$192) -> 40 | B43: =ROUND(Guida!$B$22*H43/Guida!$B$29+Guida!$B$23*MAX(0,MIN(1,(AE43-5.4)/1.6))+Guida!$B$24*0+Guida!$B$25*0,1) -> 14.5 | C43: Tiago Gabriel | D43: Lecce | E43: Difensore centrale | F43: 7 | G43: 8 | H43: 20 | I43: =MAX(1,ROUND(H43^Guida!$B$18*Guida!$F$12,0)) -> 8 | J43: =MAX(2,ROUND(I43*1.2,0)) -> 10 | K43: =IF(I43>=60,"Top",IF(I43>=30,"1a fascia",IF(I43>=15,"2a fascia",IF(I43>=7,"3a fascia",IF(I43>=3,"4a fascia","Scommessa"))))) -> 3a fascia | L43: Titolare | M43: Titolare confermato (2/2) | N43: - | O43: - | P43: 36 | Q43: 6 | R43: 6.01 | S43: 2 | T43: 0 | U43: 0/0 | V43: 7 | W43: 0 | X43: 2 | Y43: 6 | Z43: 7.5 | AA43: 1 | AB43: 0 | AC43: Lecce | AD43: No | AE43: =ROUND(IF(P43="",5.5,R43*MIN(1,P43/25)+5.5*(1-MIN(1,P43/25))),2) -> 6.01 | AF43: Valeri (PAR) | AG43: 4 | AH43: =RANK(H43,$H$4:$H$192) -> 33
A44: =RANK(B44,$B$4:$B$192) -> 40 | B44: =ROUND(Guida!$B$22*H44/Guida!$B$29+Guida!$B$23*MAX(0,MIN(1,(AE44-5.4)/1.6))+Guida!$B$24*0+Guida!$B$25*0,1) -> 14.5 | C44: Norton-Cuffy | D44: Genoa | E44: Terzino destro / Esterno basso | F44: 8 | G44: 8 | H44: 15 | I44: =MAX(1,ROUND(H44^Guida!$B$18*Guida!$F$12,0)) -> 6 | J44: =MAX(2,ROUND(I44*1.2,0)) -> 7 | K44: =IF(I44>=60,"Top",IF(I44>=30,"1a fascia",IF(I44>=15,"2a fascia",IF(I44>=7,"3a fascia",IF(I44>=3,"4a fascia","Scommessa"))))) -> 4a fascia | L44: Titolare | M44: Titolare confermato (2/2) | N44: - | O44: - | P44: 27 | Q44: 5.93 | R44: 6.09 | S44: 2 | T44: 1 | U44: 0/0 | V44: 3 | W44: 1 | X44: 2 | Y44: 5.75 | Z44: 5.75 | AA44: 0 | AB44: 0 | AC44: Genoa | AD44: No | AE44: =ROUND(IF(P44="",5.5,R44*MIN(1,P44/25)+5.5*(1-MIN(1,P44/25))),2) -> 6.09 | AF44: Bremer (JUV) | AG44: 5 | AH44: =RANK(H44,$H$4:$H$192) -> 58
A45: =RANK(B45,$B$4:$B$192) -> 42 | B45: =ROUND(Guida!$B$22*H45/Guida!$B$29+Guida!$B$23*MAX(0,MIN(1,(AE45-5.4)/1.6))+Guida!$B$24*0+Guida!$B$25*0,1) -> 14.2 | C45: Holm | D45: Bologna | E45: Terzino destro / Esterno basso | F45: 5 | G45: 6 | H45: 13 | I45: =MAX(1,ROUND(H45^Guida!$B$18*Guida!$F$12,0)) -> 6 | J45: =MAX(2,ROUND(I45*1.2,0)) -> 7 | K45: =IF(I45>=60,"Top",IF(I45>=30,"1a fascia",IF(I45>=15,"2a fascia",IF(I45>=7,"3a fascia",IF(I45>=3,"4a fascia","Scommessa"))))) -> 4a fascia | L45: Ballottaggio | M45: Nuovo - In ballottaggio (2/2) | N45: - | O45: - | P45: 16 | Q45: 6.09 | R45: 6.44 | S45: 1 | T45: 4 | U45: 0/0 | V45: 1 | W45: 1 | X45: 2 | Y45: 6.25 | Z45: 6.25 | AA45: 0 | AB45: 0 | AC45: Juventus | AD45: Si | AE45: =ROUND(IF(P45="",5.5,R45*MIN(1,P45/25)+5.5*(1-MIN(1,P45/25))),2) -> 6.1 | AF45: Rrahmani (NAP) | AG45: 6 | AH45: =RANK(H45,$H$4:$H$192) -> 76
A46: =RANK(B46,$B$4:$B$192) -> 43 | B46: =ROUND(Guida!$B$22*H46/Guida!$B$29+Guida!$B$23*MAX(0,MIN(1,(AE46-5.4)/1.6))+Guida!$B$24*0+Guida!$B$25*0,1) -> 13.9 | C46: Marusic | D46: Lazio | E46: Terzino destro / Terzino sinistro / Esterno basso | F46: 6 | G46: 6 | H46: 20 | I46: =MAX(1,ROUND(H46^Guida!$B$18*Guida!$F$12,0)) -> 8 | J46: =MAX(2,ROUND(I46*1.2,0)) -> 10 | K46: =IF(I46>=60,"Top",IF(I46>=30,"1a fascia",IF(I46>=15,"2a fascia",IF(I46>=7,"3a fascia",IF(I46>=3,"4a fascia","Scommessa"))))) -> 3a fascia | L46: Ballottaggio | M46: INFORTUNATO (lungo stop) - presenze finora: 1/2 | N46: - | O46: - | P46: 33 | Q46: 5.86 | R46: 5.97 | S46: 1 | T46: 2 | U46: 0/0 | V46: 1 | W46: 1 | X46: 1 | Y46: 6 | Z46: 6 | AA46: 0 | AB46: 0 | AC46: Lazio | AD46: No | AE46: =ROUND(IF(P46="",5.5,R46*MIN(1,P46/25)+5.5*(1-MIN(1,P46/25))),2) -> 5.97 | AF46: Mancini (ROM) | AG46: 0 | AH46: =RANK(H46,$H$4:$H$192) -> 33 | AI46: Lesione muscolare alla coscia (24/8). Ipotesi rientro da inizio ottobre.
A47: =RANK(B47,$B$4:$B$192) -> 43 | B47: =ROUND(Guida!$B$22*H47/Guida!$B$29+Guida!$B$23*MAX(0,MIN(1,(AE47-5.4)/1.6))+Guida!$B$24*0+Guida!$B$25*0,1) -> 13.9 | C47: Obrador | D47: Sassuolo | E47: Terzino sinistro / Esterno basso | F47: 6 | G47: 6 | H47: 13 | I47: =MAX(1,ROUND(H47^Guida!$B$18*Guida!$F$12,0)) -> 6 | J47: =MAX(2,ROUND(I47*1.2,0)) -> 7 | K47: =IF(I47>=60,"Top",IF(I47>=30,"1a fascia",IF(I47>=15,"2a fascia",IF(I47>=7,"3a fascia",IF(I47>=3,"4a fascia","Scommessa"))))) -> 4a fascia | L47: Titolare | M47: Nuovo - Rischia il posto (1/2) | N47: - | O47: - | P47: 16 | Q47: 6.06 | R47: 6.41 | S47: 1 | T47: 3 | U47: 0/0 | V47: 1 | W47: 0 | X47: 1 | Y47: 6 | Z47: 6 | AA47: 0 | AB47: 0 | AC47: Torino | AD47: Si | AE47: =ROUND(IF(P47="",5.5,R47*MIN(1,P47/25)+5.5*(1-MIN(1,P47/25))),2) -> 6.08 | AF47: Akanji (INT) | AG47: 4 | AH47: =RANK(H47,$H$4:$H$192) -> 76
A48: =RANK(B48,$B$4:$B$192) -> 45 | B48: =ROUND(Guida!$B$22*H48/Guida!$B$29+Guida!$B$23*MAX(0,MIN(1,(AE48-5.4)/1.6))+Guida!$B$24*0+Guida!$B$25*0,1) -> 13.7 | C48: Cambiaso | D48: Juventus | E48: Terzino destro / Terzino sinistro / Esterno basso | F48: 9 | G48: 8 | H48: 18 | I48: =MAX(1,ROUND(H48^Guida!$B$18*Guida!$F$12,0)) -> 7 | J48: =MAX(2,ROUND(I48*1.2,0)) -> 8 | K48: =IF(I48>=60,"Top",IF(I48>=30,"1a fascia",IF(I48>=15,"2a fascia",IF(I48>=7,"3a fascia",IF(I48>=3,"4a fascia","Scommessa"))))) -> 3a fascia | L48: Titolare | M48: Rischia il posto (1/2) | N48: - | O48: - | P48: 36 | Q48: 5.81 | R48: 5.99 | S48: 3 | T48: 4 | U48: 0/0 | V48: 3 | W48: 1 | X48: 1 | Y48: 6 | Z48: 5.5 | AA48: 0 | AB48: 0 | AC48: Juventus | AD48: No | AE48: =ROUND(IF(P48="",5.5,R48*MIN(1,P48/25)+5.5*(1-MIN(1,P48/25))),2) -> 5.99 | AF48: Belghali (TOR) | AG48: 0 | AH48: =RANK(H48,$H$4:$H$192) -> 49
A49: =RANK(B49,$B$4:$B$192) -> 46 | B49: =ROUND(Guida!$B$22*H49/Guida!$B$29+Guida!$B$23*MAX(0,MIN(1,(AE49-5.4)/1.6))+Guida!$B$24*0+Guida!$B$25*0,1) -> 13.6 | C49: Beukema | D49: Napoli | E49: Difensore centrale | F49: 6 | G49: 6 | H49: 12 | I49: =MAX(1,ROUND(H49^Guida!$B$18*Guida!$F$12,0)) -> 6 | J49: =MAX(2,ROUND(I49*1.2,0)) -> 7 | K49: =IF(I49>=60,"Top",IF(I49>=30,"1a fascia",IF(I49>=15,"2a fascia",IF(I49>=7,"3a fascia",IF(I49>=3,"4a fascia","Scommessa"))))) -> 4a fascia | L49: Ballottaggio | M49: In ballottaggio (0/2) | N49: - | O49: - | P49: 22 | Q49: 5.93 | R49: 6.16 | S49: 2 | T49: 0 | U49: 0/0 | V49: 2 | W49: 0 | X49: 0 | AC49: Napoli | AD49: No | AE49: =ROUND(IF(P49="",5.5,R49*MIN(1,P49/25)+5.5*(1-MIN(1,P49/25))),2) -> 6.08 | AF49: Mancini (ROM) | AG49: 3 | AH49: =RANK(H49,$H$4:$H$192) -> 89
A50: =RANK(B50,$B$4:$B$192) -> 47 | B50: =ROUND(Guida!$B$22*H50/Guida!$B$29+Guida!$B$23*MAX(0,MIN(1,(AE50-5.4)/1.6))+Guida!$B$24*0+Guida!$B$25*0,1) -> 13.5 | C50: Kelly L. | D50: Juventus | E50: Terzino sinistro / Difensore centrale | F50: 5 | G50: 5 | H50: 12 | I50: =MAX(1,ROUND(H50^Guida!$B$18*Guida!$F$12,0)) -> 6 | J50: =MAX(2,ROUND(I50*1.2,0)) -> 7 | K50: =IF(I50>=60,"Top",IF(I50>=30,"1a fascia",IF(I50>=15,"2a fascia",IF(I50>=7,"3a fascia",IF(I50>=3,"4a fascia","Scommessa"))))) -> 4a fascia | L50: Ballottaggio | M50: In ballottaggio (2/2) | N50: - | O50: - | P50: 35 | Q50: 6.01 | R50: 6.07 | S50: 1 | T50: 1 | U50: 0/0 | V50: 4 | W50: 0 | X50: 2 | Y50: 5.75 | Z50: 5.75 | AA50: 0 | AB50: 0 | AC50: Juventus | AD50: No | AE50: =ROUND(IF(P50="",5.5,R50*MIN(1,P50/25)+5.5*(1-MIN(1,P50/25))),2) -> 6.07 | AF50: Belghali (TOR) | AG50: 0 | AH50: =RANK(H50,$H$4:$H$192) -> 89
A51: =RANK(B51,$B$4:$B$192) -> 48 | B51: =ROUND(Guida!$B$22*H51/Guida!$B$29+Guida!$B$23*MAX(0,MIN(1,(AE51-5.4)/1.6))+Guida!$B$24*0+Guida!$B$25*0,1) -> 13.4 | C51: Zanoli | D51: Udinese | E51: Terzino destro / Esterno basso | F51: 4 | G51: 4 | H51: 10 | I51: =MAX(1,ROUND(H51^Guida!$B$18*Guida!$F$12,0)) -> 5 | J51: =MAX(2,ROUND(I51*1.2,0)) -> 6 | K51: =IF(I51>=60,"Top",IF(I51>=30,"1a fascia",IF(I51>=15,"2a fascia",IF(I51>=7,"3a fascia",IF(I51>=3,"4a fascia","Scommessa"))))) -> 4a fascia | L51: Ballottaggio | M51: INFORTUNATO (lungo stop) - presenze finora: 0/2 | N51: - | O51: - | P51: 19 | Q51: 6.05 | R51: 6.29 | S51: 1 | T51: 2 | U51: 0/0 | V51: 1 | W51: 0 | X51: 0 | AC51: Udinese | AD51: No | AE51: =ROUND(IF(P51="",5.5,R51*MIN(1,P51/25)+5.5*(1-MIN(1,P51/25))),2) -> 6.1 | AF51: Vasquez (GEN) | AG51: 7 | AH51: =RANK(H51,$H$4:$H$192) -> 114 | AI51: Operato al crociato a gennaio. Puo tornare in campo da ottobre.
A52: =RANK(B52,$B$4:$B$192) -> 49 | B52: =ROUND(Guida!$B$22*H52/Guida!$B$29+Guida!$B$23*MAX(0,MIN(1,(AE52-5.4)/1.6))+Guida!$B$24*0+Guida!$B$25*0,1) -> 13.1 | C52: Romagnoli | D52: Lazio | E52: Difensore centrale | F52: 7 | G52: 6 | H52: 20 | I52: =MAX(1,ROUND(H52^Guida!$B$18*Guida!$F$12,0)) -> 8 | J52: =MAX(2,ROUND(I52*1.2,0)) -> 10 | K52: =IF(I52>=60,"Top",IF(I52>=30,"1a fascia",IF(I52>=15,"2a fascia",IF(I52>=7,"3a fascia",IF(I52>=3,"4a fascia","Scommessa"))))) -> 3a fascia | L52: Titolare | M52: RISCHIA il posto (0/2) | N52: - | O52: - | P52: 32 | Q52: 6.03 | R52: 5.92 | S52: 0 | T52: 0 | U52: 0/0 | V52: 5 | W52: 1 | X52: 0 | AC52: Lazio | AD52: No | AE52: =ROUND(IF(P52="",5.5,R52*MIN(1,P52/25)+5.5*(1-MIN(1,P52/25))),2) -> 5.92 | AF52: N'Dicka (ROM) | AG52: 0 | AH52: =RANK(H52,$H$4:$H$192) -> 33
A53: =RANK(B53,$B$4:$B$192) -> 50 | B53: =ROUND(Guida!$B$22*H53/Guida!$B$29+Guida!$B$23*MAX(0,MIN(1,(AE53-5.4)/1.6))+Guida!$B$24*0+Guida!$B$25*0,1) -> 12.6 | C53: Idzes | D53: Sassuolo | E53: Difensore centrale | F53: 7 | G53: 7 | H53: 19 | I53: =MAX(1,ROUND(H53^Guida!$B$18*Guida!$F$12,0)) -> 7 | J53: =MAX(2,ROUND(I53*1.2,0)) -> 8 | K53: =IF(I53>=60,"Top",IF(I53>=30,"1a fascia",IF(I53>=15,"2a fascia",IF(I53>=7,"3a fascia",IF(I53>=3,"4a fascia","Scommessa"))))) -> 3a fascia | L53: Titolare | M53: Rischia il posto (1/2) | N53: - | O53: - | P53: 35 | Q53: 5.94 | R53: 5.9 | S53: 0 | T53: 0 | U53: 0/0 | V53: 3 | W53: 0 | X53: 1 | Y53: 6 | Z53: 6 | AA53: 0 | AB53: 0 | AC53: Sassuolo | AD53: No | AE53: =ROUND(IF(P53="",5.5,R53*MIN(1,P53/25)+5.5*(1-MIN(1,P53/25))),2) -> 5.9 | AF53: Bastoni (INT) | AG53: 4 | AH53: =RANK(H53,$H$4:$H$192) -> 44
A54: =RANK(B54,$B$4:$B$192) -> 51 | B54: =ROUND(Guida!$B$22*H54/Guida!$B$29+Guida!$B$23*MAX(0,MIN(1,(AE54-5.4)/1.6))+Guida!$B$24*0+Guida!$B$25*0,1) -> 12.5 | C54: De Winter | D54: Milan | E54: Terzino destro / Difensore centrale | F54: 3 | G54: 5 | H54: 20 | I54: =MAX(1,ROUND(H54^Guida!$B$18*Guida!$F$12,0)) -> 8 | J54: =MAX(2,ROUND(I54*1.2,0)) -> 10 | K54: =IF(I54>=60,"Top",IF(I54>=30,"1a fascia",IF(I54>=15,"2a fascia",IF(I54>=7,"3a fascia",IF(I54>=3,"4a fascia","Scommessa"))))) -> 3a fascia | L54: Ballottaggio | M54: In ballottaggio (2/2) | N54: - | O54: - | P54: 24 | Q54: 5.75 | R54: 5.9 | S54: 1 | T54: 1 | U54: 0/0 | V54: 1 | W54: 0 | X54: 2 | Y54: 6.75 | Z54: 6.75 | AA54: 0 | AB54: 0 | AC54: Milan | AD54: No | AE54: =ROUND(IF(P54="",5.5,R54*MIN(1,P54/25)+5.5*(1-MIN(1,P54/25))),2) -> 5.88 | AF54: Bastoni (INT) | AG54: 0 | AH54: =RANK(H54,$H$4:$H$192) -> 33
A55: =RANK(B55,$B$4:$B$192) -> 52 | B55: =ROUND(Guida!$B$22*H55/Guida!$B$29+Guida!$B$23*MAX(0,MIN(1,(AE55-5.4)/1.6))+Guida!$B$24*0+Guida!$B$25*0,1) -> 12.4 | C55: Zortea | D55: Bologna | E55: Terzino destro / Esterno basso | F55: 6 | G55: 7 | H55: 19 | I55: =MAX(1,ROUND(H55^Guida!$B$18*Guida!$F$12,0)) -> 7 | J55: =MAX(2,ROUND(I55*1.2,0)) -> 8 | K55: =IF(I55>=60,"Top",IF(I55>=30,"1a fascia",IF(I55>=15,"2a fascia",IF(I55>=7,"3a fascia",IF(I55>=3,"4a fascia","Scommessa"))))) -> 3a fascia | L55: Titolare | M55: Titolare confermato (2/2) | N55: - | O55: - | P55: 28 | Q55: 5.86 | R55: 5.89 | S55: 0 | T55: 2 | U55: 0/0 | V55: 2 | W55: 0 | X55: 2 | Y55: 6 | Z55: 6 | AA55: 0 | AB55: 0 | AC55: Bologna | AD55: No | AE55: =ROUND(IF(P55="",5.5,R55*MIN(1,P55/25)+5.5*(1-MIN(1,P55/25))),2) -> 5.89 | AF55: Di Lorenzo (NAP) | AG55: 6 | AH55: =RANK(H55,$H$4:$H$192) -> 44
A56: =RANK(B56,$B$4:$B$192) -> 53 | B56: =ROUND(Guida!$B$22*H56/Guida!$B$29+Guida!$B$23*MAX(0,MIN(1,(AE56-5.4)/1.6))+Guida!$B$24*0+Guida!$B$25*0,1) -> 12.2 | C56: Gallo | D56: Lecce | E56: Terzino sinistro / Esterno basso | F56: 6 | G56: 6 | H56: 12 | I56: =MAX(1,ROUND(H56^Guida!$B$18*Guida!$F$12,0)) -> 6 | J56: =MAX(2,ROUND(I56*1.2,0)) -> 7 | K56: =IF(I56>=60,"Top",IF(I56>=30,"1a fascia",IF(I56>=15,"2a fascia",IF(I56>=7,"3a fascia",IF(I56>=3,"4a fascia","Scommessa"))))) -> 4a fascia | L56: Titolare | M56: Rischia il posto (1/2) | N56: - | O56: - | P56: 37 | Q56: 5.95 | R56: 5.99 | S56: 0 | T56: 3 | U56: 0/0 | V56: 3 | W56: 0 | X56: 1 | Y56: 5.5 | Z56: 5.5 | AA56: 0 | AB56: 0 | AC56: Lecce | AD56: No | AE56: =ROUND(IF(P56="",5.5,R56*MIN(1,P56/25)+5.5*(1-MIN(1,P56/25))),2) -> 5.99 | AF56: Valeri (PAR) | AG56: 4 | AH56: =RANK(H56,$H$4:$H$192) -> 89
A57: =RANK(B57,$B$4:$B$192) -> 54 | B57: =ROUND(Guida!$B$22*H57/Guida!$B$29+Guida!$B$23*MAX(0,MIN(1,(AE57-5.4)/1.6))+Guida!$B$24*0+Guida!$B$25*0,1) -> 11.9 | C57: Tavares N. | D57: Lazio | E57: Terzino sinistro / Esterno basso | F57: 6 | G57: 7 | H57: 25 | I57: =MAX(1,ROUND(H57^Guida!$B$18*Guida!$F$12,0)) -> 9 | J57: =MAX(2,ROUND(I57*1.2,0)) -> 11 | K57: =IF(I57>=60,"Top",IF(I57>=30,"1a fascia",IF(I57>=15,"2a fascia",IF(I57>=7,"3a fascia",IF(I57>=3,"4a fascia","Scommessa"))))) -> 3a fascia | L57: Titolare | M57: Rischia il posto (1/2) | N57: - | O57: - | P57: 22 | Q57: 5.91 | R57: 5.8 | S57: 0 | T57: 0 | U57: 0/0 | V57: 5 | W57: 0 | X57: 1 | Y57: 6.5 | Z57: 7.5 | AA57: 0 | AB57: 1 | AC57: Lazio | AD57: No | AE57: =ROUND(IF(P57="",5.5,R57*MIN(1,P57/25)+5.5*(1-MIN(1,P57/25))),2) -> 5.76 | AF57: Hermoso (ROM) | AG57: 0 | AH57: =RANK(H57,$H$4:$H$192) -> 24
A58: =RANK(B58,$B$4:$B$192) -> 54 | B58: =ROUND(Guida!$B$22*H58/Guida!$B$29+Guida!$B$23*MAX(0,MIN(1,(AE58-5.4)/1.6))+Guida!$B$24*0+Guida!$B$25*0,1) -> 11.9 | C58: Lucumì | D58: Juventus | E58: Difensore centrale | F58: 8 | G58: 7 | H58: 17 | I58: =MAX(1,ROUND(H58^Guida!$B$18*Guida!$F$12,0)) -> 7 | J58: =MAX(2,ROUND(I58*1.2,0)) -> 8 | K58: =IF(I58>=60,"Top",IF(I58>=30,"1a fascia",IF(I58>=15,"2a fascia",IF(I58>=7,"3a fascia",IF(I58>=3,"4a fascia","Scommessa"))))) -> 3a fascia | L58: Ballottaggio | M58: Nuovo - In ballottaggio (1/2) | N58: - | O58: - | P58: 28 | Q58: 5.88 | R58: 5.89 | S58: 1 | T58: 0 | U58: 0/0 | V58: 5 | W58: 0 | X58: 1 | Y58: 5.5 | Z58: 5 | AA58: 0 | AB58: 0 | AC58: Bologna | AD58: Si | AE58: =ROUND(IF(P58="",5.5,R58*MIN(1,P58/25)+5.5*(1-MIN(1,P58/25))),2) -> 5.89 | AF58: Belghali (TOR) | AG58: 0 | AH58: =RANK(H58,$H$4:$H$192) -> 53
A59: =RANK(B59,$B$4:$B$192) -> 56 | B59: =ROUND(Guida!$B$22*H59/Guida!$B$29+Guida!$B$23*MAX(0,MIN(1,(AE59-5.4)/1.6))+Guida!$B$24*0+Guida!$B$25*0,1) -> 11.5 | C59: Coco | D59: Torino | E59: Difensore centrale | F59: 7 | G59: 7 | H59: 14 | I59: =MAX(1,ROUND(H59^Guida!$B$18*Guida!$F$12,0)) -> 6 | J59: =MAX(2,ROUND(I59*1.2,0)) -> 7 | K59: =IF(I59>=60,"Top",IF(I59>=30,"1a fascia",IF(I59>=15,"2a fascia",IF(I59>=7,"3a fascia",IF(I59>=3,"4a fascia","Scommessa"))))) -> 4a fascia | L59: Titolare | M59: Titolare confermato (2/2) | N59: - | O59: - | P59: 35 | Q59: 5.84 | R59: 5.91 | S59: 1 | T59: 1 | U59: 0/0 | V59: 3 | W59: 0 | X59: 2 | Y59: 5.75 | Z59: 5.75 | AA59: 0 | AB59: 0 | AC59: Torino | AD59: No | AE59: =ROUND(IF(P59="",5.5,R59*MIN(1,P59/25)+5.5*(1-MIN(1,P59/25))),2) -> 5.91 | AF59: Celik (JUV) | AG59: 0 | AH59: =RANK(H59,$H$4:$H$192) -> 68
A60: =RANK(B60,$B$4:$B$192) -> 57 | B60: =ROUND(Guida!$B$22*H60/Guida!$B$29+Guida!$B$23*MAX(0,MIN(1,(AE60-5.4)/1.6))+Guida!$B$24*0+Guida!$B$25*0,1) -> 11.3 | C60: Buongiorno | D60: Napoli | E60: Difensore centrale | F60: 7 | G60: 6 | H60: 15 | I60: =MAX(1,ROUND(H60^Guida!$B$18*Guida!$F$12,0)) -> 6 | J60: =MAX(2,ROUND(I60*1.2,0)) -> 7 | K60: =IF(I60>=60,"Top",IF(I60>=30,"1a fascia",IF(I60>=15,"2a fascia",IF(I60>=7,"3a fascia",IF(I60>=3,"4a fascia","Scommessa"))))) -> 4a fascia | L60: Ballottaggio | M60: INFORTUNATO (lungo stop) - presenze finora: 0/2 | N60: - | O60: - | P60: 32 | Q60: 5.89 | R60: 5.88 | S60: 0 | T60: 1 | U60: 0/0 | V60: 3 | W60: 0 | X60: 0 | AC60: Napoli | AD60: No | AE60: =ROUND(IF(P60="",5.5,R60*MIN(1,P60/25)+5.5*(1-MIN(1,P60/25))),2) -> 5.88 | AF60: Hermoso (ROM) | AG60: 3 | AH60: =RANK(H60,$H$4:$H$192) -> 58 | AI60: Operato al menisco del ginocchio destro a luglio. Rientro ipotizzato a meta novembre.
A61: =RANK(B61,$B$4:$B$192) -> 57 | B61: =ROUND(Guida!$B$22*H61/Guida!$B$29+Guida!$B$23*MAX(0,MIN(1,(AE61-5.4)/1.6))+Guida!$B$24*0+Guida!$B$25*0,1) -> 11.3 | C61: Gatti | D61: Juventus | E61: Difensore centrale | F61: 4 | G61: 4 | H61: 10 | I61: =MAX(1,ROUND(H61^Guida!$B$18*Guida!$F$12,0)) -> 5 | J61: =MAX(2,ROUND(I61*1.2,0)) -> 6 | K61: =IF(I61>=60,"Top",IF(I61>=30,"1a fascia",IF(I61>=15,"2a fascia",IF(I61>=7,"3a fascia",IF(I61>=3,"4a fascia","Scommessa"))))) -> 4a fascia | L61: Riserva | M61: Riserva (0/2) | N61: - | O61: - | P61: 16 | Q61: 5.94 | R61: 6.22 | S61: 2 | T61: 0 | U61: 0/0 | V61: 3 | W61: 0 | X61: 0 | AC61: Juventus | AD61: No | AE61: =ROUND(IF(P61="",5.5,R61*MIN(1,P61/25)+5.5*(1-MIN(1,P61/25))),2) -> 5.96 | AF61: Belghali (TOR) | AG61: 0 | AH61: =RANK(H61,$H$4:$H$192) -> 114
A62: =RANK(B62,$B$4:$B$192) -> 59 | B62: =ROUND(Guida!$B$22*H62/Guida!$B$29+Guida!$B$23*MAX(0,MIN(1,(AE62-5.4)/1.6))+Guida!$B$24*0+Guida!$B$25*0,1) -> 10.9 | C62: Parisi | D62: Fiorentina | E62: Terzino sinistro / Esterno basso | F62: 5 | G62: 4 | H62: 10 | I62: =MAX(1,ROUND(H62^Guida!$B$18*Guida!$F$12,0)) -> 5 | J62: =MAX(2,ROUND(I62*1.2,0)) -> 6 | K62: =IF(I62>=60,"Top",IF(I62>=30,"1a fascia",IF(I62>=15,"2a fascia",IF(I62>=7,"3a fascia",IF(I62>=3,"4a fascia","Scommessa"))))) -> 4a fascia | L62: Ballottaggio | M62: INFORTUNATO (lungo stop) - presenze finora: 0/2 | N62: - | O62: - | P62: 23 | Q62: 6.02 | R62: 5.98 | S62: 1 | T62: 1 | U62: 0/0 | V62: 6 | W62: 0 | X62: 0 | AC62: Fiorentina | AD62: No | AE62: =ROUND(IF(P62="",5.5,R62*MIN(1,P62/25)+5.5*(1-MIN(1,P62/25))),2) -> 5.94 | AF62: Kempf (COM) | AG62: 6 | AH62: =RANK(H62,$H$4:$H$192) -> 114 | AI62: Recupero dalla lesione del crociato: punta a tornare convocabile da novembre.
A63: =RANK(B63,$B$4:$B$192) -> 60 | B63: =ROUND(Guida!$B$22*H63/Guida!$B$29+Guida!$B$23*MAX(0,MIN(1,(AE63-5.4)/1.6))+Guida!$B$24*0+Guida!$B$25*0,1) -> 10.8 | C63: Spence | D63: Inter | E63: Esterno basso | F63: 12 | G63: 11 | H63: 37 | I63: =MAX(1,ROUND(H63^Guida!$B$18*Guida!$F$12,0)) -> 11 | J63: =MAX(2,ROUND(I63*1.2,0)) -> 13 | K63: =IF(I63>=60,"Top",IF(I63>=30,"1a fascia",IF(I63>=15,"2a fascia",IF(I63>=7,"3a fascia",IF(I63>=3,"4a fascia","Scommessa"))))) -> 3a fascia | L63: Ballottaggio | M63: Nuovo - In ballottaggio (0/2) | N63: - | O63: - | X63: 0 | AC63: - | AD63: Si | AE63: =ROUND(IF(P63="",5.5,R63*MIN(1,P63/25)+5.5*(1-MIN(1,P63/25))),2) -> 5.5 | AF63: Gila (MIL) | AG63: 0 | AH63: =RANK(H63,$H$4:$H$192) -> 15
A64: =RANK(B64,$B$4:$B$192) -> 60 | B64: =ROUND(Guida!$B$22*H64/Guida!$B$29+Guida!$B$23*MAX(0,MIN(1,(AE64-5.4)/1.6))+Guida!$B$24*0+Guida!$B$25*0,1) -> 10.8 | C64: Ismajli | D64: Torino | E64: Difensore centrale | F64: 7 | G64: 7 | H64: 13 | I64: =MAX(1,ROUND(H64^Guida!$B$18*Guida!$F$12,0)) -> 6 | J64: =MAX(2,ROUND(I64*1.2,0)) -> 7 | K64: =IF(I64>=60,"Top",IF(I64>=30,"1a fascia",IF(I64>=15,"2a fascia",IF(I64>=7,"3a fascia",IF(I64>=3,"4a fascia","Scommessa"))))) -> 4a fascia | L64: Titolare | M64: Titolare confermato (2/2) | N64: - | O64: - | P64: 24 | Q64: 5.92 | R64: 5.9 | S64: 0 | T64: 2 | U64: 0/0 | V64: 5 | W64: 0 | X64: 2 | Y64: 6 | Z64: 6 | AA64: 0 | AB64: 0 | AC64: Torino | AD64: No | AE64: =ROUND(IF(P64="",5.5,R64*MIN(1,P64/25)+5.5*(1-MIN(1,P64/25))),2) -> 5.88 | AF64: Celik (JUV) | AG64: 0 | AH64: =RANK(H64,$H$4:$H$192) -> 76
A65: =RANK(B65,$B$4:$B$192) -> 62 | B65: =ROUND(Guida!$B$22*H65/Guida!$B$29+Guida!$B$23*MAX(0,MIN(1,(AE65-5.4)/1.6))+Guida!$B$24*0+Guida!$B$25*0,1) -> 10.6 | C65: Gabbia | D65: Milan | E65: Difensore centrale | F65: 7 | G65: 7 | H65: 15 | I65: =MAX(1,ROUND(H65^Guida!$B$18*Guida!$F$12,0)) -> 6 | J65: =MAX(2,ROUND(I65*1.2,0)) -> 7 | K65: =IF(I65>=60,"Top",IF(I65>=30,"1a fascia",IF(I65>=15,"2a fascia",IF(I65>=7,"3a fascia",IF(I65>=3,"4a fascia","Scommessa"))))) -> 4a fascia | L65: Titolare | M65: Rischia il posto (1/2) | N65: - | O65: - | P65: 29 | Q65: 5.91 | R65: 5.84 | S65: 0 | T65: 0 | U65: 0/0 | V65: 4 | W65: 0 | X65: 1 | Y65: 6 | Z65: 6 | AA65: 0 | AB65: 0 | AC65: Milan | AD65: No | AE65: =ROUND(IF(P65="",5.5,R65*MIN(1,P65/25)+5.5*(1-MIN(1,P65/25))),2) -> 5.84 | AF65: Carlos Augusto (INT) | AG65: 0 | AH65: =RANK(H65,$H$4:$H$192) -> 58
A66: =RANK(B66,$B$4:$B$192) -> 63 | B66: =ROUND(Guida!$B$22*H66/Guida!$B$29+Guida!$B$23*MAX(0,MIN(1,(AE66-5.4)/1.6))+Guida!$B$24*0+Guida!$B$25*0,1) -> 10.5 | C66: Kossounou | D66: Atalanta | E66: Terzino destro / Difensore centrale | F66: 3 | G66: 4 | H66: 12 | I66: =MAX(1,ROUND(H66^Guida!$B$18*Guida!$F$12,0)) -> 6 | J66: =MAX(2,ROUND(I66*1.2,0)) -> 7 | K66: =IF(I66>=60,"Top",IF(I66>=30,"1a fascia",IF(I66>=15,"2a fascia",IF(I66>=7,"3a fascia",IF(I66>=3,"4a fascia","Scommessa"))))) -> 4a fascia | L66: Riserva | M66: Riserva (2/2) | N66: - | O66: - | P66: 16 | Q66: 5.94 | R66: 6.09 | S66: 1 | T66: 0 | U66: 0/0 | V66: 1 | W66: 0 | X66: 2 | Y66: 5.75 | Z66: 5.75 | AA66: 0 | AB66: 0 | AC66: Atalanta | AD66: No | AE66: =ROUND(IF(P66="",5.5,R66*MIN(1,P66/25)+5.5*(1-MIN(1,P66/25))),2) -> 5.88 | AF66: Miranda J. (BOL) | AG66: 6 | AH66: =RANK(H66,$H$4:$H$192) -> 89
A67: =RANK(B67,$B$4:$B$192) -> 64 | B67: =ROUND(Guida!$B$22*H67/Guida!$B$29+Guida!$B$23*MAX(0,MIN(1,(AE67-5.4)/1.6))+Guida!$B$24*0+Guida!$B$25*0,1) -> 10.4 | C67: Marcandalli | D67: Genoa | E67: Difensore centrale | F67: 6 | G67: 6 | H67: 14 | I67: =MAX(1,ROUND(H67^Guida!$B$18*Guida!$F$12,0)) -> 6 | J67: =MAX(2,ROUND(I67*1.2,0)) -> 7 | K67: =IF(I67>=60,"Top",IF(I67>=30,"1a fascia",IF(I67>=15,"2a fascia",IF(I67>=7,"3a fascia",IF(I67>=3,"4a fascia","Scommessa"))))) -> 4a fascia | L67: Titolare | M67: Titolare confermato (2/2) | N67: - | O67: - | P67: 31 | Q67: 5.87 | R67: 5.84 | S67: 0 | T67: 1 | U67: 0/0 | V67: 4 | W67: 0 | X67: 2 | Y67: 5.75 | Z67: 5.75 | AA67: 0 | AB67: 0 | AC67: Genoa | AD67: No | AE67: =ROUND(IF(P67="",5.5,R67*MIN(1,P67/25)+5.5*(1-MIN(1,P67/25))),2) -> 5.84 | AF67: Celik (JUV) | AG67: 5 | AH67: =RANK(H67,$H$4:$H$192) -> 68
A68: =RANK(B68,$B$4:$B$192) -> 65 | B68: =ROUND(Guida!$B$22*H68/Guida!$B$29+Guida!$B$23*MAX(0,MIN(1,(AE68-5.4)/1.6))+Guida!$B$24*0+Guida!$B$25*0,1) -> 10.3 | C68: Obert | D68: Cagliari | E68: Braccetto / Terzino sinistro / Esterno basso | F68: 7 | G68: 7 | H68: 15 | I68: =MAX(1,ROUND(H68^Guida!$B$18*Guida!$F$12,0)) -> 6 | J68: =MAX(2,ROUND(I68*1.2,0)) -> 7 | K68: =IF(I68>=60,"Top",IF(I68>=30,"1a fascia",IF(I68>=15,"2a fascia",IF(I68>=7,"3a fascia",IF(I68>=3,"4a fascia","Scommessa"))))) -> 4a fascia | L68: Titolare | M68: Titolare confermato (2/2) | N68: - | O68: - | P68: 34 | Q68: 5.88 | R68: 5.82 | S68: 0 | T68: 3 | U68: 0/0 | V68: 8 | W68: 1 | X68: 2 | Y68: 5.75 | Z68: 5.75 | AA68: 0 | AB68: 0 | AC68: Cagliari | AD68: No | AE68: =ROUND(IF(P68="",5.5,R68*MIN(1,P68/25)+5.5*(1-MIN(1,P68/25))),2) -> 5.82 | AF68: Kristensen T. (ATA) | AG68: 6 | AH68: =RANK(H68,$H$4:$H$192) -> 58
A69: =RANK(B69,$B$4:$B$192) -> 65 | B69: =ROUND(Guida!$B$22*H69/Guida!$B$29+Guida!$B$23*MAX(0,MIN(1,(AE69-5.4)/1.6))+Guida!$B$24*0+Guida!$B$25*0,1) -> 10.3 | C69: Kamara H. | D69: Udinese | E69: Terzino sinistro / Esterno basso | F69: 6 | G69: 9 | H69: 12 | I69: =MAX(1,ROUND(H69^Guida!$B$18*Guida!$F$12,0)) -> 6 | J69: =MAX(2,ROUND(I69*1.2,0)) -> 7 | K69: =IF(I69>=60,"Top",IF(I69>=30,"1a fascia",IF(I69>=15,"2a fascia",IF(I69>=7,"3a fascia",IF(I69>=3,"4a fascia","Scommessa"))))) -> 4a fascia | L69: Titolare | M69: Titolare confermato (2/2) | N69: - | O69: - | P69: 26 | Q69: 5.88 | R69: 5.87 | S69: 0 | T69: 2 | U69: 0/0 | V69: 5 | W69: 0 | X69: 2 | Y69: 7 | Z69: 10 | AA69: 2 | AB69: 0 | AC69: Udinese | AD69: No | AE69: =ROUND(IF(P69="",5.5,R69*MIN(1,P69/25)+5.5*(1-MIN(1,P69/25))),2) -> 5.87 | AF69: Gila (MIL) | AG69: 7 | AH69: =RANK(H69,$H$4:$H$192) -> 89
A70: =RANK(B70,$B$4:$B$192) -> 67 | B70: =ROUND(Guida!$B$22*H70/Guida!$B$29+Guida!$B$23*MAX(0,MIN(1,(AE70-5.4)/1.6))+Guida!$B$24*0+Guida!$B$25*0,1) -> 10.2 | C70: Bellanova | D70: Atalanta | E70: Terzino destro / Esterno basso | F70: 6 | G70: 6 | H70: 17 | I70: =MAX(1,ROUND(H70^Guida!$B$18*Guida!$F$12,0)) -> 7 | J70: =MAX(2,ROUND(I70*1.2,0)) -> 8 | K70: =IF(I70>=60,"Top",IF(I70>=30,"1a fascia",IF(I70>=15,"2a fascia",IF(I70>=7,"3a fascia",IF(I70>=3,"4a fascia","Scommessa"))))) -> 3a fascia | L70: Ballottaggio | M70: In ballottaggio (0/2) | N70: - | O70: - | P70: 22 | Q70: 5.82 | R70: 5.82 | S70: 0 | T70: 1 | U70: 0/0 | V70: 2 | W70: 0 | X70: 0 | AC70: Atalanta | AD70: No | AE70: =ROUND(IF(P70="",5.5,R70*MIN(1,P70/25)+5.5*(1-MIN(1,P70/25))),2) -> 5.78 | AF70: Holm (BOL) | AG70: 6 | AH70: =RANK(H70,$H$4:$H$192) -> 53
A71: =RANK(B71,$B$4:$B$192) -> 68 | B71: =ROUND(Guida!$B$22*H71/Guida!$B$29+Guida!$B$23*MAX(0,MIN(1,(AE71-5.4)/1.6))+Guida!$B$24*0+Guida!$B$25*0,1) -> 10 | C71: Heggem | D71: Bologna | E71: Terzino sinistro / Difensore centrale | F71: 6 | G71: 6 | H71: 15 | I71: =MAX(1,ROUND(H71^Guida!$B$18*Guida!$F$12,0)) -> 6 | J71: =MAX(2,ROUND(I71*1.2,0)) -> 7 | K71: =IF(I71>=60,"Top",IF(I71>=30,"1a fascia",IF(I71>=15,"2a fascia",IF(I71>=7,"3a fascia",IF(I71>=3,"4a fascia","Scommessa"))))) -> 4a fascia | L71: Titolare | M71: Titolare confermato (2/2) | N71: - | O71: - | P71: 25 | Q71: 5.84 | R71: 5.8 | S71: 0 | T71: 0 | U71: 0/0 | V71: 0 | W71: 1 | X71: 2 | Y71: 5.5 | Z71: 5.25 | AA71: 0 | AB71: 0 | AC71: Bologna | AD71: No | AE71: =ROUND(IF(P71="",5.5,R71*MIN(1,P71/25)+5.5*(1-MIN(1,P71/25))),2) -> 5.8 | AF71: Bernasconi (ATA) | AG71: 6 | AH71: =RANK(H71,$H$4:$H$192) -> 58
A72: =RANK(B72,$B$4:$B$192) -> 68 | B72: =ROUND(Guida!$B$22*H72/Guida!$B$29+Guida!$B$23*MAX(0,MIN(1,(AE72-5.4)/1.6))+Guida!$B$24*0+Guida!$B$25*0,1) -> 10 | C72: Ghilardi | D72: Roma | E72: Difensore centrale | F72: 4 | G72: 5 | H72: 10 | I72: =MAX(1,ROUND(H72^Guida!$B$18*Guida!$F$12,0)) -> 5 | J72: =MAX(2,ROUND(I72*1.2,0)) -> 6 | K72: =IF(I72>=60,"Top",IF(I72>=30,"1a fascia",IF(I72>=15,"2a fascia",IF(I72>=7,"3a fascia",IF(I72>=3,"4a fascia","Scommessa"))))) -> 4a fascia | L72: Riserva | M72: Riserva (1/2) | N72: - | O72: - | P72: 21 | Q72: 5.98 | R72: 5.95 | S72: 0 | T72: 0 | U72: 0/0 | V72: 1 | W72: 0 | X72: 1 | Y72: 7 | Z72: 7 | AA72: 0 | AB72: 0 | AC72: Roma | AD72: No | AE72: =ROUND(IF(P72="",5.5,R72*MIN(1,P72/25)+5.5*(1-MIN(1,P72/25))),2) -> 5.88 | AF72: Marusic (LAZ) | AG72: 0 | AH72: =RANK(H72,$H$4:$H$192) -> 114
A73: =RANK(B73,$B$4:$B$192) -> 70 | B73: =ROUND(Guida!$B$22*H73/Guida!$B$29+Guida!$B$23*MAX(0,MIN(1,(AE73-5.4)/1.6))+Guida!$B$24*0+Guida!$B$25*0,1) -> 9.9 | C73: Hien | D73: Atalanta | E73: Difensore centrale | F73: 8 | G73: 7 | H73: 11 | I73: =MAX(1,ROUND(H73^Guida!$B$18*Guida!$F$12,0)) -> 5 | J73: =MAX(2,ROUND(I73*1.2,0)) -> 6 | K73: =IF(I73>=60,"Top",IF(I73>=30,"1a fascia",IF(I73>=15,"2a fascia",IF(I73>=7,"3a fascia",IF(I73>=3,"4a fascia","Scommessa"))))) -> 4a fascia | L73: Titolare | M73: INFORTUNATO (lungo stop) - presenze finora: 0/2 | N73: - | O73: - | P73: 28 | Q73: 5.91 | R73: 5.86 | S73: 1 | T73: 0 | U73: 0/0 | V73: 5 | W73: 0 | X73: 0 | AC73: Atalanta | AD73: No | AE73: =ROUND(IF(P73="",5.5,R73*MIN(1,P73/25)+5.5*(1-MIN(1,P73/25))),2) -> 5.86 | AF73: Holm (BOL) | AG73: 6 | AH73: =RANK(H73,$H$4:$H$192) -> 108 | AI73: Operato a fine giugno al semimembranoso della coscia sinistra. Rientro da inizio ottobre.
A74: =RANK(B74,$B$4:$B$192) -> 71 | B74: =ROUND(Guida!$B$22*H74/Guida!$B$29+Guida!$B$23*MAX(0,MIN(1,(AE74-5.4)/1.6))+Guida!$B$24*0+Guida!$B$25*0,1) -> 9.8 | C74: Provstgaard | D74: Lazio | E74: Difensore centrale | F74: 3 | G74: 4 | H74: 13 | I74: =MAX(1,ROUND(H74^Guida!$B$18*Guida!$F$12,0)) -> 6 | J74: =MAX(2,ROUND(I74*1.2,0)) -> 7 | K74: =IF(I74>=60,"Top",IF(I74>=30,"1a fascia",IF(I74>=15,"2a fascia",IF(I74>=7,"3a fascia",IF(I74>=3,"4a fascia","Scommessa"))))) -> 4a fascia | L74: Riserva | M74: Riserva (2/2) | N74: - | O74: - | P74: 23 | Q74: 5.91 | R74: 5.85 | S74: 0 | T74: 0 | U74: 0/0 | V74: 3 | W74: 0 | X74: 2 | Y74: 6 | Z74: 5.75 | AA74: 0 | AB74: 0 | AC74: Lazio | AD74: No | AE74: =ROUND(IF(P74="",5.5,R74*MIN(1,P74/25)+5.5*(1-MIN(1,P74/25))),2) -> 5.82 | AF74: Rensch (ROM) | AG74: 0 | AH74: =RANK(H74,$H$4:$H$192) -> 76
A75: =RANK(B75,$B$4:$B$192) -> 72 | B75: =ROUND(Guida!$B$22*H75/Guida!$B$29+Guida!$B$23*MAX(0,MIN(1,(AE75-5.4)/1.6))+Guida!$B$24*0+Guida!$B$25*0,1) -> 9.6 | C75: Chalobah T. | D75: Como | E75: Terzino destro / Difensore centrale | F75: 9 | G75: 10 | H75: 32 | I75: =MAX(1,ROUND(H75^Guida!$B$18*Guida!$F$12,0)) -> 10 | J75: =MAX(2,ROUND(I75*1.2,0)) -> 12 | K75: =IF(I75>=60,"Top",IF(I75>=30,"1a fascia",IF(I75>=15,"2a fascia",IF(I75>=7,"3a fascia",IF(I75>=3,"4a fascia","Scommessa"))))) -> 3a fascia | L75: Titolare | M75: Nuovo - Titolare confermato (2/2) | N75: - | O75: - | X75: 2 | Y75: 6.5 | Z75: 6.5 | AA75: 0 | AB75: 0 | AC75: - | AD75: Si | AE75: =ROUND(IF(P75="",5.5,R75*MIN(1,P75/25)+5.5*(1-MIN(1,P75/25))),2) -> 5.5 | AF75: Dodò (FIO) | AG75: 6 | AH75: =RANK(H75,$H$4:$H$192) -> 17
A76: =RANK(B76,$B$4:$B$192) -> 73 | B76: =ROUND(Guida!$B$22*H76/Guida!$B$29+Guida!$B$23*MAX(0,MIN(1,(AE76-5.4)/1.6))+Guida!$B$24*0+Guida!$B$25*0,1) -> 9.5 | C76: Tomori | D76: Milan | E76: Difensore centrale | F76: 7 | G76: 6 | H76: 8 | I76: =MAX(1,ROUND(H76^Guida!$B$18*Guida!$F$12,0)) -> 4 | J76: =MAX(2,ROUND(I76*1.2,0)) -> 5 | K76: =IF(I76>=60,"Top",IF(I76>=30,"1a fascia",IF(I76>=15,"2a fascia",IF(I76>=7,"3a fascia",IF(I76>=3,"4a fascia","Scommessa"))))) -> 4a fascia | L76: Ballottaggio | M76: In ballottaggio (0/2) | N76: - | O76: - | P76: 32 | Q76: 5.97 | R76: 5.88 | S76: 0 | T76: 1 | U76: 0/0 | V76: 6 | W76: 1 | X76: 0 | AC76: Milan | AD76: No | AE76: =ROUND(IF(P76="",5.5,R76*MIN(1,P76/25)+5.5*(1-MIN(1,P76/25))),2) -> 5.88 | AF76: Spence (INT) | AG76: 0 | AH76: =RANK(H76,$H$4:$H$192) -> 138
A77: =RANK(B77,$B$4:$B$192) -> 74 | B77: =ROUND(Guida!$B$22*H77/Guida!$B$29+Guida!$B$23*MAX(0,MIN(1,(AE77-5.4)/1.6))+Guida!$B$24*0+Guida!$B$25*0,1) -> 9.4 | C77: Bertola | D77: Udinese | E77: Terzino destro / Terzino sinistro / Difensore centrale | F77: 4 | G77: 4 | H77: 10 | I77: =MAX(1,ROUND(H77^Guida!$B$18*Guida!$F$12,0)) -> 5 | J77: =MAX(2,ROUND(I77*1.2,0)) -> 6 | K77: =IF(I77>=60,"Top",IF(I77>=30,"1a fascia",IF(I77>=15,"2a fascia",IF(I77>=7,"3a fascia",IF(I77>=3,"4a fascia","Scommessa"))))) -> 4a fascia | L77: Ballottaggio | M77: In ballottaggio (1/2) | N77: - | O77: - | P77: 25 | Q77: 5.86 | R77: 5.84 | S77: 0 | T77: 1 | U77: 0/0 | V77: 3 | W77: 0 | X77: 1 | Y77: 6 | Z77: 6 | AA77: 0 | AB77: 0 | AC77: Udinese | AD77: No | AE77: =ROUND(IF(P77="",5.5,R77*MIN(1,P77/25)+5.5*(1-MIN(1,P77/25))),2) -> 5.84 | AF77: Gila (MIL) | AG77: 7 | AH77: =RANK(H77,$H$4:$H$192) -> 114
A78: =RANK(B78,$B$4:$B$192) -> 74 | B78: =ROUND(Guida!$B$22*H78/Guida!$B$29+Guida!$B$23*MAX(0,MIN(1,(AE78-5.4)/1.6))+Guida!$B$24*0+Guida!$B$25*0,1) -> 9.4 | C78: Smolcic I. | D78: Como | E78: Terzino destro / Esterno basso | F78: 4 | G78: 4 | H78: 10 | I78: =MAX(1,ROUND(H78^Guida!$B$18*Guida!$F$12,0)) -> 5 | J78: =MAX(2,ROUND(I78*1.2,0)) -> 6 | K78: =IF(I78>=60,"Top",IF(I78>=30,"1a fascia",IF(I78>=15,"2a fascia",IF(I78>=7,"3a fascia",IF(I78>=3,"4a fascia","Scommessa"))))) -> 4a fascia | L78: Riserva | M78: Riserva (1/2) | N78: - | O78: - | P78: 25 | Q78: 5.96 | R78: 5.84 | S78: 0 | T78: 1 | U78: 0/0 | V78: 8 | W78: 0 | X78: 1 | Y78: 5.5 | Z78: 5.5 | AA78: 0 | AB78: 0 | AC78: Como | AD78: No | AE78: =ROUND(IF(P78="",5.5,R78*MIN(1,P78/25)+5.5*(1-MIN(1,P78/25))),2) -> 5.84 | AF78: Dodò (FIO) | AG78: 6 | AH78: =RANK(H78,$H$4:$H$192) -> 114
A79: =RANK(B79,$B$4:$B$192) -> 76 | B79: =ROUND(Guida!$B$22*H79/Guida!$B$29+Guida!$B$23*MAX(0,MIN(1,(AE79-5.4)/1.6))+Guida!$B$24*0+Guida!$B$25*0,1) -> 9.2 | C79: Valenti | D79: Parma | E79: Difensore centrale | F79: 4 | G79: 4 | H79: 10 | I79: =MAX(1,ROUND(H79^Guida!$B$18*Guida!$F$12,0)) -> 5 | J79: =MAX(2,ROUND(I79*1.2,0)) -> 6 | K79: =IF(I79>=60,"Top",IF(I79>=30,"1a fascia",IF(I79>=15,"2a fascia",IF(I79>=7,"3a fascia",IF(I79>=3,"4a fascia","Scommessa"))))) -> 4a fascia | L79: Titolare | M79: RISCHIA il posto (0/2) | N79: - | O79: - | P79: 27 | Q79: 5.96 | R79: 5.83 | S79: 0 | T79: 0 | U79: 0/0 | V79: 7 | W79: 0 | X79: 0 | AC79: Parma | AD79: No | AE79: =ROUND(IF(P79="",5.5,R79*MIN(1,P79/25)+5.5*(1-MIN(1,P79/25))),2) -> 5.83 | AF79: Tiago Gabriel (LEC) | AG79: 4 | AH79: =RANK(H79,$H$4:$H$192) -> 114
A80: =RANK(B80,$B$4:$B$192) -> 77 | B80: =ROUND(Guida!$B$22*H80/Guida!$B$29+Guida!$B$23*MAX(0,MIN(1,(AE80-5.4)/1.6))+Guida!$B$24*0+Guida!$B$25*0,1) -> 8.9 | C80: Joao Mario | D80: Fiorentina | E80: Terzino destro / Esterno basso | F80: 3 | G80: 3 | H80: 12 | I80: =MAX(1,ROUND(H80^Guida!$B$18*Guida!$F$12,0)) -> 6 | J80: =MAX(2,ROUND(I80*1.2,0)) -> 7 | K80: =IF(I80>=60,"Top",IF(I80>=30,"1a fascia",IF(I80>=15,"2a fascia",IF(I80>=7,"3a fascia",IF(I80>=3,"4a fascia","Scommessa"))))) -> 4a fascia | L80: Riserva | M80: Nuovo - Riserva (1/2) | N80: - | O80: - | P80: 14 | Q80: 5.79 | R80: 6 | S80: 1 | T80: 1 | U80: 0/0 | V80: 2 | W80: 0 | X80: 1 | Y80: 5 | Z80: 5 | AA80: 0 | AB80: 0 | AC80: Bologna | AD80: Si | AE80: =ROUND(IF(P80="",5.5,R80*MIN(1,P80/25)+5.5*(1-MIN(1,P80/25))),2) -> 5.78 | AF80: Tiago Gabriel (LEC) | AG80: 6 | AH80: =RANK(H80,$H$4:$H$192) -> 89
A81: =RANK(B81,$B$4:$B$192) -> 78 | B81: =ROUND(Guida!$B$22*H81/Guida!$B$29+Guida!$B$23*MAX(0,MIN(1,(AE81-5.4)/1.6))+Guida!$B$24*0+Guida!$B$25*0,1) -> 8.6 | C81: Comuzzo | D81: Torino | E81: Difensore centrale | F81: 6 | G81: 8 | H81: 13 | I81: =MAX(1,ROUND(H81^Guida!$B$18*Guida!$F$12,0)) -> 6 | J81: =MAX(2,ROUND(I81*1.2,0)) -> 7 | K81: =IF(I81>=60,"Top",IF(I81>=30,"1a fascia",IF(I81>=15,"2a fascia",IF(I81>=7,"3a fascia",IF(I81>=3,"4a fascia","Scommessa"))))) -> 4a fascia | L81: Titolare | M81: Nuovo - Titolare confermato (2/2) | N81: - | O81: - | P81: 24 | Q81: 5.75 | R81: 5.75 | S81: 1 | T81: 0 | U81: 0/0 | V81: 2 | W81: 0 | X81: 2 | Y81: 6.25 | Z81: 7.75 | AA81: 1 | AB81: 0 | AC81: Fiorentina | AD81: Si | AE81: =ROUND(IF(P81="",5.5,R81*MIN(1,P81/25)+5.5*(1-MIN(1,P81/25))),2) -> 5.74 | AF81: Cambiaso (JUV) | AG81: 0 | AH81: =RANK(H81,$H$4:$H$192) -> 76
A82: =RANK(B82,$B$4:$B$192) -> 78 | B82: =ROUND(Guida!$B$22*H82/Guida!$B$29+Guida!$B$23*MAX(0,MIN(1,(AE82-5.4)/1.6))+Guida!$B$24*0+Guida!$B$25*0,1) -> 8.6 | C82: Ranieri L. | D82: Fiorentina | E82: Terzino sinistro / Difensore centrale | F82: 3 | G82: 3 | H82: 10 | I82: =MAX(1,ROUND(H82^Guida!$B$18*Guida!$F$12,0)) -> 5 | J82: =MAX(2,ROUND(I82*1.2,0)) -> 6 | K82: =IF(I82>=60,"Top",IF(I82>=30,"1a fascia",IF(I82>=15,"2a fascia",IF(I82>=7,"3a fascia",IF(I82>=3,"4a fascia","Scommessa"))))) -> 4a fascia | L82: Riserva | M82: Riserva (1/2) | N82: - | O82: - | P82: 31 | Q82: 5.85 | R82: 5.79 | S82: 1 | T82: 0 | U82: 0/0 | V82: 8 | W82: 1 | X82: 1 | Y82: 5 | Z82: 5 | AA82: 0 | AB82: 0 | AC82: Fiorentina | AD82: No | AE82: =ROUND(IF(P82="",5.5,R82*MIN(1,P82/25)+5.5*(1-MIN(1,P82/25))),2) -> 5.79 | AF82: Tiago Gabriel (LEC) | AG82: 6 | AH82: =RANK(H82,$H$4:$H$192) -> 114
A83: =RANK(B83,$B$4:$B$192) -> 78 | B83: =ROUND(Guida!$B$22*H83/Guida!$B$29+Guida!$B$23*MAX(0,MIN(1,(AE83-5.4)/1.6))+Guida!$B$24*0+Guida!$B$25*0,1) -> 8.6 | C83: Idrissi R. | D83: Cagliari | E83: Terzino sinistro / Esterno basso | F83: 3 | G83: 3 | H83: 3 | I83: =MAX(1,ROUND(H83^Guida!$B$18*Guida!$F$12,0)) -> 2 | J83: =MAX(2,ROUND(I83*1.2,0)) -> 2 | K83: =IF(I83>=60,"Top",IF(I83>=30,"1a fascia",IF(I83>=15,"2a fascia",IF(I83>=7,"3a fascia",IF(I83>=3,"4a fascia","Scommessa"))))) -> Scommessa | L83: Riserva | M83: INFORTUNATO (lungo stop) - presenze finora: 0/2 | N83: - | O83: - | P83: 17 | Q83: 5.82 | R83: 6.09 | S83: 2 | T83: 0 | U83: 0/0 | V83: 3 | W83: 0 | X83: 0 | AC83: Cagliari | AD83: No | AE83: =ROUND(IF(P83="",5.5,R83*MIN(1,P83/25)+5.5*(1-MIN(1,P83/25))),2) -> 5.9 | AF83: Parisi (FIO) | AG83: 6 | AH83: =RANK(H83,$H$4:$H$192) -> 175 | AI83: In ripresa dalla rottura del crociato. Arruolabile da fine ottobre.
A84: =RANK(B84,$B$4:$B$192) -> 81 | B84: =ROUND(Guida!$B$22*H84/Guida!$B$29+Guida!$B$23*MAX(0,MIN(1,(AE84-5.4)/1.6))+Guida!$B$24*0+Guida!$B$25*0,1) -> 8.5 | C84: Cabal | D84: Juventus | E84: Braccetto / Terzino sinistro / Esterno basso | F84: 1 | G84: 1 | H84: 4 | I84: =MAX(1,ROUND(H84^Guida!$B$18*Guida!$F$12,0)) -> 3 | J84: =MAX(2,ROUND(I84*1.2,0)) -> 4 | K84: =IF(I84>=60,"Top",IF(I84>=30,"1a fascia",IF(I84>=15,"2a fascia",IF(I84>=7,"3a fascia",IF(I84>=3,"4a fascia","Scommessa"))))) -> 4a fascia | L84: Riserva | M84: Riserva (0/2) | N84: - | O84: - | P84: 9 | Q84: 5.94 | R84: 6.56 | S84: 2 | T84: 0 | U84: 0/0 | V84: 1 | W84: 0 | X84: 0 | AC84: Juventus | AD84: No | AE84: =ROUND(IF(P84="",5.5,R84*MIN(1,P84/25)+5.5*(1-MIN(1,P84/25))),2) -> 5.88 | AF84: Coco (TOR) | AG84: 0 | AH84: =RANK(H84,$H$4:$H$192) -> 167
A85: =RANK(B85,$B$4:$B$192) -> 82 | B85: =ROUND(Guida!$B$22*H85/Guida!$B$29+Guida!$B$23*MAX(0,MIN(1,(AE85-5.4)/1.6))+Guida!$B$24*0+Guida!$B$25*0,1) -> 8.4 | C85: Van Der Brempt | D85: Sassuolo | E85: Terzino destro / Esterno basso | F85: 2 | G85: 2 | H85: 11 | I85: =MAX(1,ROUND(H85^Guida!$B$18*Guida!$F$12,0)) -> 5 | J85: =MAX(2,ROUND(I85*1.2,0)) -> 6 | K85: =IF(I85>=60,"Top",IF(I85>=30,"1a fascia",IF(I85>=15,"2a fascia",IF(I85>=7,"3a fascia",IF(I85>=3,"4a fascia","Scommessa"))))) -> 4a fascia | L85: Riserva | M85: Nuovo - Riserva (0/2) | N85: - | O85: - | P85: 14 | Q85: 5.96 | R85: 5.96 | S85: 0 | T85: 1 | U85: 0/0 | V85: 2 | W85: 0 | X85: 0 | AC85: Como | AD85: Si | AE85: =ROUND(IF(P85="",5.5,R85*MIN(1,P85/25)+5.5*(1-MIN(1,P85/25))),2) -> 5.76 | AF85: Spence (INT) | AG85: 4 | AH85: =RANK(H85,$H$4:$H$192) -> 108
A86: =RANK(B86,$B$4:$B$192) -> 83 | B86: =ROUND(Guida!$B$22*H86/Guida!$B$29+Guida!$B$23*MAX(0,MIN(1,(AE86-5.4)/1.6))+Guida!$B$24*0+Guida!$B$25*0,1) -> 8.2 | C86: Kolasinac | D86: Atalanta | E86: Terzino sinistro / Difensore centrale | F86: 5 | G86: 6 | H86: 8 | I86: =MAX(1,ROUND(H86^Guida!$B$18*Guida!$F$12,0)) -> 4 | J86: =MAX(2,ROUND(I86*1.2,0)) -> 5 | K86: =IF(I86>=60,"Top",IF(I86>=30,"1a fascia",IF(I86>=15,"2a fascia",IF(I86>=7,"3a fascia",IF(I86>=3,"4a fascia","Scommessa"))))) -> 4a fascia | L86: Riserva | M86: Riserva (2/2) | N86: - | O86: - | P86: 17 | Q86: 6.03 | R86: 5.94 | S86: 0 | T86: 0 | U86: 0/0 | V86: 3 | W86: 0 | X86: 2 | Y86: 6 | Z86: 6 | AA86: 0 | AB86: 0 | AC86: Atalanta | AD86: No | AE86: =ROUND(IF(P86="",5.5,R86*MIN(1,P86/25)+5.5*(1-MIN(1,P86/25))),2) -> 5.8 | AF86: Zortea (BOL) | AG86: 6 | AH86: =RANK(H86,$H$4:$H$192) -> 138
A87: =RANK(B87,$B$4:$B$192) -> 84 | B87: =ROUND(Guida!$B$22*H87/Guida!$B$29+Guida!$B$23*MAX(0,MIN(1,(AE87-5.4)/1.6))+Guida!$B$24*0+Guida!$B$25*0,1) -> 8.1 | C87: Doig | D87: Sassuolo | E87: Terzino sinistro / Esterno basso | F87: 4 | G87: 5 | H87: 10 | I87: =MAX(1,ROUND(H87^Guida!$B$18*Guida!$F$12,0)) -> 5 | J87: =MAX(2,ROUND(I87*1.2,0)) -> 6 | K87: =IF(I87>=60,"Top",IF(I87>=30,"1a fascia",IF(I87>=15,"2a fascia",IF(I87>=7,"3a fascia",IF(I87>=3,"4a fascia","Scommessa"))))) -> 4a fascia | L87: Ballottaggio | M87: In ballottaggio (2/2) | N87: - | O87: - | P87: 27 | Q87: 5.85 | R87: 5.76 | S87: 0 | T87: 0 | U87: 0/0 | V87: 5 | W87: 0 | X87: 2 | Y87: 6 | Z87: 6 | AA87: 0 | AB87: 0 | AC87: Sassuolo | AD87: No | AE87: =ROUND(IF(P87="",5.5,R87*MIN(1,P87/25)+5.5*(1-MIN(1,P87/25))),2) -> 5.76 | AF87: Spence (INT) | AG87: 4 | AH87: =RANK(H87,$H$4:$H$192) -> 114
A88: =RANK(B88,$B$4:$B$192) -> 84 | B88: =ROUND(Guida!$B$22*H88/Guida!$B$29+Guida!$B$23*MAX(0,MIN(1,(AE88-5.4)/1.6))+Guida!$B$24*0+Guida!$B$25*0,1) -> 8.1 | C88: Vitik | D88: Bologna | E88: Difensore centrale | F88: 5 | G88: 4 | H88: 10 | I88: =MAX(1,ROUND(H88^Guida!$B$18*Guida!$F$12,0)) -> 5 | J88: =MAX(2,ROUND(I88*1.2,0)) -> 6 | K88: =IF(I88>=60,"Top",IF(I88>=30,"1a fascia",IF(I88>=15,"2a fascia",IF(I88>=7,"3a fascia",IF(I88>=3,"4a fascia","Scommessa"))))) -> 4a fascia | L88: Ballottaggio | M88: In ballottaggio (0/2) | N88: - | O88: - | P88: 18 | Q88: 5.94 | R88: 5.86 | S88: 0 | T88: 0 | U88: 0/0 | V88: 3 | W88: 0 | X88: 0 | AC88: Bologna | AD88: No | AE88: =ROUND(IF(P88="",5.5,R88*MIN(1,P88/25)+5.5*(1-MIN(1,P88/25))),2) -> 5.76 | AF88: Beukema (NAP) | AG88: 6 | AH88: =RANK(H88,$H$4:$H$192) -> 114
A89: =RANK(B89,$B$4:$B$192) -> 86 | B89: =ROUND(Guida!$B$22*H89/Guida!$B$29+Guida!$B$23*MAX(0,MIN(1,(AE89-5.4)/1.6))+Guida!$B$24*0+Guida!$B$25*0,1) -> 8 | C89: Fortini | D89: Torino | E89: Esterno basso | F89: 5 | G89: 6 | H89: 12 | I89: =MAX(1,ROUND(H89^Guida!$B$18*Guida!$F$12,0)) -> 6 | J89: =MAX(2,ROUND(I89*1.2,0)) -> 7 | K89: =IF(I89>=60,"Top",IF(I89>=30,"1a fascia",IF(I89>=15,"2a fascia",IF(I89>=7,"3a fascia",IF(I89>=3,"4a fascia","Scommessa"))))) -> 4a fascia | L89: Ballottaggio | M89: Nuovo - In ballottaggio (2/2) | N89: - | O89: - | P89: 12 | Q89: 5.96 | R89: 5.96 | S89: 0 | T89: 0 | U89: 0/0 | V89: 0 | W89: 0 | X89: 2 | Y89: 6 | Z89: 6 | AA89: 0 | AB89: 0 | AC89: Fiorentina | AD89: Si | AE89: =ROUND(IF(P89="",5.5,R89*MIN(1,P89/25)+5.5*(1-MIN(1,P89/25))),2) -> 5.72 | AF89: Kelly L. (JUV) | AG89: 0 | AH89: =RANK(H89,$H$4:$H$192) -> 89
A90: =RANK(B90,$B$4:$B$192) -> 86 | B90: =ROUND(Guida!$B$22*H90/Guida!$B$29+Guida!$B$23*MAX(0,MIN(1,(AE90-5.4)/1.6))+Guida!$B$24*0+Guida!$B$25*0,1) -> 8 | C90: Pellegrini Lu. | D90: Lazio | E90: Terzino sinistro / Esterno basso | F90: 2 | G90: 2 | H90: 7 | I90: =MAX(1,ROUND(H90^Guida!$B$18*Guida!$F$12,0)) -> 4 | J90: =MAX(2,ROUND(I90*1.2,0)) -> 5 | K90: =IF(I90>=60,"Top",IF(I90>=30,"1a fascia",IF(I90>=15,"2a fascia",IF(I90>=7,"3a fascia",IF(I90>=3,"4a fascia","Scommessa"))))) -> 4a fascia | L90: Riserva | M90: Riserva (0/2) | N90: - | O90: - | P90: 24 | Q90: 5.85 | R90: 5.81 | S90: 1 | T90: 0 | U90: 0/0 | V90: 8 | W90: 0 | X90: 0 | AC90: Lazio | AD90: No | AE90: =ROUND(IF(P90="",5.5,R90*MIN(1,P90/25)+5.5*(1-MIN(1,P90/25))),2) -> 5.8 | AF90: Coco (TOR) | AG90: 6 | AH90: =RANK(H90,$H$4:$H$192) -> 151
A91: =RANK(B91,$B$4:$B$192) -> 88 | B91: =ROUND(Guida!$B$22*H91/Guida!$B$29+Guida!$B$23*MAX(0,MIN(1,(AE91-5.4)/1.6))+Guida!$B$24*0+Guida!$B$25*0,1) -> 7.9 | C91: Troilo | D91: Parma | E91: Difensore centrale | F91: 3 | G91: 3 | H91: 14 | I91: =MAX(1,ROUND(H91^Guida!$B$18*Guida!$F$12,0)) -> 6 | J91: =MAX(2,ROUND(I91*1.2,0)) -> 7 | K91: =IF(I91>=60,"Top",IF(I91>=30,"1a fascia",IF(I91>=15,"2a fascia",IF(I91>=7,"3a fascia",IF(I91>=3,"4a fascia","Scommessa"))))) -> 4a fascia | L91: Ballottaggio | M91: In ballottaggio (2/2) | N91: - | O91: - | P91: 21 | Q91: 5.79 | R91: 5.71 | S91: 1 | T91: 0 | U91: 0/0 | V91: 5 | W91: 2 | X91: 2 | Y91: 5.5 | Z91: 5.25 | AA91: 0 | AB91: 0 | AC91: Parma | AD91: No | AE91: =ROUND(IF(P91="",5.5,R91*MIN(1,P91/25)+5.5*(1-MIN(1,P91/25))),2) -> 5.68 | AF91: Idzes (SAS) | AG91: 4 | AH91: =RANK(H91,$H$4:$H$192) -> 68
A92: =RANK(B92,$B$4:$B$192) -> 89 | B92: =ROUND(Guida!$B$22*H92/Guida!$B$29+Guida!$B$23*MAX(0,MIN(1,(AE92-5.4)/1.6))+Guida!$B$24*0+Guida!$B$25*0,1) -> 7.8 | C92: Couto | D92: Como | E92: Terzino destro / Esterno basso | F92: 8 | G92: 8 | H92: 25 | I92: =MAX(1,ROUND(H92^Guida!$B$18*Guida!$F$12,0)) -> 9 | J92: =MAX(2,ROUND(I92*1.2,0)) -> 11 | K92: =IF(I92>=60,"Top",IF(I92>=30,"1a fascia",IF(I92>=15,"2a fascia",IF(I92>=7,"3a fascia",IF(I92>=3,"4a fascia","Scommessa"))))) -> 3a fascia | L92: Titolare | M92: Nuovo - Titolare confermato (2/2) | N92: - | O92: - | X92: 2 | Y92: 5.5 | Z92: 5.5 | AA92: 0 | AB92: 0 | AC92: - | AD92: Si | AE92: =ROUND(IF(P92="",5.5,R92*MIN(1,P92/25)+5.5*(1-MIN(1,P92/25))),2) -> 5.5 | AF92: Parisi (FIO) | AG92: 6 | AH92: =RANK(H92,$H$4:$H$192) -> 24
A93: =RANK(B93,$B$4:$B$192) -> 89 | B93: =ROUND(Guida!$B$22*H93/Guida!$B$29+Guida!$B$23*MAX(0,MIN(1,(AE93-5.4)/1.6))+Guida!$B$24*0+Guida!$B$25*0,1) -> 7.8 | C93: Stones | D93: Inter | E93: Difensore centrale | F93: 12 | G93: 12 | H93: 25 | I93: =MAX(1,ROUND(H93^Guida!$B$18*Guida!$F$12,0)) -> 9 | J93: =MAX(2,ROUND(I93*1.2,0)) -> 11 | K93: =IF(I93>=60,"Top",IF(I93>=30,"1a fascia",IF(I93>=15,"2a fascia",IF(I93>=7,"3a fascia",IF(I93>=3,"4a fascia","Scommessa"))))) -> 3a fascia | L93: Ballottaggio | M93: Nuovo - In ballottaggio (2/2) | N93: - | O93: - | X93: 2 | Y93: 6 | Z93: 6 | AA93: 0 | AB93: 0 | AC93: - | AD93: Si | AE93: =ROUND(IF(P93="",5.5,R93*MIN(1,P93/25)+5.5*(1-MIN(1,P93/25))),2) -> 5.5 | AF93: De Winter (MIL) | AG93: 0 | AH93: =RANK(H93,$H$4:$H$192) -> 24
A94: =RANK(B94,$B$4:$B$192) -> 89 | B94: =ROUND(Guida!$B$22*H94/Guida!$B$29+Guida!$B$23*MAX(0,MIN(1,(AE94-5.4)/1.6))+Guida!$B$24*0+Guida!$B$25*0,1) -> 7.8 | C94: Walukiewicz | D94: Sassuolo | E94: Terzino destro / Difensore centrale | F94: 4 | G94: 4 | H94: 10 | I94: =MAX(1,ROUND(H94^Guida!$B$18*Guida!$F$12,0)) -> 5 | J94: =MAX(2,ROUND(I94*1.2,0)) -> 6 | K94: =IF(I94>=60,"Top",IF(I94>=30,"1a fascia",IF(I94>=15,"2a fascia",IF(I94>=7,"3a fascia",IF(I94>=3,"4a fascia","Scommessa"))))) -> 4a fascia | L94: Ballottaggio | M94: Infortunato - presenze finora: 0/2 | N94: - | O94: - | P94: 34 | Q94: 5.81 | R94: 5.74 | S94: 0 | T94: 1 | U94: 0/0 | V94: 7 | W94: 0 | X94: 0 | AC94: Sassuolo | AD94: No | AE94: =ROUND(IF(P94="",5.5,R94*MIN(1,P94/25)+5.5*(1-MIN(1,P94/25))),2) -> 5.74 | AF94: Spence (INT) | AG94: 4 | AH94: =RANK(H94,$H$4:$H$192) -> 114 | AI94: Forte trauma contusivo alla gamba destra. Rientro da valutare a meta settembre.
A95: =RANK(B95,$B$4:$B$192) -> 92 | B95: =ROUND(Guida!$B$22*H95/Guida!$B$29+Guida!$B$23*MAX(0,MIN(1,(AE95-5.4)/1.6))+Guida!$B$24*0+Guida!$B$25*0,1) -> 7.7 | C95: Siebert | D95: Lecce | E95: Difensore centrale | F95: 4 | G95: 4 | H95: 12 | I95: =MAX(1,ROUND(H95^Guida!$B$18*Guida!$F$12,0)) -> 6 | J95: =MAX(2,ROUND(I95*1.2,0)) -> 7 | K95: =IF(I95>=60,"Top",IF(I95>=30,"1a fascia",IF(I95>=15,"2a fascia",IF(I95>=7,"3a fascia",IF(I95>=3,"4a fascia","Scommessa"))))) -> 4a fascia | L95: Ballottaggio | M95: In ballottaggio (2/2) | N95: - | O95: - | P95: 19 | Q95: 5.68 | R95: 5.76 | S95: 1 | T95: 0 | U95: 0/0 | V95: 3 | W95: 0 | X95: 2 | Y95: 5.5 | Z95: 5.5 | AA95: 0 | AB95: 0 | AC95: Lecce | AD95: No | AE95: =ROUND(IF(P95="",5.5,R95*MIN(1,P95/25)+5.5*(1-MIN(1,P95/25))),2) -> 5.7 | AF95: Zortea (BOL) | AG95: 6 | AH95: =RANK(H95,$H$4:$H$192) -> 89
A96: =RANK(B96,$B$4:$B$192) -> 92 | B96: =ROUND(Guida!$B$22*H96/Guida!$B$29+Guida!$B$23*MAX(0,MIN(1,(AE96-5.4)/1.6))+Guida!$B$24*0+Guida!$B$25*0,1) -> 7.7 | C96: Terracciano F. | D96: Milan | E96: Braccetto / Terzino destro / Terzino sinistro | F96: 2 | G96: 2 | H96: 4 | I96: =MAX(1,ROUND(H96^Guida!$B$18*Guida!$F$12,0)) -> 3 | J96: =MAX(2,ROUND(I96*1.2,0)) -> 4 | K96: =IF(I96>=60,"Top",IF(I96>=30,"1a fascia",IF(I96>=15,"2a fascia",IF(I96>=7,"3a fascia",IF(I96>=3,"4a fascia","Scommessa"))))) -> 4a fascia | L96: Riserva | M96: Nuovo - Riserva (0/2) | N96: - | O96: - | P96: 35 | Q96: 5.86 | R96: 5.83 | S96: 2 | T96: 0 | U96: 0/0 | V96: 6 | W96: 0 | X96: 0 | AC96: Cremonese | AD96: Si | AE96: =ROUND(IF(P96="",5.5,R96*MIN(1,P96/25)+5.5*(1-MIN(1,P96/25))),2) -> 5.83 | AF96: Spence (INT) | AG96: 0 | AH96: =RANK(H96,$H$4:$H$192) -> 167
A97: =RANK(B97,$B$4:$B$192) -> 94 | B97: =ROUND(Guida!$B$22*H97/Guida!$B$29+Guida!$B$23*MAX(0,MIN(1,(AE97-5.4)/1.6))+Guida!$B$24*0+Guida!$B$25*0,1) -> 7.6 | C97: Bella-Kotchap | D97: Venezia | E97: Difensore centrale | F97: 6 | G97: 5 | H97: 13 | I97: =MAX(1,ROUND(H97^Guida!$B$18*Guida!$F$12,0)) -> 6 | J97: =MAX(2,ROUND(I97*1.2,0)) -> 7 | K97: =IF(I97>=60,"Top",IF(I97>=30,"1a fascia",IF(I97>=15,"2a fascia",IF(I97>=7,"3a fascia",IF(I97>=3,"4a fascia","Scommessa"))))) -> 4a fascia | L97: Titolare | M97: Nuovo - Titolare confermato (2/2) | N97: - | O97: - | P97: 18 | Q97: 5.83 | R97: 5.75 | S97: 0 | T97: 0 | U97: 0/0 | V97: 3 | W97: 0 | X97: 2 | Y97: 5 | Z97: 5 | AA97: 0 | AB97: 0 | AC97: Verona | AD97: Si | AE97: =ROUND(IF(P97="",5.5,R97*MIN(1,P97/25)+5.5*(1-MIN(1,P97/25))),2) -> 5.68 | AF97: Buongiorno (NAP) | AG97: 7 | AH97: =RANK(H97,$H$4:$H$192) -> 76
A98: =RANK(B98,$B$4:$B$192) -> 95 | B98: =ROUND(Guida!$B$22*H98/Guida!$B$29+Guida!$B$23*MAX(0,MIN(1,(AE98-5.4)/1.6))+Guida!$B$24*0+Guida!$B$25*0,1) -> 7.5 | C98: Veiga D. | D98: Lecce | E98: Terzino destro / Esterno basso | F98: 5 | G98: 6 | H98: 12 | I98: =MAX(1,ROUND(H98^Guida!$B$18*Guida!$F$12,0)) -> 6 | J98: =MAX(2,ROUND(I98*1.2,0)) -> 7 | K98: =IF(I98>=60,"Top",IF(I98>=30,"1a fascia",IF(I98>=15,"2a fascia",IF(I98>=7,"3a fascia",IF(I98>=3,"4a fascia","Scommessa"))))) -> 4a fascia | L98: Titolare | M98: Titolare confermato (2/2) | N98: - | O98: - | P98: 36 | Q98: 5.82 | R98: 5.69 | S98: 0 | T98: 0 | U98: 0/0 | V98: 9 | W98: 0 | X98: 2 | Y98: 5.75 | Z98: 6 | AA98: 0 | AB98: 1 | AC98: Lecce | AD98: No | AE98: =ROUND(IF(P98="",5.5,R98*MIN(1,P98/25)+5.5*(1-MIN(1,P98/25))),2) -> 5.69 | AF98: Parisi (FIO) | AG98: 6 | AH98: =RANK(H98,$H$4:$H$192) -> 89
A99: =RANK(B99,$B$4:$B$192) -> 96 | B99: =ROUND(Guida!$B$22*H99/Guida!$B$29+Guida!$B$23*MAX(0,MIN(1,(AE99-5.4)/1.6))+Guida!$B$24*0+Guida!$B$25*0,1) -> 7.3 | C99: Olivera | D99: Napoli | E99: Braccetto / Terzino sinistro / Esterno basso | F99: 5 | G99: 5 | H99: 13 | I99: =MAX(1,ROUND(H99^Guida!$B$18*Guida!$F$12,0)) -> 6 | J99: =MAX(2,ROUND(I99*1.2,0)) -> 7 | K99: =IF(I99>=60,"Top",IF(I99>=30,"1a fascia",IF(I99>=15,"2a fascia",IF(I99>=7,"3a fascia",IF(I99>=3,"4a fascia","Scommessa"))))) -> 4a fascia | L99: Riserva | M99: Riserva (1/2) | N99: - | O99: - | P99: 22 | Q99: 5.75 | R99: 5.68 | S99: 0 | T99: 0 | U99: 0/0 | V99: 3 | W99: 0 | X99: 1 | Y99: 5 | Z99: 5 | AA99: 0 | AB99: 0 | AC99: Napoli | AD99: No | AE99: =ROUND(IF(P99="",5.5,R99*MIN(1,P99/25)+5.5*(1-MIN(1,P99/25))),2) -> 5.66 | AF99: Coco (TOR) | AG99: 7 | AH99: =RANK(H99,$H$4:$H$192) -> 76
A100: =RANK(B100,$B$4:$B$192) -> 96 | B100: =ROUND(Guida!$B$22*H100/Guida!$B$29+Guida!$B$23*MAX(0,MIN(1,(AE100-5.4)/1.6))+Guida!$B$24*0+Guida!$B$25*0,1) -> 7.3 | C100: Zè Pedro | D100: Cagliari | E100: Terzino destro / Difensore centrale | F100: 5 | G100: 5 | H100: 13 | I100: =MAX(1,ROUND(H100^Guida!$B$18*Guida!$F$12,0)) -> 6 | J100: =MAX(2,ROUND(I100*1.2,0)) -> 7 | K100: =IF(I100>=60,"Top",IF(I100>=30,"1a fascia",IF(I100>=15,"2a fascia",IF(I100>=7,"3a fascia",IF(I100>=3,"4a fascia","Scommessa"))))) -> 4a fascia | L100: Titolare | M100: Titolare confermato (2/2) | N100: - | O100: - | P100: 22 | Q100: 5.77 | R100: 5.68 | S100: 0 | T100: 1 | U100: 0/0 | V100: 6 | W100: 0 | X100: 2 | Y100: 5.75 | Z100: 5.5 | AA100: 0 | AB100: 0 | AC100: Cagliari | AD100: No | AE100: =ROUND(IF(P100="",5.5,R100*MIN(1,P100/25)+5.5*(1-MIN(1,P100/25))),2) -> 5.66 | AF100: Parisi (FIO) | AG100: 6 | AH100: =RANK(H100,$H$4:$H$192) -> 76
...

Sheet Centrocampisti
A1: CENTROCAMPISTI - Listone Fantacalcio Classic 2026/27
A2: 193 giocatori, solo quelli presenti nelle rose ufficiali di Serie A 2026/27. Ordinati per indice di priorita. Colonna NOTA: infortuni, rischio titolarita e nuovi acquisti (dati al 01/09/2026, dopo 2 giornate).
A3: Prio | B3: Indice | C3: Giocatore | D3: Squadra | E3: Ruolo Mantra | F3: Qt.I | G3: Qt.A | H3: FVM | I3: Prezzo consigliato | J3: Prezzo max | K3: Fascia | L3: Gerarchia stimata | M3: NOTA | N3: Rigorista | O3: Calci piazzati | P3: PG 25/26 | Q3: MV 25/26 | R3: FM 25/26 | S3: Gol 25/26 | T3: Assist 25/26 | U3: Rig. segnati 25/26 | V3: Amm. 25/26 | W3: Esp. 25/26 | X3: PG 26/27 (su 2) | Y3: MV 26/27 | Z3: FM 26/27 | AA3: Gol 26/27 | AB3: Assist 26/27 | AC3: Squadra 25/26 | AD3: Nuovo/Trasf. | AE3: FM ponderata | AF3: Miglior abbinamento (calendario) | AG3: Trasferte in comune | AH3: Rank FVM di ruolo | AI3: Dettaglio infortunio / stato
A4: =RANK(B4,$B$4:$B$196) -> 1 | B4: =ROUND(Guida!$B$22*H4/Guida!$B$30+Guida!$B$23*MAX(0,MIN(1,(AE4-5.4)/1.6))+Guida!$B$24*1+Guida!$B$25*1,1) -> 99.5 | C4: Calhanoglu | D4: Inter | E4: Mediano / Centrale | F4: 27 | G4: 28 | H4: 243 | I4: =MAX(1,ROUND(H4^Guida!$B$18*Guida!$F$13,0)) -> 49 | J4: =MAX(2,ROUND(I4*1.2,0)) -> 59 | K4: =IF(I4>=60,"Top",IF(I4>=30,"1a fascia",IF(I4>=15,"2a fascia",IF(I4>=7,"3a fascia",IF(I4>=3,"4a fascia","Scommessa"))))) -> 1a fascia | L4: Titolare | M4: Titolare confermato (2/2) | N4: 1o | O4: 1o | P4: 22 | Q4: 6.52 | R4: 7.64 | S4: 9 | T4: 4 | U4: 4/5 | V4: 7 | W4: 0 | X4: 2 | Y4: 7 | Z4: 9.75 | AA4: 2 | AB4: 0 | AC4: Inter | AD4: No | AE4: =ROUND(IF(P4="",5.5,R4*MIN(1,P4/25)+5.5*(1-MIN(1,P4/25))),2) -> 7.38 | AF4: Pulisic (MIL) | AG4: 0 | AH4: =RANK(H4,$H$4:$H$196) -> 2
A5: =RANK(B5,$B$4:$B$196) -> 2 | B5: =ROUND(Guida!$B$22*H5/Guida!$B$30+Guida!$B$23*MAX(0,MIN(1,(AE5-5.4)/1.6))+Guida!$B$24*0.35+Guida!$B$25*1,1) -> 93.5 | C5: Paz N. | D5: Como | E5: Trequartista / Attaccante | F5: 30 | G5: 29 | H5: 245 | I5: =MAX(1,ROUND(H5^Guida!$B$18*Guida!$F$13,0)) -> 49 | J5: =MAX(2,ROUND(I5*1.2,0)) -> 59 | K5: =IF(I5>=60,"Top",IF(I5>=30,"1a fascia",IF(I5>=15,"2a fascia",IF(I5>=7,"3a fascia",IF(I5>=3,"4a fascia","Scommessa"))))) -> 1a fascia | L5: Titolare | M5: Titolare confermato (2/2) | N5: 3o | O5: 1o | P5: 35 | Q5: 6.37 | R5: 7.3 | S5: 12 | T5: 5 | U5: 0/2 | V5: 5 | W5: 0 | X5: 2 | Y5: 5.75 | Z5: 5.75 | AA5: 0 | AB5: 0 | AC5: Como | AD5: No | AE5: =ROUND(IF(P5="",5.5,R5*MIN(1,P5/25)+5.5*(1-MIN(1,P5/25))),2) -> 7.3 | AF5: McTominay (NAP) | AG5: 7 | AH5: =RANK(H5,$H$4:$H$196) -> 1
A6: =RANK(B6,$B$4:$B$196) -> 3 | B6: =ROUND(Guida!$B$22*H6/Guida!$B$30+Guida!$B$23*MAX(0,MIN(1,(AE6-5.4)/1.6))+Guida!$B$24*1+Guida!$B$25*1,1) -> 79.6 | C6: Orsolini | D6: Bologna | E6: Esterno alto / Attaccante | F6: 26 | G6: 25 | H6: 177 | I6: =MAX(1,ROUND(H6^Guida!$B$18*Guida!$F$13,0)) -> 40 | J6: =MAX(2,ROUND(I6*1.2,0)) -> 48 | K6: =IF(I6>=60,"Top",IF(I6>=30,"1a fascia",IF(I6>=15,"2a fascia",IF(I6>=7,"3a fascia",IF(I6>=3,"4a fascia","Scommessa"))))) -> 1a fascia | L6: Titolare | M6: Infortunato - presenze finora: 2/2 | N6: 1o | O6: 1o | P6: 34 | Q6: 6.06 | R6: 6.76 | S6: 10 | T6: 1 | U6: 4/6 | V6: 2 | W6: 0 | X6: 2 | Y6: 5.75 | Z6: 5.75 | AA6: 0 | AB6: 0 | AC6: Bologna | AD6: No | AE6: =ROUND(IF(P6="",5.5,R6*MIN(1,P6/25)+5.5*(1-MIN(1,P6/25))),2) -> 6.76 | AF6: McTominay (NAP) | AG6: 6 | AH6: =RANK(H6,$H$4:$H$196) -> 4 | AI6: Risentimento ai flessori della coscia sinistra (31/8). Esami in corso, salta il Sassuolo.
A7: =RANK(B7,$B$4:$B$196) -> 4 | B7: =ROUND(Guida!$B$22*H7/Guida!$B$30+Guida!$B$23*MAX(0,MIN(1,(AE7-5.4)/1.6))+Guida!$B$24*0+Guida!$B$25*0,1) -> 78.9 | C7: McTominay | D7: Napoli | E7: Centrale / Trequartista | F7: 28 | G7: 27 | H7: 220 | I7: =MAX(1,ROUND(H7^Guida!$B$18*Guida!$F$13,0)) -> 46 | J7: =MAX(2,ROUND(I7*1.2,0)) -> 55 | K7: =IF(I7>=60,"Top",IF(I7>=30,"1a fascia",IF(I7>=15,"2a fascia",IF(I7>=7,"3a fascia",IF(I7>=3,"4a fascia","Scommessa"))))) -> 1a fascia | L7: Titolare | M7: INFORTUNATO (lungo stop) - presenze finora: 2/2 | N7: - | O7: - | P7: 33 | Q7: 6.39 | R7: 7.26 | S7: 10 | T7: 2 | U7: 0/1 | V7: 1 | W7: 0 | X7: 2 | Y7: 5.75 | Z7: 5.75 | AA7: 0 | AB7: 0 | AC7: Napoli | AD7: No | AE7: =ROUND(IF(P7="",5.5,R7*MIN(1,P7/25)+5.5*(1-MIN(1,P7/25))),2) -> 7.26 | AF7: Orsolini (BOL) | AG7: 6 | AH7: =RANK(H7,$H$4:$H$196) -> 3 | AI7: Ablazione per una lieve aritmia benigna (1/9). Rientro da inizio ottobre.
A8: =RANK(B8,$B$4:$B$196) -> 5 | B8: =ROUND(Guida!$B$22*H8/Guida!$B$30+Guida!$B$23*MAX(0,MIN(1,(AE8-5.4)/1.6))+Guida!$B$24*0.6+Guida!$B$25*0.6,1) -> 70.7 | C8: Pulisic | D8: Milan | E8: Trequartista / Attaccante | F8: 25 | G8: 24 | H8: 150 | I8: =MAX(1,ROUND(H8^Guida!$B$18*Guida!$F$13,0)) -> 37 | J8: =MAX(2,ROUND(I8*1.2,0)) -> 44 | K8: =IF(I8>=60,"Top",IF(I8>=30,"1a fascia",IF(I8>=15,"2a fascia",IF(I8>=7,"3a fascia",IF(I8>=3,"4a fascia","Scommessa"))))) -> 1a fascia | L8: Titolare | M8: RISCHIA il posto (0/2) | N8: 2o | O8: 2o | P8: 27 | Q8: 6.15 | R8: 7.07 | S8: 8 | T8: 4 | U8: 0/1 | V8: 0 | W8: 0 | X8: 0 | AC8: Milan | AD8: No | AE8: =ROUND(IF(P8="",5.5,R8*MIN(1,P8/25)+5.5*(1-MIN(1,P8/25))),2) -> 7.07 | AF8: Calhanoglu (INT) | AG8: 0 | AH8: =RANK(H8,$H$4:$H$196) -> 5
A9: =RANK(B9,$B$4:$B$196) -> 6 | B9: =ROUND(Guida!$B$22*H9/Guida!$B$30+Guida!$B$23*MAX(0,MIN(1,(AE9-5.4)/1.6))+Guida!$B$24*1+Guida!$B$25*1,1) -> 61.4 | C9: De Bruyne | D9: Napoli | E9: Trequartista | F9: 15 | G9: 17 | H9: 108 | I9: =MAX(1,ROUND(H9^Guida!$B$18*Guida!$F$13,0)) -> 30 | J9: =MAX(2,ROUND(I9*1.2,0)) -> 36 | K9: =IF(I9>=60,"Top",IF(I9>=30,"1a fascia",IF(I9>=15,"2a fascia",IF(I9>=7,"3a fascia",IF(I9>=3,"4a fascia","Scommessa"))))) -> 1a fascia | L9: Titolare | M9: Titolare confermato (2/2) | N9: 1o | O9: 1o | P9: 17 | Q9: 6.26 | R9: 7.24 | S9: 5 | T9: 2 | U9: 3/3 | V9: 1 | W9: 0 | X9: 2 | Y9: 7 | Z9: 9 | AA9: 1 | AB9: 1 | AC9: Napoli | AD9: No | AE9: =ROUND(IF(P9="",5.5,R9*MIN(1,P9/25)+5.5*(1-MIN(1,P9/25))),2) -> 6.68 | AF9: Orsolini (BOL) | AG9: 6 | AH9: =RANK(H9,$H$4:$H$196) -> 7
A10: =RANK(B10,$B$4:$B$196) -> 7 | B10: =ROUND(Guida!$B$22*H10/Guida!$B$30+Guida!$B$23*MAX(0,MIN(1,(AE10-5.4)/1.6))+Guida!$B$24*0+Guida!$B$25*0,1) -> 60.2 | C10: Rabiot | D10: Milan | E10: Centrale / Trequartista | F10: 22 | G10: 23 | H10: 145 | I10: =MAX(1,ROUND(H10^Guida!$B$18*Guida!$F$13,0)) -> 36 | J10: =MAX(2,ROUND(I10*1.2,0)) -> 43 | K10: =IF(I10>=60,"Top",IF(I10>=30,"1a fascia",IF(I10>=15,"2a fascia",IF(I10>=7,"3a fascia",IF(I10>=3,"4a fascia","Scommessa"))))) -> 1a fascia | L10: Titolare | M10: Titolare confermato (2/2) | N10: - | O10: - | P10: 29 | Q10: 6.33 | R10: 6.98 | S10: 6 | T10: 4 | U10: 0/0 | V10: 4 | W10: 1 | X10: 2 | Y10: 6.75 | Z10: 8.75 | AA10: 1 | AB10: 1 | AC10: Milan | AD10: No | AE10: =ROUND(IF(P10="",5.5,R10*MIN(1,P10/25)+5.5*(1-MIN(1,P10/25))),2) -> 6.98 | AF10: Calhanoglu (INT) | AG10: 0 | AH10: =RANK(H10,$H$4:$H$196) -> 6
A11: =RANK(B11,$B$4:$B$196) -> 8 | B11: =ROUND(Guida!$B$22*H11/Guida!$B$30+Guida!$B$23*MAX(0,MIN(1,(AE11-5.4)/1.6))+Guida!$B$24*1+Guida!$B$25*0,1) -> 54.9 | C11: Da Cunha | D11: Como | E11: Centrale / Trequartista | F11: 18 | G11: 18 | H11: 87 | I11: =MAX(1,ROUND(H11^Guida!$B$18*Guida!$F$13,0)) -> 26 | J11: =MAX(2,ROUND(I11*1.2,0)) -> 31 | K11: =IF(I11>=60,"Top",IF(I11>=30,"1a fascia",IF(I11>=15,"2a fascia",IF(I11>=7,"3a fascia",IF(I11>=3,"4a fascia","Scommessa"))))) -> 2a fascia | L11: Titolare | M11: Titolare confermato (2/2) | N11: 1o | O11: - | P11: 35 | Q11: 6.34 | R11: 6.91 | S11: 6 | T11: 4 | U11: 4/4 | V11: 4 | W11: 0 | X11: 2 | Y11: 6.25 | Z11: 6.25 | AA11: 0 | AB11: 0 | AC11: Como | AD11: No | AE11: =ROUND(IF(P11="",5.5,R11*MIN(1,P11/25)+5.5*(1-MIN(1,P11/25))),2) -> 6.91 | AF11: Atta (FIO) | AG11: 6 | AH11: =RANK(H11,$H$4:$H$196) -> 10
A12: =RANK(B12,$B$4:$B$196) -> 9 | B12: =ROUND(Guida!$B$22*H12/Guida!$B$30+Guida!$B$23*MAX(0,MIN(1,(AE12-5.4)/1.6))+Guida!$B$24*0+Guida!$B$25*0.6,1) -> 53.7 | C12: Baturina | D12: Como | E12: Trequartista | F12: 19 | G12: 20 | H12: 105 | I12: =MAX(1,ROUND(H12^Guida!$B$18*Guida!$F$13,0)) -> 30 | J12: =MAX(2,ROUND(I12*1.2,0)) -> 36 | K12: =IF(I12>=60,"Top",IF(I12>=30,"1a fascia",IF(I12>=15,"2a fascia",IF(I12>=7,"3a fascia",IF(I12>=3,"4a fascia","Scommessa"))))) -> 1a fascia | L12: Titolare | M12: Titolare confermato (2/2) | N12: - | O12: 2o | P12: 25 | Q12: 6.3 | R12: 7.14 | S12: 6 | T12: 3 | U12: 0/0 | V12: 0 | W12: 0 | X12: 2 | Y12: 6.5 | Z12: 8 | AA12: 1 | AB12: 0 | AC12: Como | AD12: No | AE12: =ROUND(IF(P12="",5.5,R12*MIN(1,P12/25)+5.5*(1-MIN(1,P12/25))),2) -> 7.14 | AF12: Atta (FIO) | AG12: 6 | AH12: =RANK(H12,$H$4:$H$196) -> 8
A13: =RANK(B13,$B$4:$B$196) -> 10 | B13: =ROUND(Guida!$B$22*H13/Guida!$B$30+Guida!$B$23*MAX(0,MIN(1,(AE13-5.4)/1.6))+Guida!$B$24*1+Guida!$B$25*1,1) -> 52.6 | C13: Vlasic | D13: Torino | E13: Trequartista | F13: 14 | G13: 13 | H13: 73 | I13: =MAX(1,ROUND(H13^Guida!$B$18*Guida!$F$13,0)) -> 24 | J13: =MAX(2,ROUND(I13*1.2,0)) -> 29 | K13: =IF(I13>=60,"Top",IF(I13>=30,"1a fascia",IF(I13>=15,"2a fascia",IF(I13>=7,"3a fascia",IF(I13>=3,"4a fascia","Scommessa"))))) -> 2a fascia | L13: Titolare | M13: Titolare confermato (2/2) | N13: 1o | O13: 1o | P13: 37 | Q13: 6.03 | R13: 6.66 | S13: 8 | T13: 3 | U13: 5/5 | V13: 7 | W13: 0 | X13: 2 | Y13: 5.25 | Z13: 5.25 | AA13: 0 | AB13: 0 | AC13: Torino | AD13: No | AE13: =ROUND(IF(P13="",5.5,R13*MIN(1,P13/25)+5.5*(1-MIN(1,P13/25))),2) -> 6.66 | AF13: McKennie (JUV) | AG13: 0 | AH13: =RANK(H13,$H$4:$H$196) -> 16
A14: =RANK(B14,$B$4:$B$196) -> 11 | B14: =ROUND(Guida!$B$22*H14/Guida!$B$30+Guida!$B$23*MAX(0,MIN(1,(AE14-5.4)/1.6))+Guida!$B$24*0.35+Guida!$B$25*1,1) -> 49.5 | C14: Zaniolo | D14: Udinese | E14: Trequartista / Attaccante | F14: 18 | G14: 18 | H14: 80 | I14: =MAX(1,ROUND(H14^Guida!$B$18*Guida!$F$13,0)) -> 25 | J14: =MAX(2,ROUND(I14*1.2,0)) -> 30 | K14: =IF(I14>=60,"Top",IF(I14>=30,"1a fascia",IF(I14>=15,"2a fascia",IF(I14>=7,"3a fascia",IF(I14>=3,"4a fascia","Scommessa"))))) -> 2a fascia | L14: Titolare | M14: Infortunato - presenze finora: 1/2 | N14: 3o | O14: 1o | P14: 31 | Q14: 6.26 | R14: 6.77 | S14: 5 | T14: 5 | U14: 0/0 | V14: 8 | W14: 0 | X14: 1 | Y14: 6.5 | Z14: 6.5 | AA14: 0 | AB14: 0 | AC14: Udinese | AD14: No | AE14: =ROUND(IF(P14="",5.5,R14*MIN(1,P14/25)+5.5*(1-MIN(1,P14/25))),2) -> 6.77 | AF14: Pulisic (MIL) | AG14: 7 | AH14: =RANK(H14,$H$4:$H$196) -> 13 | AI14: Lesione al bicipite femorale destro (1a giornata). Stop ~25 giorni, rientro seconda meta di settembre.
A15: =RANK(B15,$B$4:$B$196) -> 12 | B15: =ROUND(Guida!$B$22*H15/Guida!$B$30+Guida!$B$23*MAX(0,MIN(1,(AE15-5.4)/1.6))+Guida!$B$24*0+Guida!$B$25*0.35,1) -> 44 | C15: Atta | D15: Fiorentina | E15: Centrale / Trequartista | F15: 17 | G15: 15 | H15: 78 | I15: =MAX(1,ROUND(H15^Guida!$B$18*Guida!$F$13,0)) -> 25 | J15: =MAX(2,ROUND(I15*1.2,0)) -> 30 | K15: =IF(I15>=60,"Top",IF(I15>=30,"1a fascia",IF(I15>=15,"2a fascia",IF(I15>=7,"3a fascia",IF(I15>=3,"4a fascia","Scommessa"))))) -> 2a fascia | L15: Titolare | M15: Nuovo - Titolare confermato (2/2) | N15: - | O15: 3o | P15: 32 | Q15: 6.36 | R15: 6.88 | S15: 5 | T15: 3 | U15: 0/0 | V15: 3 | W15: 0 | X15: 2 | Y15: 4.5 | Z15: 4.5 | AA15: 0 | AB15: 0 | AC15: Udinese | AD15: Si | AE15: =ROUND(IF(P15="",5.5,R15*MIN(1,P15/25)+5.5*(1-MIN(1,P15/25))),2) -> 6.88 | AF15: Paz N. (COM) | AG15: 6 | AH15: =RANK(H15,$H$4:$H$196) -> 14
A16: =RANK(B16,$B$4:$B$196) -> 13 | B16: =ROUND(Guida!$B$22*H16/Guida!$B$30+Guida!$B$23*MAX(0,MIN(1,(AE16-5.4)/1.6))+Guida!$B$24*1+Guida!$B$25*0.6,1) -> 43.1 | C16: Zaccagni | D16: Lazio | E16: Esterno alto / Attaccante | F16: 16 | G16: 16 | H16: 87 | I16: =MAX(1,ROUND(H16^Guida!$B$18*Guida!$F$13,0)) -> 26 | J16: =MAX(2,ROUND(I16*1.2,0)) -> 31 | K16: =IF(I16>=60,"Top",IF(I16>=30,"1a fascia",IF(I16>=15,"2a fascia",IF(I16>=7,"3a fascia",IF(I16>=3,"4a fascia","Scommessa"))))) -> 2a fascia | L16: Titolare | M16: Titolare confermato (2/2) | N16: 1o | O16: 2o | P16: 26 | Q16: 5.88 | R16: 5.96 | S16: 3 | T16: 0 | U16: 0/1 | V16: 6 | W16: 1 | X16: 2 | Y16: 6 | Z16: 5.75 | AA16: 0 | AB16: 0 | AC16: Lazio | AD16: No | AE16: =ROUND(IF(P16="",5.5,R16*MIN(1,P16/25)+5.5*(1-MIN(1,P16/25))),2) -> 5.96 | AF16: Konè M. (ROM) | AG16: 0 | AH16: =RANK(H16,$H$4:$H$196) -> 10
A17: =RANK(B17,$B$4:$B$196) -> 14 | B17: =ROUND(Guida!$B$22*H17/Guida!$B$30+Guida!$B$23*MAX(0,MIN(1,(AE17-5.4)/1.6))+Guida!$B$24*0.6+Guida!$B$25*0.35,1) -> 40.6 | C17: Zielinski | D17: Inter | E17: Centrale | F17: 10 | G17: 12 | H17: 45 | I17: =MAX(1,ROUND(H17^Guida!$B$18*Guida!$F$13,0)) -> 18 | J17: =MAX(2,ROUND(I17*1.2,0)) -> 22 | K17: =IF(I17>=60,"Top",IF(I17>=30,"1a fascia",IF(I17>=15,"2a fascia",IF(I17>=7,"3a fascia",IF(I17>=3,"4a fascia","Scommessa"))))) -> 2a fascia | L17: Titolare | M17: Titolare confermato (2/2) | N17: 2o | O17: 3o | P17: 30 | Q17: 6.25 | R17: 6.8 | S17: 6 | T17: 2 | U17: 1/1 | V17: 3 | W17: 0 | X17: 2 | Y17: 6.75 | Z17: 8.25 | AA17: 1 | AB17: 0 | AC17: Inter | AD17: No | AE17: =ROUND(IF(P17="",5.5,R17*MIN(1,P17/25)+5.5*(1-MIN(1,P17/25))),2) -> 6.8 | AF17: Pulisic (MIL) | AG17: 0 | AH17: =RANK(H17,$H$4:$H$196) -> 26
A18: =RANK(B18,$B$4:$B$196) -> 15 | B18: =ROUND(Guida!$B$22*H18/Guida!$B$30+Guida!$B$23*MAX(0,MIN(1,(AE18-5.4)/1.6))+Guida!$B$24*0+Guida!$B$25*0,1) -> 40.3 | C18: Barella | D18: Inter | E18: Centrale | F18: 17 | G18: 18 | H18: 81 | I18: =MAX(1,ROUND(H18^Guida!$B$18*Guida!$F$13,0)) -> 25 | J18: =MAX(2,ROUND(I18*1.2,0)) -> 30 | K18: =IF(I18>=60,"Top",IF(I18>=30,"1a fascia",IF(I18>=15,"2a fascia",IF(I18>=7,"3a fascia",IF(I18>=3,"4a fascia","Scommessa"))))) -> 2a fascia | L18: Titolare | M18: Titolare confermato (2/2) | N18: - | O18: - | P18: 34 | Q18: 6.28 | R18: 6.71 | S18: 3 | T18: 9 | U18: 0/0 | V18: 7 | W18: 0 | X18: 2 | Y18: 6.5 | Z18: 7 | AA18: 0 | AB18: 1 | AC18: Inter | AD18: No | AE18: =ROUND(IF(P18="",5.5,R18*MIN(1,P18/25)+5.5*(1-MIN(1,P18/25))),2) -> 6.71 | AF18: Pulisic (MIL) | AG18: 0 | AH18: =RANK(H18,$H$4:$H$196) -> 12
A19: =RANK(B19,$B$4:$B$196) -> 16 | B19: =ROUND(Guida!$B$22*H19/Guida!$B$30+Guida!$B$23*MAX(0,MIN(1,(AE19-5.4)/1.6))+Guida!$B$24*0.35+Guida!$B$25*1,1) -> 39.4 | C19: Modric | D19: Milan | E19: Mediano / Centrale | F19: 12 | G19: 12 | H19: 45 | I19: =MAX(1,ROUND(H19^Guida!$B$18*Guida!$F$13,0)) -> 18 | J19: =MAX(2,ROUND(I19*1.2,0)) -> 22 | K19: =IF(I19>=60,"Top",IF(I19>=30,"1a fascia",IF(I19>=15,"2a fascia",IF(I19>=7,"3a fascia",IF(I19>=3,"4a fascia","Scommessa"))))) -> 2a fascia | L19: Titolare | M19: Titolare confermato (2/2) | N19: 3o | O19: 1o | P19: 33 | Q19: 6.45 | R19: 6.67 | S19: 2 | T19: 3 | U19: 0/0 | V19: 4 | W19: 0 | X19: 2 | Y19: 6 | Z19: 6 | AA19: 0 | AB19: 0 | AC19: Milan | AD19: No | AE19: =ROUND(IF(P19="",5.5,R19*MIN(1,P19/25)+5.5*(1-MIN(1,P19/25))),2) -> 6.67 | AF19: Calhanoglu (INT) | AG19: 0 | AH19: =RANK(H19,$H$4:$H$196) -> 26
A20: =RANK(B20,$B$4:$B$196) -> 17 | B20: =ROUND(Guida!$B$22*H20/Guida!$B$30+Guida!$B$23*MAX(0,MIN(1,(AE20-5.4)/1.6))+Guida!$B$24*0+Guida!$B$25*0,1) -> 37.1 | C20: McKennie | D20: Juventus | E20: Centrale / Trequartista | F20: 17 | G20: 17 | H20: 70 | I20: =MAX(1,ROUND(H20^Guida!$B$18*Guida!$F$13,0)) -> 23 | J20: =MAX(2,ROUND(I20*1.2,0)) -> 28 | K20: =IF(I20>=60,"Top",IF(I20>=30,"1a fascia",IF(I20>=15,"2a fascia",IF(I20>=7,"3a fascia",IF(I20>=3,"4a fascia","Scommessa"))))) -> 2a fascia | L20: Titolare | M20: In dubbio / da valutare - presenze finora: 1/2 | N20: - | O20: - | P20: 34 | Q20: 6.13 | R20: 6.68 | S20: 5 | T20: 6 | U20: 0/0 | V20: 5 | W20: 0 | X20: 1 | Y20: 6 | Z20: 6 | AA20: 0 | AB20: 0 | AC20: Juventus | AD20: No | AE20: =ROUND(IF(P20="",5.5,R20*MIN(1,P20/25)+5.5*(1-MIN(1,P20/25))),2) -> 6.68 | AF20: Vlasic (TOR) | AG20: 0 | AH20: =RANK(H20,$H$4:$H$196) -> 17 | AI20: Affaticamento muscolare dal 27/8. Gia assente col Parma, convocazione a rischio.
A21: =RANK(B21,$B$4:$B$196) -> 18 | B21: =ROUND(Guida!$B$22*H21/Guida!$B$30+Guida!$B$23*MAX(0,MIN(1,(AE21-5.4)/1.6))+Guida!$B$24*0+Guida!$B$25*0,1) -> 37 | C21: Conceicao | D21: Juventus | E21: Esterno alto / Attaccante | F21: 12 | G21: 13 | H21: 68 | I21: =MAX(1,ROUND(H21^Guida!$B$18*Guida!$F$13,0)) -> 23 | J21: =MAX(2,ROUND(I21*1.2,0)) -> 28 | K21: =IF(I21>=60,"Top",IF(I21>=30,"1a fascia",IF(I21>=15,"2a fascia",IF(I21>=7,"3a fascia",IF(I21>=3,"4a fascia","Scommessa"))))) -> 2a fascia | L21: Titolare | M21: Titolare confermato (2/2) | N21: - | O21: - | P21: 30 | Q21: 6.28 | R21: 6.7 | S21: 3 | T21: 5 | U21: 0/0 | V21: 3 | W21: 0 | X21: 2 | Y21: 6.5 | Z21: 7 | AA21: 0 | AB21: 1 | AC21: Juventus | AD21: No | AE21: =ROUND(IF(P21="",5.5,R21*MIN(1,P21/25)+5.5*(1-MIN(1,P21/25))),2) -> 6.7 | AF21: Vlasic (TOR) | AG21: 0 | AH21: =RANK(H21,$H$4:$H$196) -> 18
A22: =RANK(B22,$B$4:$B$196) -> 19 | B22: =ROUND(Guida!$B$22*H22/Guida!$B$30+Guida!$B$23*MAX(0,MIN(1,(AE22-5.4)/1.6))+Guida!$B$24*0+Guida!$B$25*0.6,1) -> 35.9 | C22: Ekkelenkamp | D22: Udinese | E22: Centrale / Trequartista | F22: 10 | G22: 12 | H22: 57 | I22: =MAX(1,ROUND(H22^Guida!$B$18*Guida!$F$13,0)) -> 20 | J22: =MAX(2,ROUND(I22*1.2,0)) -> 24 | K22: =IF(I22>=60,"Top",IF(I22>=30,"1a fascia",IF(I22>=15,"2a fascia",IF(I22>=7,"3a fascia",IF(I22>=3,"4a fascia","Scommessa"))))) -> 2a fascia | L22: Titolare | M22: Titolare confermato (2/2) | N22: - | O22: 2o | P22: 31 | Q22: 6.05 | R22: 6.61 | S22: 5 | T22: 3 | U22: 0/0 | V22: 1 | W22: 0 | X22: 2 | Y22: 7 | Z22: 9 | AA22: 1 | AB22: 1 | AC22: Udinese | AD22: No | AE22: =ROUND(IF(P22="",5.5,R22*MIN(1,P22/25)+5.5*(1-MIN(1,P22/25))),2) -> 6.61 | AF22: Pulisic (MIL) | AG22: 7 | AH22: =RANK(H22,$H$4:$H$196) -> 19
A23: =RANK(B23,$B$4:$B$196) -> 20 | B23: =ROUND(Guida!$B$22*H23/Guida!$B$30+Guida!$B$23*MAX(0,MIN(1,(AE23-5.4)/1.6))+Guida!$B$24*0.6+Guida!$B$25*0.6,1) -> 33.1 | C23: Bernardeschi | D23: Bologna | E23: Esterno alto / Trequartista | F23: 9 | G23: 10 | H23: 27 | I23: =MAX(1,ROUND(H23^Guida!$B$18*Guida!$F$13,0)) -> 13 | J23: =MAX(2,ROUND(I23*1.2,0)) -> 16 | K23: =IF(I23>=60,"Top",IF(I23>=30,"1a fascia",IF(I23>=15,"2a fascia",IF(I23>=7,"3a fascia",IF(I23>=3,"4a fascia","Scommessa"))))) -> 3a fascia | L23: Titolare | M23: Titolare confermato (2/2) | N23: 2o | O23: 2o | P23: 24 | Q23: 6.04 | R23: 6.56 | S23: 4 | T23: 2 | U23: 1/1 | V23: 3 | W23: 0 | X23: 2 | Y23: 6.5 | Z23: 6.5 | AA23: 0 | AB23: 0 | AC23: Bologna | AD23: No | AE23: =ROUND(IF(P23="",5.5,R23*MIN(1,P23/25)+5.5*(1-MIN(1,P23/25))),2) -> 6.52 | AF23: McTominay (NAP) | AG23: 6 | AH23: =RANK(H23,$H$4:$H$196) -> 51
A24: =RANK(B24,$B$4:$B$196) -> 21 | B24: =ROUND(Guida!$B$22*H24/Guida!$B$30+Guida!$B$23*MAX(0,MIN(1,(AE24-5.4)/1.6))+Guida!$B$24*0.2+Guida!$B$25*1,1) -> 32.2 | C24: Bernabè | D24: Parma | E24: Centrale | F24: 7 | G24: 7 | H24: 34 | I24: =MAX(1,ROUND(H24^Guida!$B$18*Guida!$F$13,0)) -> 15 | J24: =MAX(2,ROUND(I24*1.2,0)) -> 18 | K24: =IF(I24>=60,"Top",IF(I24>=30,"1a fascia",IF(I24>=15,"2a fascia",IF(I24>=7,"3a fascia",IF(I24>=3,"4a fascia","Scommessa"))))) -> 2a fascia | L24: Titolare | M24: Titolare confermato (2/2) | N24: 4o | O24: 1o | P24: 32 | Q24: 6.17 | R24: 6.48 | S24: 3 | T24: 1 | U24: 0/0 | V24: 0 | W24: 0 | X24: 2 | Y24: 5.75 | Z24: 5.75 | AA24: 0 | AB24: 0 | AC24: Parma | AD24: No | AE24: =ROUND(IF(P24="",5.5,R24*MIN(1,P24/25)+5.5*(1-MIN(1,P24/25))),2) -> 6.48 | AF24: Thorstvedt (SAS) | AG24: 4 | AH24: =RANK(H24,$H$4:$H$196) -> 41
A25: =RANK(B25,$B$4:$B$196) -> 22 | B25: =ROUND(Guida!$B$22*H25/Guida!$B$30+Guida!$B$23*MAX(0,MIN(1,(AE25-5.4)/1.6))+Guida!$B$24*0.35+Guida!$B$25*0.6,1) -> 30.6 | C25: Politano | D25: Napoli | E25: Esterno alto | F25: 10 | G25: 9 | H25: 37 | I25: =MAX(1,ROUND(H25^Guida!$B$18*Guida!$F$13,0)) -> 16 | J25: =MAX(2,ROUND(I25*1.2,0)) -> 19 | K25: =IF(I25>=60,"Top",IF(I25>=30,"1a fascia",IF(I25>=15,"2a fascia",IF(I25>=7,"3a fascia",IF(I25>=3,"4a fascia","Scommessa"))))) -> 2a fascia | L25: Ballottaggio | M25: In ballottaggio (2/2) | N25: 3o | O25: 2o | P25: 33 | Q25: 6.09 | R25: 6.36 | S25: 2 | T25: 5 | U25: 0/0 | V25: 4 | W25: 0 | X25: 2 | Y25: 5.5 | Z25: 5.25 | AA25: 0 | AB25: 0 | AC25: Napoli | AD25: No | AE25: =ROUND(IF(P25="",5.5,R25*MIN(1,P25/25)+5.5*(1-MIN(1,P25/25))),2) -> 6.36 | AF25: Konè M. (ROM) | AG25: 3 | AH25: =RANK(H25,$H$4:$H$196) -> 38
A26: =RANK(B26,$B$4:$B$196) -> 23 | B26: =ROUND(Guida!$B$22*H26/Guida!$B$30+Guida!$B$23*MAX(0,MIN(1,(AE26-5.4)/1.6))+Guida!$B$24*0.35+Guida!$B$25*0.6,1) -> 29.2 | C26: Samardzic | D26: Atalanta | E26: Centrale / Trequartista | F26: 12 | G26: 13 | H26: 44 | I26: =MAX(1,ROUND(H26^Guida!$B$18*Guida!$F$13,0)) -> 18 | J26: =MAX(2,ROUND(I26*1.2,0)) -> 22 | K26: =IF(I26>=60,"Top",IF(I26>=30,"1a fascia",IF(I26>=15,"2a fascia",IF(I26>=7,"3a fascia",IF(I26>=3,"4a fascia","Scommessa"))))) -> 2a fascia | L26: Titolare | M26: Titolare confermato (2/2) | N26: 3o | O26: 2o | P26: 21 | Q26: 5.93 | R26: 6.29 | S26: 2 | T26: 2 | U26: 0/0 | V26: 1 | W26: 0 | X26: 2 | Y26: 6.5 | Z26: 8 | AA26: 1 | AB26: 0 | AC26: Atalanta | AD26: No | AE26: =ROUND(IF(P26="",5.5,R26*MIN(1,P26/25)+5.5*(1-MIN(1,P26/25))),2) -> 6.16 | AF26: Calò (FRO) | AG26: 5 | AH26: =RANK(H26,$H$4:$H$196) -> 30
A27: =RANK(B27,$B$4:$B$196) -> 24 | B27: =ROUND(Guida!$B$22*H27/Guida!$B$30+Guida!$B$23*MAX(0,MIN(1,(AE27-5.4)/1.6))+Guida!$B$24*0+Guida!$B$25*0,1) -> 28.4 | C27: Rowe | D27: Atalanta | E27: Esterno alto / Trequartista | F27: 11 | G27: 10 | H27: 40 | I27: =MAX(1,ROUND(H27^Guida!$B$18*Guida!$F$13,0)) -> 17 | J27: =MAX(2,ROUND(I27*1.2,0)) -> 20 | K27: =IF(I27>=60,"Top",IF(I27>=30,"1a fascia",IF(I27>=15,"2a fascia",IF(I27>=7,"3a fascia",IF(I27>=3,"4a fascia","Scommessa"))))) -> 2a fascia | L27: Titolare | M27: Nuovo - Rischia il posto (1/2) | N27: - | O27: - | P27: 28 | Q27: 6.2 | R27: 6.59 | S27: 3 | T27: 3 | U27: 0/0 | V27: 2 | W27: 0 | X27: 1 | Y27: 5.5 | Z27: 5.5 | AA27: 0 | AB27: 0 | AC27: Bologna | AD27: Si | AE27: =ROUND(IF(P27="",5.5,R27*MIN(1,P27/25)+5.5*(1-MIN(1,P27/25))),2) -> 6.59 | AF27: Calò (FRO) | AG27: 5 | AH27: =RANK(H27,$H$4:$H$196) -> 35
A28: =RANK(B28,$B$4:$B$196) -> 25 | B28: =ROUND(Guida!$B$22*H28/Guida!$B$30+Guida!$B$23*MAX(0,MIN(1,(AE28-5.4)/1.6))+Guida!$B$24*0+Guida!$B$25*0,1) -> 27.9 | C28: Konè M. | D28: Roma | E28: Mediano / Centrale | F28: 10 | G28: 10 | H28: 42 | I28: =MAX(1,ROUND(H28^Guida!$B$18*Guida!$F$13,0)) -> 17 | J28: =MAX(2,ROUND(I28*1.2,0)) -> 20 | K28: =IF(I28>=60,"Top",IF(I28>=30,"1a fascia",IF(I28>=15,"2a fascia",IF(I28>=7,"3a fascia",IF(I28>=3,"4a fascia","Scommessa"))))) -> 2a fascia | L28: Titolare | M28: Titolare confermato (2/2) | N28: - | O28: - | P28: 29 | Q28: 6.26 | R28: 6.53 | S28: 2 | T28: 3 | U28: 0/0 | V28: 2 | W28: 0 | X28: 2 | Y28: 6.5 | Z28: 6.25 | AA28: 0 | AB28: 0 | AC28: Roma | AD28: No | AE28: =ROUND(IF(P28="",5.5,R28*MIN(1,P28/25)+5.5*(1-MIN(1,P28/25))),2) -> 6.53 | AF28: Zaccagni (LAZ) | AG28: 0 | AH28: =RANK(H28,$H$4:$H$196) -> 32
A29: =RANK(B29,$B$4:$B$196) -> 26 | B29: =ROUND(Guida!$B$22*H29/Guida!$B$30+Guida!$B$23*MAX(0,MIN(1,(AE29-5.4)/1.6))+Guida!$B$24*0+Guida!$B$25*0,1) -> 27.4 | C29: Ederson D.S. | D29: Atalanta | E29: Mediano / Centrale | F29: 12 | G29: 12 | H29: 46 | I29: =MAX(1,ROUND(H29^Guida!$B$18*Guida!$F$13,0)) -> 18 | J29: =MAX(2,ROUND(I29*1.2,0)) -> 22 | K29: =IF(I29>=60,"Top",IF(I29>=30,"1a fascia",IF(I29>=15,"2a fascia",IF(I29>=7,"3a fascia",IF(I29>=3,"4a fascia","Scommessa"))))) -> 2a fascia | L29: Titolare | M29: Titolare confermato (2/2) | N29: - | O29: - | P29: 30 | Q29: 6.25 | R29: 6.43 | S29: 2 | T29: 1 | U29: 1/1 | V29: 3 | W29: 0 | X29: 2 | Y29: 5.75 | Z29: 5.75 | AA29: 0 | AB29: 0 | AC29: Atalanta | AD29: No | AE29: =ROUND(IF(P29="",5.5,R29*MIN(1,P29/25)+5.5*(1-MIN(1,P29/25))),2) -> 6.43 | AF29: Calò (FRO) | AG29: 5 | AH29: =RANK(H29,$H$4:$H$196) -> 25
A30: =RANK(B30,$B$4:$B$196) -> 27 | B30: =ROUND(Guida!$B$22*H30/Guida!$B$30+Guida!$B$23*MAX(0,MIN(1,(AE30-5.4)/1.6))+Guida!$B$24*0+Guida!$B$25*0,1) -> 27.3 | C30: Rodriguez Je. | D30: Como | E30: Esterno alto / Attaccante | F30: 12 | G30: 11 | H30: 31 | I30: =MAX(1,ROUND(H30^Guida!$B$18*Guida!$F$13,0)) -> 14 | J30: =MAX(2,ROUND(I30*1.2,0)) -> 17 | K30: =IF(I30>=60,"Top",IF(I30>=30,"1a fascia",IF(I30>=15,"2a fascia",IF(I30>=7,"3a fascia",IF(I30>=3,"4a fascia","Scommessa"))))) -> 3a fascia | L30: Titolare | M30: Rischia il posto (1/2) | N30: - | O30: - | P30: 28 | Q30: 6.25 | R30: 6.66 | S30: 2 | T30: 8 | U30: 0/0 | V30: 3 | W30: 1 | X30: 1 | Y30: 5.5 | Z30: 5.5 | AA30: 0 | AB30: 0 | AC30: Como | AD30: No | AE30: =ROUND(IF(P30="",5.5,R30*MIN(1,P30/25)+5.5*(1-MIN(1,P30/25))),2) -> 6.66 | AF30: Atta (FIO) | AG30: 6 | AH30: =RANK(H30,$H$4:$H$196) -> 44
A31: =RANK(B31,$B$4:$B$196) -> 28 | B31: =ROUND(Guida!$B$22*H31/Guida!$B$30+Guida!$B$23*MAX(0,MIN(1,(AE31-5.4)/1.6))+Guida!$B$24*0+Guida!$B$25*0,1) -> 26.9 | C31: Zambo Anguissa | D31: Napoli | E31: Centrale | F31: 11 | G31: 10 | H31: 41 | I31: =MAX(1,ROUND(H31^Guida!$B$18*Guida!$F$13,0)) -> 17 | J31: =MAX(2,ROUND(I31*1.2,0)) -> 20 | K31: =IF(I31>=60,"Top",IF(I31>=30,"1a fascia",IF(I31>=15,"2a fascia",IF(I31>=7,"3a fascia",IF(I31>=3,"4a fascia","Scommessa"))))) -> 2a fascia | L31: Titolare | M31: Titolare confermato (2/2) | N31: - | O31: - | P31: 18 | Q31: 6.17 | R31: 6.86 | S31: 4 | T31: 1 | U31: 0/0 | V31: 1 | W31: 0 | X31: 2 | Y31: 5.25 | Z31: 5.25 | AA31: 0 | AB31: 0 | AC31: Napoli | AD31: No | AE31: =ROUND(IF(P31="",5.5,R31*MIN(1,P31/25)+5.5*(1-MIN(1,P31/25))),2) -> 6.48 | AF31: Konè M. (ROM) | AG31: 3 | AH31: =RANK(H31,$H$4:$H$196) -> 34
A32: =RANK(B32,$B$4:$B$196) -> 28 | B32: =ROUND(Guida!$B$22*H32/Guida!$B$30+Guida!$B$23*MAX(0,MIN(1,(AE32-5.4)/1.6))+Guida!$B$24*0.35+Guida!$B$25*0.6,1) -> 26.9 | C32: Locatelli | D32: Juventus | E32: Mediano / Centrale | F32: 8 | G32: 9 | H32: 33 | I32: =MAX(1,ROUND(H32^Guida!$B$18*Guida!$F$13,0)) -> 15 | J32: =MAX(2,ROUND(I32*1.2,0)) -> 18 | K32: =IF(I32>=60,"Top",IF(I32>=30,"1a fascia",IF(I32>=15,"2a fascia",IF(I32>=7,"3a fascia",IF(I32>=3,"4a fascia","Scommessa"))))) -> 2a fascia | L32: Ballottaggio | M32: In ballottaggio (2/2) | N32: 3o | O32: 2o | P32: 36 | Q32: 6.26 | R32: 6.19 | S32: 1 | T32: 2 | U32: 0/1 | V32: 9 | W32: 0 | X32: 2 | Y32: 6.5 | Z32: 6.75 | AA32: 0 | AB32: 1 | AC32: Juventus | AD32: No | AE32: =ROUND(IF(P32="",5.5,R32*MIN(1,P32/25)+5.5*(1-MIN(1,P32/25))),2) -> 6.19 | AF32: Vlasic (TOR) | AG32: 0 | AH32: =RANK(H32,$H$4:$H$196) -> 43
A33: =RANK(B33,$B$4:$B$196) -> 30 | B33: =ROUND(Guida!$B$22*H33/Guida!$B$30+Guida!$B$23*MAX(0,MIN(1,(AE33-5.4)/1.6))+Guida!$B$24*0.6+Guida!$B$25*0.35,1) -> 26.5 | C33: Cataldi | D33: Lazio | E33: Mediano / Centrale | F33: 4 | G33: 4 | H33: 12 | I33: =MAX(1,ROUND(H33^Guida!$B$18*Guida!$F$13,0)) -> 8 | J33: =MAX(2,ROUND(I33*1.2,0)) -> 10 | K33: =IF(I33>=60,"Top",IF(I33>=30,"1a fascia",IF(I33>=15,"2a fascia",IF(I33>=7,"3a fascia",IF(I33>=3,"4a fascia","Scommessa"))))) -> 3a fascia | L33: Riserva | M33: Infortunato - presenze finora: 0/2 | N33: 2o | O33: 3o | P33: 27 | Q33: 6.07 | R33: 6.41 | S33: 3 | T33: 3 | U33: 2/2 | V33: 6 | W33: 0 | X33: 0 | AC33: Lazio | AD33: No | AE33: =ROUND(IF(P33="",5.5,R33*MIN(1,P33/25)+5.5*(1-MIN(1,P33/25))),2) -> 6.41 | AF33: Konè M. (ROM) | AG33: 0 | AH33: =RANK(H33,$H$4:$H$196) -> 118 | AI33: Ernia bilaterale, saltata la preparazione. Recuperabile da meta settembre.
A34: =RANK(B34,$B$4:$B$196) -> 31 | B34: =ROUND(Guida!$B$22*H34/Guida!$B$30+Guida!$B$23*MAX(0,MIN(1,(AE34-5.4)/1.6))+Guida!$B$24*0+Guida!$B$25*0,1) -> 26.4 | C34: Thorstvedt | D34: Sassuolo | E34: Centrale / Trequartista | F34: 10 | G34: 10 | H34: 39 | I34: =MAX(1,ROUND(H34^Guida!$B$18*Guida!$F$13,0)) -> 16 | J34: =MAX(2,ROUND(I34*1.2,0)) -> 19 | K34: =IF(I34>=60,"Top",IF(I34>=30,"1a fascia",IF(I34>=15,"2a fascia",IF(I34>=7,"3a fascia",IF(I34>=3,"4a fascia","Scommessa"))))) -> 2a fascia | L34: Titolare | M34: Titolare confermato (2/2) | N34: - | O34: - | P34: 31 | Q34: 6.15 | R34: 6.48 | S34: 4 | T34: 3 | U34: 0/0 | V34: 9 | W34: 0 | X34: 2 | Y34: 6 | Z34: 6 | AA34: 0 | AB34: 0 | AC34: Sassuolo | AD34: No | AE34: =ROUND(IF(P34="",5.5,R34*MIN(1,P34/25)+5.5*(1-MIN(1,P34/25))),2) -> 6.48 | AF34: Calhanoglu (INT) | AG34: 4 | AH34: =RANK(H34,$H$4:$H$196) -> 37
A35: =RANK(B35,$B$4:$B$196) -> 32 | B35: =ROUND(Guida!$B$22*H35/Guida!$B$30+Guida!$B$23*MAX(0,MIN(1,(AE35-5.4)/1.6))+Guida!$B$24*0+Guida!$B$25*0,1) -> 26.1 | C35: Mora | D35: Roma | E35: Trequartista | F35: 19 | G35: 20 | H35: 100 | I35: =MAX(1,ROUND(H35^Guida!$B$18*Guida!$F$13,0)) -> 29 | J35: =MAX(2,ROUND(I35*1.2,0)) -> 35 | K35: =IF(I35>=60,"Top",IF(I35>=30,"1a fascia",IF(I35>=15,"2a fascia",IF(I35>=7,"3a fascia",IF(I35>=3,"4a fascia","Scommessa"))))) -> 2a fascia | L35: Titolare | M35: Nuovo - Titolare confermato (2/2) | N35: - | O35: - | X35: 2 | Y35: 6.75 | Z35: 8.25 | AA35: 1 | AB35: 0 | AC35: - | AD35: Si | AE35: =ROUND(IF(P35="",5.5,R35*MIN(1,P35/25)+5.5*(1-MIN(1,P35/25))),2) -> 5.5 | AF35: Zaccagni (LAZ) | AG35: 0 | AH35: =RANK(H35,$H$4:$H$196) -> 9
A36: =RANK(B36,$B$4:$B$196) -> 32 | B36: =ROUND(Guida!$B$22*H36/Guida!$B$30+Guida!$B$23*MAX(0,MIN(1,(AE36-5.4)/1.6))+Guida!$B$24*0+Guida!$B$25*0.35,1) -> 26.1 | C36: Saelemaekers | D36: Milan | E36: Esterno basso / Esterno alto | F36: 10 | G36: 11 | H36: 35 | I36: =MAX(1,ROUND(H36^Guida!$B$18*Guida!$F$13,0)) -> 15 | J36: =MAX(2,ROUND(I36*1.2,0)) -> 18 | K36: =IF(I36>=60,"Top",IF(I36>=30,"1a fascia",IF(I36>=15,"2a fascia",IF(I36>=7,"3a fascia",IF(I36>=3,"4a fascia","Scommessa"))))) -> 2a fascia | L36: Ballottaggio | M36: In ballottaggio (2/2) | N36: - | O36: 3o | P36: 35 | Q36: 6.14 | R36: 6.41 | S36: 3 | T36: 3 | U36: 0/0 | V36: 5 | W36: 0 | X36: 2 | Y36: 6.5 | Z36: 7 | AA36: 0 | AB36: 1 | AC36: Milan | AD36: No | AE36: =ROUND(IF(P36="",5.5,R36*MIN(1,P36/25)+5.5*(1-MIN(1,P36/25))),2) -> 6.41 | AF36: Calhanoglu (INT) | AG36: 0 | AH36: =RANK(H36,$H$4:$H$196) -> 39
A37: =RANK(B37,$B$4:$B$196) -> 34 | B37: =ROUND(Guida!$B$22*H37/Guida!$B$30+Guida!$B$23*MAX(0,MIN(1,(AE37-5.4)/1.6))+Guida!$B$24*0+Guida!$B$25*0,1) -> 25.8 | C37: Taylor K. | D37: Lazio | E37: Centrale / Trequartista | F37: 13 | G37: 13 | H37: 53 | I37: =MAX(1,ROUND(H37^Guida!$B$18*Guida!$F$13,0)) -> 20 | J37: =MAX(2,ROUND(I37*1.2,0)) -> 24 | K37: =IF(I37>=60,"Top",IF(I37>=30,"1a fascia",IF(I37>=15,"2a fascia",IF(I37>=7,"3a fascia",IF(I37>=3,"4a fascia","Scommessa"))))) -> 2a fascia | L37: Titolare | M37: Titolare confermato (2/2) | N37: - | O37: - | P37: 17 | Q37: 6.06 | R37: 6.56 | S37: 3 | T37: 2 | U37: 0/0 | V37: 5 | W37: 0 | X37: 2 | Y37: 6 | Z37: 6 | AA37: 0 | AB37: 0 | AC37: Lazio | AD37: No | AE37: =ROUND(IF(P37="",5.5,R37*MIN(1,P37/25)+5.5*(1-MIN(1,P37/25))),2) -> 6.22 | AF37: Konè M. (ROM) | AG37: 0 | AH37: =RANK(H37,$H$4:$H$196) -> 20
A38: =RANK(B38,$B$4:$B$196) -> 35 | B38: =ROUND(Guida!$B$22*H38/Guida!$B$30+Guida!$B$23*MAX(0,MIN(1,(AE38-5.4)/1.6))+Guida!$B$24*0+Guida!$B$25*0,1) -> 25 | C38: Perrone | D38: Como | E38: Mediano / Centrale | F38: 10 | G38: 10 | H38: 34 | I38: =MAX(1,ROUND(H38^Guida!$B$18*Guida!$F$13,0)) -> 15 | J38: =MAX(2,ROUND(I38*1.2,0)) -> 18 | K38: =IF(I38>=60,"Top",IF(I38>=30,"1a fascia",IF(I38>=15,"2a fascia",IF(I38>=7,"3a fascia",IF(I38>=3,"4a fascia","Scommessa"))))) -> 2a fascia | L38: Ballottaggio | M38: In ballottaggio (2/2) | N38: - | O38: - | P38: 36 | Q38: 6.22 | R38: 6.47 | S38: 3 | T38: 4 | U38: 0/0 | V38: 8 | W38: 0 | X38: 2 | Y38: 6 | Z38: 6 | AA38: 0 | AB38: 0 | AC38: Como | AD38: No | AE38: =ROUND(IF(P38="",5.5,R38*MIN(1,P38/25)+5.5*(1-MIN(1,P38/25))),2) -> 6.47 | AF38: Atta (FIO) | AG38: 6 | AH38: =RANK(H38,$H$4:$H$196) -> 41
A39: =RANK(B39,$B$4:$B$196) -> 36 | B39: =ROUND(Guida!$B$22*H39/Guida!$B$30+Guida!$B$23*MAX(0,MIN(1,(AE39-5.4)/1.6))+Guida!$B$24*0+Guida!$B$25*0,1) -> 24.7 | C39: Mandragora | D39: Torino | E39: Centrale | F39: 9 | G39: 8 | H39: 23 | I39: =MAX(1,ROUND(H39^Guida!$B$18*Guida!$F$13,0)) -> 12 | J39: =MAX(2,ROUND(I39*1.2,0)) -> 14 | K39: =IF(I39>=60,"Top",IF(I39>=30,"1a fascia",IF(I39>=15,"2a fascia",IF(I39>=7,"3a fascia",IF(I39>=3,"4a fascia","Scommessa"))))) -> 3a fascia | L39: Titolare | M39: Nuovo - Titolare confermato (2/2) | N39: - | O39: - | P39: 34 | Q39: 6.04 | R39: 6.62 | S39: 7 | T39: 2 | U39: 1/1 | V39: 7 | W39: 0 | X39: 2 | Y39: 5.25 | Z39: 5.25 | AA39: 0 | AB39: 0 | AC39: Fiorentina | AD39: Si | AE39: =ROUND(IF(P39="",5.5,R39*MIN(1,P39/25)+5.5*(1-MIN(1,P39/25))),2) -> 6.62 | AF39: McKennie (JUV) | AG39: 0 | AH39: =RANK(H39,$H$4:$H$196) -> 63
A40: =RANK(B40,$B$4:$B$196) -> 37 | B40: =ROUND(Guida!$B$22*H40/Guida!$B$30+Guida!$B$23*MAX(0,MIN(1,(AE40-5.4)/1.6))+Guida!$B$24*0+Guida!$B$25*0,1) -> 24.6 | C40: Isaksen | D40: Lazio | E40: Esterno alto / Attaccante | F40: 9 | G40: 9 | H40: 22 | I40: =MAX(1,ROUND(H40^Guida!$B$18*Guida!$F$13,0)) -> 12 | J40: =MAX(2,ROUND(I40*1.2,0)) -> 14 | K40: =IF(I40>=60,"Top",IF(I40>=30,"1a fascia",IF(I40>=15,"2a fascia",IF(I40>=7,"3a fascia",IF(I40>=3,"4a fascia","Scommessa"))))) -> 3a fascia | L40: Ballottaggio | M40: In ballottaggio (2/2) | N40: - | O40: - | P40: 27 | Q40: 6.04 | R40: 6.63 | S40: 5 | T40: 1 | U40: 0/0 | V40: 0 | W40: 0 | X40: 2 | Y40: 6 | Z40: 6 | AA40: 0 | AB40: 0 | AC40: Lazio | AD40: No | AE40: =ROUND(IF(P40="",5.5,R40*MIN(1,P40/25)+5.5*(1-MIN(1,P40/25))),2) -> 6.63 | AF40: Konè M. (ROM) | AG40: 0 | AH40: =RANK(H40,$H$4:$H$196) -> 68
A41: =RANK(B41,$B$4:$B$196) -> 38 | B41: =ROUND(Guida!$B$22*H41/Guida!$B$30+Guida!$B$23*MAX(0,MIN(1,(AE41-5.4)/1.6))+Guida!$B$24*0+Guida!$B$25*0,1) -> 24.5 | C41: Gudmundsson A. | D41: Lazio | E41: Trequartista / Attaccante | F41: 13 | G41: 12 | H41: 40 | I41: =MAX(1,ROUND(H41^Guida!$B$18*Guida!$F$13,0)) -> 17 | J41: =MAX(2,ROUND(I41*1.2,0)) -> 20 | K41: =IF(I41>=60,"Top",IF(I41>=30,"1a fascia",IF(I41>=15,"2a fascia",IF(I41>=7,"3a fascia",IF(I41>=3,"4a fascia","Scommessa"))))) -> 2a fascia | L41: Titolare | M41: Nuovo - Rischia il posto (1/2) | N41: - | O41: - | P41: 32 | Q41: 5.88 | R41: 6.34 | S41: 5 | T41: 3 | U41: 3/3 | V41: 4 | W41: 1 | X41: 1 | Y41: 4.5 | Z41: 4 | AA41: 0 | AB41: 0 | AC41: Fiorentina | AD41: Si | AE41: =ROUND(IF(P41="",5.5,R41*MIN(1,P41/25)+5.5*(1-MIN(1,P41/25))),2) -> 6.34 | AF41: Konè M. (ROM) | AG41: 0 | AH41: =RANK(H41,$H$4:$H$196) -> 35
A42: =RANK(B42,$B$4:$B$196) -> 38 | B42: =ROUND(Guida!$B$22*H42/Guida!$B$30+Guida!$B$23*MAX(0,MIN(1,(AE42-5.4)/1.6))+Guida!$B$24*0+Guida!$B$25*0.35,1) -> 24.5 | C42: Pellegrini Lo. | D42: Roma | E42: Centrale / Trequartista | F42: 10 | G42: 9 | H42: 20 | I42: =MAX(1,ROUND(H42^Guida!$B$18*Guida!$F$13,0)) -> 11 | J42: =MAX(2,ROUND(I42*1.2,0)) -> 13 | K42: =IF(I42>=60,"Top",IF(I42>=30,"1a fascia",IF(I42>=15,"2a fascia",IF(I42>=7,"3a fascia",IF(I42>=3,"4a fascia","Scommessa"))))) -> 3a fascia | L42: Titolare | M42: RISCHIA il posto (0/2) | N42: - | O42: 3o | P42: 24 | Q42: 6.04 | R42: 6.58 | S42: 4 | T42: 2 | U42: 2/2 | V42: 2 | W42: 0 | X42: 0 | AC42: Roma | AD42: No | AE42: =ROUND(IF(P42="",5.5,R42*MIN(1,P42/25)+5.5*(1-MIN(1,P42/25))),2) -> 6.54 | AF42: Zaccagni (LAZ) | AG42: 0 | AH42: =RANK(H42,$H$4:$H$196) -> 76
A43: =RANK(B43,$B$4:$B$196) -> 40 | B43: =ROUND(Guida!$B$22*H43/Guida!$B$30+Guida!$B$23*MAX(0,MIN(1,(AE43-5.4)/1.6))+Guida!$B$24*0+Guida!$B$25*0,1) -> 24.1 | C43: Konè I. | D43: Sassuolo | E43: Centrale | F43: 9 | G43: 8 | H43: 20 | I43: =MAX(1,ROUND(H43^Guida!$B$18*Guida!$F$13,0)) -> 11 | J43: =MAX(2,ROUND(I43*1.2,0)) -> 13 | K43: =IF(I43>=60,"Top",IF(I43>=30,"1a fascia",IF(I43>=15,"2a fascia",IF(I43>=7,"3a fascia",IF(I43>=3,"4a fascia","Scommessa"))))) -> 3a fascia | L43: Titolare | M43: INFORTUNATO (lungo stop) - presenze finora: 0/2 | N43: - | O43: - | P43: 35 | Q43: 6.19 | R43: 6.63 | S43: 6 | T43: 0 | U43: 0/0 | V43: 3 | W43: 1 | X43: 0 | AC43: Sassuolo | AD43: No | AE43: =ROUND(IF(P43="",5.5,R43*MIN(1,P43/25)+5.5*(1-MIN(1,P43/25))),2) -> 6.63 | AF43: Calhanoglu (INT) | AG43: 4 | AH43: =RANK(H43,$H$4:$H$196) -> 76 | AI43: Rottura di tibia e perone ai Mondiali di giugno. Punta a rientrare a dicembre.
A44: =RANK(B44,$B$4:$B$196) -> 41 | B44: =ROUND(Guida!$B$22*H44/Guida!$B$30+Guida!$B$23*MAX(0,MIN(1,(AE44-5.4)/1.6))+Guida!$B$24*0+Guida!$B$25*0,1) -> 23.4 | C44: Frattesi | D44: Lazio | E44: Centrale / Trequartista | F44: 7 | G44: 10 | H44: 75 | I44: =MAX(1,ROUND(H44^Guida!$B$18*Guida!$F$13,0)) -> 24 | J44: =MAX(2,ROUND(I44*1.2,0)) -> 29 | K44: =IF(I44>=60,"Top",IF(I44>=30,"1a fascia",IF(I44>=15,"2a fascia",IF(I44>=7,"3a fascia",IF(I44>=3,"4a fascia","Scommessa"))))) -> 2a fascia | L44: Titolare | M44: Nuovo - Titolare confermato (2/2) | N44: - | O44: - | P44: 14 | Q44: 5.89 | R44: 5.89 | S44: 0 | T44: 0 | U44: 0/0 | V44: 0 | W44: 0 | X44: 2 | Y44: 7.25 | Z44: 10.25 | AA44: 2 | AB44: 0 | AC44: Inter | AD44: Si | AE44: =ROUND(IF(P44="",5.5,R44*MIN(1,P44/25)+5.5*(1-MIN(1,P44/25))),2) -> 5.72 | AF44: Konè M. (ROM) | AG44: 0 | AH44: =RANK(H44,$H$4:$H$196) -> 15
A45: =RANK(B45,$B$4:$B$196) -> 42 | B45: =ROUND(Guida!$B$22*H45/Guida!$B$30+Guida!$B$23*MAX(0,MIN(1,(AE45-5.4)/1.6))+Guida!$B$24*0+Guida!$B$25*0.35,1) -> 23.3 | C45: Gaetano | D45: Atalanta | E45: Mediano / Centrale | F45: 7 | G45: 7 | H45: 30 | I45: =MAX(1,ROUND(H45^Guida!$B$18*Guida!$F$13,0)) -> 14 | J45: =MAX(2,ROUND(I45*1.2,0)) -> 17 | K45: =IF(I45>=60,"Top",IF(I45>=30,"1a fascia",IF(I45>=15,"2a fascia",IF(I45>=7,"3a fascia",IF(I45>=3,"4a fascia","Scommessa"))))) -> 3a fascia | L45: Ballottaggio | M45: Nuovo - In ballottaggio (2/2) | N45: - | O45: 3o | P45: 32 | Q45: 6.06 | R45: 6.31 | S45: 2 | T45: 4 | U45: 0/0 | V45: 4 | W45: 0 | X45: 2 | Y45: 5.75 | Z45: 6.25 | AA45: 0 | AB45: 1 | AC45: Cagliari | AD45: Si | AE45: =ROUND(IF(P45="",5.5,R45*MIN(1,P45/25)+5.5*(1-MIN(1,P45/25))),2) -> 6.31 | AF45: Calò (FRO) | AG45: 5 | AH45: =RANK(H45,$H$4:$H$196) -> 45
A46: =RANK(B46,$B$4:$B$196) -> 43 | B46: =ROUND(Guida!$B$22*H46/Guida!$B$30+Guida!$B$23*MAX(0,MIN(1,(AE46-5.4)/1.6))+Guida!$B$24*1+Guida!$B$25*1,1) -> 23.2 | C46: Calò | D46: Frosinone | E46: Mediano / Centrale | F46: 7 | G46: 8 | H46: 27 | I46: =MAX(1,ROUND(H46^Guida!$B$18*Guida!$F$13,0)) -> 13 | J46: =MAX(2,ROUND(I46*1.2,0)) -> 16 | K46: =IF(I46>=60,"Top",IF(I46>=30,"1a fascia",IF(I46>=15,"2a fascia",IF(I46>=7,"3a fascia",IF(I46>=3,"4a fascia","Scommessa"))))) -> 3a fascia | L46: Titolare | M46: Nuovo - Titolare confermato (2/2) | N46: 1o | O46: 1o | X46: 2 | Y46: 6.25 | Z46: 6.75 | AA46: 0 | AB46: 1 | AC46: - | AD46: Si | AE46: =ROUND(IF(P46="",5.5,R46*MIN(1,P46/25)+5.5*(1-MIN(1,P46/25))),2) -> 5.5 | AF46: Samardzic (ATA) | AG46: 5 | AH46: =RANK(H46,$H$4:$H$196) -> 51
A47: =RANK(B47,$B$4:$B$196) -> 44 | B47: =ROUND(Guida!$B$22*H47/Guida!$B$30+Guida!$B$23*MAX(0,MIN(1,(AE47-5.4)/1.6))+Guida!$B$24*0+Guida!$B$25*0,1) -> 23 | C47: Casadei | D47: Torino | E47: Centrale / Trequartista | F47: 10 | G47: 9 | H47: 27 | I47: =MAX(1,ROUND(H47^Guida!$B$18*Guida!$F$13,0)) -> 13 | J47: =MAX(2,ROUND(I47*1.2,0)) -> 16 | K47: =IF(I47>=60,"Top",IF(I47>=30,"1a fascia",IF(I47>=15,"2a fascia",IF(I47>=7,"3a fascia",IF(I47>=3,"4a fascia","Scommessa"))))) -> 3a fascia | L47: Titolare | M47: In dubbio / da valutare - presenze finora: 1/2 | N47: - | O47: - | P47: 32 | Q47: 5.97 | R47: 6.45 | S47: 6 | T47: 0 | U47: 0/0 | V47: 5 | W47: 0 | X47: 1 | Y47: 5 | Z47: 5 | AA47: 0 | AB47: 0 | AC47: Torino | AD47: No | AE47: =ROUND(IF(P47="",5.5,R47*MIN(1,P47/25)+5.5*(1-MIN(1,P47/25))),2) -> 6.45 | AF47: McKennie (JUV) | AG47: 0 | AH47: =RANK(H47,$H$4:$H$196) -> 51 | AI47: Affaticamento muscolare: fuori col Sassuolo, a rischio anche a Firenze.
A48: =RANK(B48,$B$4:$B$196) -> 45 | B48: =ROUND(Guida!$B$22*H48/Guida!$B$30+Guida!$B$23*MAX(0,MIN(1,(AE48-5.4)/1.6))+Guida!$B$24*0+Guida!$B$25*1,1) -> 22.8 | C48: Baldanzi | D48: Genoa | E48: Trequartista | F48: 11 | G48: 11 | H48: 28 | I48: =MAX(1,ROUND(H48^Guida!$B$18*Guida!$F$13,0)) -> 13 | J48: =MAX(2,ROUND(I48*1.2,0)) -> 16 | K48: =IF(I48>=60,"Top",IF(I48>=30,"1a fascia",IF(I48>=15,"2a fascia",IF(I48>=7,"3a fascia",IF(I48>=3,"4a fascia","Scommessa"))))) -> 3a fascia | L48: Titolare | M48: Titolare confermato (2/2) | N48: - | O48: 1o | P48: 17 | Q48: 6.15 | R48: 6.38 | S48: 1 | T48: 2 | U48: 0/0 | V48: 2 | W48: 0 | X48: 2 | Y48: 5.75 | Z48: 5.75 | AA48: 0 | AB48: 0 | AC48: Genoa | AD48: No | AE48: =ROUND(IF(P48="",5.5,R48*MIN(1,P48/25)+5.5*(1-MIN(1,P48/25))),2) -> 6.1 | AF48: McKennie (JUV) | AG48: 5 | AH48: =RANK(H48,$H$4:$H$196) -> 48
A49: =RANK(B49,$B$4:$B$196) -> 46 | B49: =ROUND(Guida!$B$22*H49/Guida!$B$30+Guida!$B$23*MAX(0,MIN(1,(AE49-5.4)/1.6))+Guida!$B$24*0+Guida!$B$25*0,1) -> 21.7 | C49: Thuram K. | D49: Juventus | E49: Centrale | F49: 10 | G49: 9 | H49: 25 | I49: =MAX(1,ROUND(H49^Guida!$B$18*Guida!$F$13,0)) -> 12 | J49: =MAX(2,ROUND(I49*1.2,0)) -> 14 | K49: =IF(I49>=60,"Top",IF(I49>=30,"1a fascia",IF(I49>=15,"2a fascia",IF(I49>=7,"3a fascia",IF(I49>=3,"4a fascia","Scommessa"))))) -> 3a fascia | L49: Ballottaggio | M49: In dubbio / da valutare - presenze finora: 0/2 | N49: - | O49: - | P49: 34 | Q49: 6.1 | R49: 6.4 | S49: 3 | T49: 2 | U49: 0/0 | V49: 2 | W49: 0 | X49: 0 | AC49: Juventus | AD49: No | AE49: =ROUND(IF(P49="",5.5,R49*MIN(1,P49/25)+5.5*(1-MIN(1,P49/25))),2) -> 6.4 | AF49: Vlasic (TOR) | AG49: 0 | AH49: =RANK(H49,$H$4:$H$196) -> 54 | AI49: Sindrome femoro-rotulea, non convocato col Parma. Da valutare per il Milan.
A50: =RANK(B50,$B$4:$B$196) -> 47 | B50: =ROUND(Guida!$B$22*H50/Guida!$B$30+Guida!$B$23*MAX(0,MIN(1,(AE50-5.4)/1.6))+Guida!$B$24*0.35+Guida!$B$25*0.6,1) -> 21.6 | C50: Berisha M. | D50: Lecce | E50: Centrale / Trequartista | F50: 5 | G50: 4 | H50: 12 | I50: =MAX(1,ROUND(H50^Guida!$B$18*Guida!$F$13,0)) -> 8 | J50: =MAX(2,ROUND(I50*1.2,0)) -> 10 | K50: =IF(I50>=60,"Top",IF(I50>=30,"1a fascia",IF(I50>=15,"2a fascia",IF(I50>=7,"3a fascia",IF(I50>=3,"4a fascia","Scommessa"))))) -> 3a fascia | L50: Ballottaggio | M50: In ballottaggio (0/2) | N50: 3o | O50: 2o | P50: 12 | Q50: 6.17 | R50: 6.92 | S50: 2 | T50: 3 | U50: 0/0 | V50: 0 | W50: 0 | X50: 0 | AC50: Lecce | AD50: No | AE50: =ROUND(IF(P50="",5.5,R50*MIN(1,P50/25)+5.5*(1-MIN(1,P50/25))),2) -> 6.18 | AF50: Bernabè (PAR) | AG50: 4 | AH50: =RANK(H50,$H$4:$H$196) -> 118
A51: =RANK(B51,$B$4:$B$196) -> 48 | B51: =ROUND(Guida!$B$22*H51/Guida!$B$30+Guida!$B$23*MAX(0,MIN(1,(AE51-5.4)/1.6))+Guida!$B$24*0+Guida!$B$25*0,1) -> 21.4 | C51: Cambiaghi | D51: Bologna | E51: Esterno alto / Attaccante | F51: 8 | G51: 8 | H51: 25 | I51: =MAX(1,ROUND(H51^Guida!$B$18*Guida!$F$13,0)) -> 12 | J51: =MAX(2,ROUND(I51*1.2,0)) -> 14 | K51: =IF(I51>=60,"Top",IF(I51>=30,"1a fascia",IF(I51>=15,"2a fascia",IF(I51>=7,"3a fascia",IF(I51>=3,"4a fascia","Scommessa"))))) -> 3a fascia | L51: Titolare | M51: Titolare confermato (2/2) | N51: - | O51: - | P51: 24 | Q51: 5.98 | R51: 6.42 | S51: 3 | T51: 4 | U51: 0/0 | V51: 3 | W51: 1 | X51: 2 | Y51: 6 | Z51: 5.75 | AA51: 0 | AB51: 0 | AC51: Bologna | AD51: No | AE51: =ROUND(IF(P51="",5.5,R51*MIN(1,P51/25)+5.5*(1-MIN(1,P51/25))),2) -> 6.38 | AF51: Politano (NAP) | AG51: 6 | AH51: =RANK(H51,$H$4:$H$196) -> 54
A52: =RANK(B52,$B$4:$B$196) -> 49 | B52: =ROUND(Guida!$B$22*H52/Guida!$B$30+Guida!$B$23*MAX(0,MIN(1,(AE52-5.4)/1.6))+Guida!$B$24*0+Guida!$B$25*0,1) -> 21.1 | C52: Volpato | D52: Sassuolo | E52: Esterno alto / Trequartista | F52: 7 | G52: 9 | H52: 25 | I52: =MAX(1,ROUND(H52^Guida!$B$18*Guida!$F$13,0)) -> 12 | J52: =MAX(2,ROUND(I52*1.2,0)) -> 14 | K52: =IF(I52>=60,"Top",IF(I52>=30,"1a fascia",IF(I52>=15,"2a fascia",IF(I52>=7,"3a fascia",IF(I52>=3,"4a fascia","Scommessa"))))) -> 3a fascia | L52: Titolare | M52: Titolare confermato (2/2) | N52: - | O52: - | P52: 21 | Q52: 6.14 | R52: 6.52 | S52: 2 | T52: 4 | U52: 0/0 | V52: 4 | W52: 0 | X52: 2 | Y52: 6.75 | Z52: 8 | AA52: 1 | AB52: 0 | AC52: Sassuolo | AD52: No | AE52: =ROUND(IF(P52="",5.5,R52*MIN(1,P52/25)+5.5*(1-MIN(1,P52/25))),2) -> 6.36 | AF52: Zielinski (INT) | AG52: 4 | AH52: =RANK(H52,$H$4:$H$196) -> 54
A53: =RANK(B53,$B$4:$B$196) -> 50 | B53: =ROUND(Guida!$B$22*H53/Guida!$B$30+Guida!$B$23*MAX(0,MIN(1,(AE53-5.4)/1.6))+Guida!$B$24*0+Guida!$B$25*0,1) -> 21 | C53: Odgaard | D53: Bologna | E53: Trequartista | F53: 8 | G53: 8 | H53: 17 | I53: =MAX(1,ROUND(H53^Guida!$B$18*Guida!$F$13,0)) -> 10 | J53: =MAX(2,ROUND(I53*1.2,0)) -> 12 | K53: =IF(I53>=60,"Top",IF(I53>=30,"1a fascia",IF(I53>=15,"2a fascia",IF(I53>=7,"3a fascia",IF(I53>=3,"4a fascia","Scommessa"))))) -> 3a fascia | L53: Ballottaggio | M53: In ballottaggio (2/2) | N53: - | O53: - | P53: 22 | Q53: 5.91 | R53: 6.61 | S53: 5 | T53: 1 | U53: 0/0 | V53: 1 | W53: 0 | X53: 2 | Y53: 5.75 | Z53: 5.5 | AA53: 0 | AB53: 0 | AC53: Bologna | AD53: No | AE53: =ROUND(IF(P53="",5.5,R53*MIN(1,P53/25)+5.5*(1-MIN(1,P53/25))),2) -> 6.48 | AF53: Politano (NAP) | AG53: 6 | AH53: =RANK(H53,$H$4:$H$196) -> 88
A54: =RANK(B54,$B$4:$B$196) -> 51 | B54: =ROUND(Guida!$B$22*H54/Guida!$B$30+Guida!$B$23*MAX(0,MIN(1,(AE54-5.4)/1.6))+Guida!$B$24*0+Guida!$B$25*0,1) -> 20.8 | C54: Mkhitaryan | D54: Inter | E54: Centrale | F54: 5 | G54: 4 | H54: 9 | I54: =MAX(1,ROUND(H54^Guida!$B$18*Guida!$F$13,0)) -> 7 | J54: =MAX(2,ROUND(I54*1.2,0)) -> 8 | K54: =IF(I54>=60,"Top",IF(I54>=30,"1a fascia",IF(I54>=15,"2a fascia",IF(I54>=7,"3a fascia",IF(I54>=3,"4a fascia","Scommessa"))))) -> 3a fascia | L54: Riserva | M54: Riserva (0/2) | N54: - | O54: - | P54: 28 | Q54: 6.21 | R54: 6.59 | S54: 4 | T54: 1 | U54: 0/0 | V54: 5 | W54: 0 | X54: 0 | AC54: Inter | AD54: No | AE54: =ROUND(IF(P54="",5.5,R54*MIN(1,P54/25)+5.5*(1-MIN(1,P54/25))),2) -> 6.59 | AF54: Modric (MIL) | AG54: 0 | AH54: =RANK(H54,$H$4:$H$196) -> 153
A55: =RANK(B55,$B$4:$B$196) -> 52 | B55: =ROUND(Guida!$B$22*H55/Guida!$B$30+Guida!$B$23*MAX(0,MIN(1,(AE55-5.4)/1.6))+Guida!$B$24*1+Guida!$B$25*1,1) -> 20.2 | C55: Pessina | D55: Monza | E55: Mediano / Centrale | F55: 7 | G55: 6 | H55: 15 | I55: =MAX(1,ROUND(H55^Guida!$B$18*Guida!$F$13,0)) -> 9 | J55: =MAX(2,ROUND(I55*1.2,0)) -> 11 | K55: =IF(I55>=60,"Top",IF(I55>=30,"1a fascia",IF(I55>=15,"2a fascia",IF(I55>=7,"3a fascia",IF(I55>=3,"4a fascia","Scommessa"))))) -> 3a fascia | L55: Titolare | M55: INFORTUNATO (lungo stop) - Nuovo - presenze finora: 0/2 | N55: 1o | O55: 1o | X55: 0 | AC55: - | AD55: Si | AE55: =ROUND(IF(P55="",5.5,R55*MIN(1,P55/25)+5.5*(1-MIN(1,P55/25))),2) -> 5.5 | AF55: Berisha M. (LEC) | AG55: 6 | AH55: =RANK(H55,$H$4:$H$196) -> 99 | AI55: Lussazione della rotula del ginocchio destro. Prova a rientrare da inizio novembre.
A56: =RANK(B56,$B$4:$B$196) -> 53 | B56: =ROUND(Guida!$B$22*H56/Guida!$B$30+Guida!$B$23*MAX(0,MIN(1,(AE56-5.4)/1.6))+Guida!$B$24*0+Guida!$B$25*0,1) -> 20 | C56: Cancellieri | D56: Lazio | E56: Esterno alto / Attaccante | F56: 9 | G56: 9 | H56: 25 | I56: =MAX(1,ROUND(H56^Guida!$B$18*Guida!$F$13,0)) -> 12 | J56: =MAX(2,ROUND(I56*1.2,0)) -> 14 | K56: =IF(I56>=60,"Top",IF(I56>=30,"1a fascia",IF(I56>=15,"2a fascia",IF(I56>=7,"3a fascia",IF(I56>=3,"4a fascia","Scommessa"))))) -> 3a fascia | L56: Ballottaggio | M56: In ballottaggio (2/2) | N56: - | O56: - | P56: 28 | Q56: 5.93 | R56: 6.29 | S56: 4 | T56: 1 | U56: 0/0 | V56: 6 | W56: 0 | X56: 2 | Y56: 5.75 | Z56: 5.5 | AA56: 0 | AB56: 0 | AC56: Lazio | AD56: No | AE56: =ROUND(IF(P56="",5.5,R56*MIN(1,P56/25)+5.5*(1-MIN(1,P56/25))),2) -> 6.29 | AF56: Konè M. (ROM) | AG56: 0 | AH56: =RANK(H56,$H$4:$H$196) -> 54
A57: =RANK(B57,$B$4:$B$196) -> 53 | B57: =ROUND(Guida!$B$22*H57/Guida!$B$30+Guida!$B$23*MAX(0,MIN(1,(AE57-5.4)/1.6))+Guida!$B$24*0+Guida!$B$25*0,1) -> 20 | C57: Zalewski | D57: Atalanta | E57: Esterno alto | F57: 6 | G57: 7 | H57: 18 | I57: =MAX(1,ROUND(H57^Guida!$B$18*Guida!$F$13,0)) -> 10 | J57: =MAX(2,ROUND(I57*1.2,0)) -> 12 | K57: =IF(I57>=60,"Top",IF(I57>=30,"1a fascia",IF(I57>=15,"2a fascia",IF(I57>=7,"3a fascia",IF(I57>=3,"4a fascia","Scommessa"))))) -> 3a fascia | L57: Riserva | M57: Riserva (2/2) | N57: - | O57: - | P57: 31 | Q57: 6.1 | R57: 6.4 | S57: 2 | T57: 5 | U57: 0/0 | V57: 3 | W57: 0 | X57: 2 | Y57: 6.25 | Z57: 6.75 | AA57: 0 | AB57: 1 | AC57: Atalanta | AD57: No | AE57: =ROUND(IF(P57="",5.5,R57*MIN(1,P57/25)+5.5*(1-MIN(1,P57/25))),2) -> 6.4 | AF57: Calò (FRO) | AG57: 5 | AH57: =RANK(H57,$H$4:$H$196) -> 85
A58: =RANK(B58,$B$4:$B$196) -> 53 | B58: =ROUND(Guida!$B$22*H58/Guida!$B$30+Guida!$B$23*MAX(0,MIN(1,(AE58-5.4)/1.6))+Guida!$B$24*1+Guida!$B$25*1,1) -> 20 | C58: Busio | D58: Venezia | E58: Mediano / Centrale | F58: 5 | G58: 5 | H58: 14 | I58: =MAX(1,ROUND(H58^Guida!$B$18*Guida!$F$13,0)) -> 9 | J58: =MAX(2,ROUND(I58*1.2,0)) -> 11 | K58: =IF(I58>=60,"Top",IF(I58>=30,"1a fascia",IF(I58>=15,"2a fascia",IF(I58>=7,"3a fascia",IF(I58>=3,"4a fascia","Scommessa"))))) -> 3a fascia | L58: Titolare | M58: Nuovo - Titolare confermato (2/2) | N58: 1o | O58: 1o | X58: 2 | Y58: 5.75 | Z58: 5.75 | AA58: 0 | AB58: 0 | AC58: - | AD58: Si | AE58: =ROUND(IF(P58="",5.5,R58*MIN(1,P58/25)+5.5*(1-MIN(1,P58/25))),2) -> 5.5 | AF58: Pessina (MON) | AG58: 6 | AH58: =RANK(H58,$H$4:$H$196) -> 110
A59: =RANK(B59,$B$4:$B$196) -> 56 | B59: =ROUND(Guida!$B$22*H59/Guida!$B$30+Guida!$B$23*MAX(0,MIN(1,(AE59-5.4)/1.6))+Guida!$B$24*0+Guida!$B$25*0,1) -> 19.9 | C59: Cristante | D59: Roma | E59: Mediano / Centrale | F59: 8 | G59: 9 | H59: 29 | I59: =MAX(1,ROUND(H59^Guida!$B$18*Guida!$F$13,0)) -> 14 | J59: =MAX(2,ROUND(I59*1.2,0)) -> 17 | K59: =IF(I59>=60,"Top",IF(I59>=30,"1a fascia",IF(I59>=15,"2a fascia",IF(I59>=7,"3a fascia",IF(I59>=3,"4a fascia","Scommessa"))))) -> 3a fascia | L59: Titolare | M59: Titolare confermato (2/2) | N59: - | O59: - | P59: 37 | Q59: 6.11 | R59: 6.22 | S59: 2 | T59: 1 | U59: 0/0 | V59: 6 | W59: 0 | X59: 2 | Y59: 6.5 | Z59: 6.5 | AA59: 0 | AB59: 0 | AC59: Roma | AD59: No | AE59: =ROUND(IF(P59="",5.5,R59*MIN(1,P59/25)+5.5*(1-MIN(1,P59/25))),2) -> 6.22 | AF59: Cataldi (LAZ) | AG59: 0 | AH59: =RANK(H59,$H$4:$H$196) -> 47
A60: =RANK(B60,$B$4:$B$196) -> 56 | B60: =ROUND(Guida!$B$22*H60/Guida!$B$30+Guida!$B$23*MAX(0,MIN(1,(AE60-5.4)/1.6))+Guida!$B$24*0+Guida!$B$25*0,1) -> 19.9 | C60: Caqueret | D60: Como | E60: Centrale / Trequartista | F60: 6 | G60: 6 | H60: 17 | I60: =MAX(1,ROUND(H60^Guida!$B$18*Guida!$F$13,0)) -> 10 | J60: =MAX(2,ROUND(I60*1.2,0)) -> 12 | K60: =IF(I60>=60,"Top",IF(I60>=30,"1a fascia",IF(I60>=15,"2a fascia",IF(I60>=7,"3a fascia",IF(I60>=3,"4a fascia","Scommessa"))))) -> 3a fascia | L60: Riserva | M60: Riserva (1/2) | N60: - | O60: - | P60: 28 | Q60: 6.11 | R60: 6.41 | S60: 2 | T60: 4 | U60: 0/0 | V60: 3 | W60: 0 | X60: 1 | Y60: 6 | Z60: 6 | AA60: 0 | AB60: 0 | AC60: Como | AD60: No | AE60: =ROUND(IF(P60="",5.5,R60*MIN(1,P60/25)+5.5*(1-MIN(1,P60/25))),2) -> 6.41 | AF60: Calò (FRO) | AG60: 6 | AH60: =RANK(H60,$H$4:$H$196) -> 88
A61: =RANK(B61,$B$4:$B$196) -> 58 | B61: =ROUND(Guida!$B$22*H61/Guida!$B$30+Guida!$B$23*MAX(0,MIN(1,(AE61-5.4)/1.6))+Guida!$B$24*0+Guida!$B$25*0,1) -> 19.7 | C61: Basic | D61: Venezia | E61: Mediano / Centrale | F61: 6 | G61: 6 | H61: 19 | I61: =MAX(1,ROUND(H61^Guida!$B$18*Guida!$F$13,0)) -> 11 | J61: =MAX(2,ROUND(I61*1.2,0)) -> 13 | K61: =IF(I61>=60,"Top",IF(I61>=30,"1a fascia",IF(I61>=15,"2a fascia",IF(I61>=7,"3a fascia",IF(I61>=3,"4a fascia","Scommessa"))))) -> 3a fascia | L61: Titolare | M61: Nuovo - Titolare confermato (2/2) | N61: - | O61: - | P61: 23 | Q61: 6.09 | R61: 6.43 | S61: 2 | T61: 3 | U61: 0/0 | V61: 0 | W61: 1 | X61: 2 | Y61: 5.75 | Z61: 5.75 | AA61: 0 | AB61: 0 | AC61: Lazio | AD61: Si | AE61: =ROUND(IF(P61="",5.5,R61*MIN(1,P61/25)+5.5*(1-MIN(1,P61/25))),2) -> 6.36 | AF61: Pessina (MON) | AG61: 6 | AH61: =RANK(H61,$H$4:$H$196) -> 81
A62: =RANK(B62,$B$4:$B$196) -> 58 | B62: =ROUND(Guida!$B$22*H62/Guida!$B$30+Guida!$B$23*MAX(0,MIN(1,(AE62-5.4)/1.6))+Guida!$B$24*0+Guida!$B$25*0,1) -> 19.7 | C62: Pisilli | D62: Roma | E62: Centrale | F62: 5 | G62: 7 | H62: 19 | I62: =MAX(1,ROUND(H62^Guida!$B$18*Guida!$F$13,0)) -> 11 | J62: =MAX(2,ROUND(I62*1.2,0)) -> 13 | K62: =IF(I62>=60,"Top",IF(I62>=30,"1a fascia",IF(I62>=15,"2a fascia",IF(I62>=7,"3a fascia",IF(I62>=3,"4a fascia","Scommessa"))))) -> 3a fascia | L62: Ballottaggio | M62: In ballottaggio (2/2) | N62: - | O62: - | P62: 22 | Q62: 6.09 | R62: 6.48 | S62: 2 | T62: 4 | U62: 0/0 | V62: 3 | W62: 0 | X62: 2 | Y62: 6.5 | Z62: 8 | AA62: 1 | AB62: 0 | AC62: Roma | AD62: No | AE62: =ROUND(IF(P62="",5.5,R62*MIN(1,P62/25)+5.5*(1-MIN(1,P62/25))),2) -> 6.36 | AF62: Cataldi (LAZ) | AG62: 0 | AH62: =RANK(H62,$H$4:$H$196) -> 81
A63: =RANK(B63,$B$4:$B$196) -> 60 | B63: =ROUND(Guida!$B$22*H63/Guida!$B$30+Guida!$B$23*MAX(0,MIN(1,(AE63-5.4)/1.6))+Guida!$B$24*0+Guida!$B$25*0,1) -> 19 | C63: Pasalic | D63: Atalanta | E63: Centrale / Trequartista | F63: 9 | G63: 8 | H63: 22 | I63: =MAX(1,ROUND(H63^Guida!$B$18*Guida!$F$13,0)) -> 12 | J63: =MAX(2,ROUND(I63*1.2,0)) -> 14 | K63: =IF(I63>=60,"Top",IF(I63>=30,"1a fascia",IF(I63>=15,"2a fascia",IF(I63>=7,"3a fascia",IF(I63>=3,"4a fascia","Scommessa"))))) -> 3a fascia | L63: Ballottaggio | M63: In ballottaggio (2/2) | N63: - | O63: - | P63: 31 | Q63: 5.94 | R63: 6.27 | S63: 3 | T63: 3 | U63: 0/0 | V63: 3 | W63: 0 | X63: 2 | Y63: 5.5 | Z63: 5.5 | AA63: 0 | AB63: 0 | AC63: Atalanta | AD63: No | AE63: =ROUND(IF(P63="",5.5,R63*MIN(1,P63/25)+5.5*(1-MIN(1,P63/25))),2) -> 6.27 | AF63: Calò (FRO) | AG63: 5 | AH63: =RANK(H63,$H$4:$H$196) -> 68
A64: =RANK(B64,$B$4:$B$196) -> 61 | B64: =ROUND(Guida!$B$22*H64/Guida!$B$30+Guida!$B$23*MAX(0,MIN(1,(AE64-5.4)/1.6))+Guida!$B$24*0+Guida!$B$25*0,1) -> 18.9 | C64: Loftus-Cheek | D64: Milan | E64: Centrale / Trequartista | F64: 4 | G64: 4 | H64: 16 | I64: =MAX(1,ROUND(H64^Guida!$B$18*Guida!$F$13,0)) -> 10 | J64: =MAX(2,ROUND(I64*1.2,0)) -> 12 | K64: =IF(I64>=60,"Top",IF(I64>=30,"1a fascia",IF(I64>=15,"2a fascia",IF(I64>=7,"3a fascia",IF(I64>=3,"4a fascia","Scommessa"))))) -> 3a fascia | L64: Riserva | M64: Riserva (2/2) | N64: - | O64: - | P64: 21 | Q64: 6.1 | R64: 6.52 | S64: 3 | T64: 1 | U64: 0/0 | V64: 2 | W64: 0 | X64: 2 | Y64: 6 | Z64: 5.75 | AA64: 0 | AB64: 0 | AC64: Milan | AD64: No | AE64: =ROUND(IF(P64="",5.5,R64*MIN(1,P64/25)+5.5*(1-MIN(1,P64/25))),2) -> 6.36 | AF64: Mkhitaryan (INT) | AG64: 0 | AH64: =RANK(H64,$H$4:$H$196) -> 93
A65: =RANK(B65,$B$4:$B$196) -> 62 | B65: =ROUND(Guida!$B$22*H65/Guida!$B$30+Guida!$B$23*MAX(0,MIN(1,(AE65-5.4)/1.6))+Guida!$B$24*0+Guida!$B$25*0,1) -> 18.7 | C65: Sucic P. | D65: Inter | E65: Centrale | F65: 8 | G65: 9 | H65: 21 | I65: =MAX(1,ROUND(H65^Guida!$B$18*Guida!$F$13,0)) -> 11 | J65: =MAX(2,ROUND(I65*1.2,0)) -> 13 | K65: =IF(I65>=60,"Top",IF(I65>=30,"1a fascia",IF(I65>=15,"2a fascia",IF(I65>=7,"3a fascia",IF(I65>=3,"4a fascia","Scommessa"))))) -> 3a fascia | L65: Ballottaggio | M65: In ballottaggio (2/2) | N65: - | O65: - | P65: 28 | Q65: 6.07 | R65: 6.27 | S65: 2 | T65: 2 | U65: 0/0 | V65: 5 | W65: 0 | X65: 2 | Y65: 6.5 | Z65: 6.5 | AA65: 0 | AB65: 0 | AC65: Inter | AD65: No | AE65: =ROUND(IF(P65="",5.5,R65*MIN(1,P65/25)+5.5*(1-MIN(1,P65/25))),2) -> 6.27 | AF65: Saelemaekers (MIL) | AG65: 0 | AH65: =RANK(H65,$H$4:$H$196) -> 73
A66: =RANK(B66,$B$4:$B$196) -> 63 | B66: =ROUND(Guida!$B$22*H66/Guida!$B$30+Guida!$B$23*MAX(0,MIN(1,(AE66-5.4)/1.6))+Guida!$B$24*0+Guida!$B$25*0,1) -> 18.1 | C66: Coulibaly L. | D66: Lecce | E66: Mediano / Centrale | F66: 6 | G66: 7 | H66: 17 | I66: =MAX(1,ROUND(H66^Guida!$B$18*Guida!$F$13,0)) -> 10 | J66: =MAX(2,ROUND(I66*1.2,0)) -> 12 | K66: =IF(I66>=60,"Top",IF(I66>=30,"1a fascia",IF(I66>=15,"2a fascia",IF(I66>=7,"3a fascia",IF(I66>=3,"4a fascia","Scommessa"))))) -> 3a fascia | L66: Titolare | M66: Titolare confermato (2/2) | N66: - | O66: - | P66: 33 | Q66: 6.05 | R66: 6.29 | S66: 3 | T66: 1 | U66: 0/0 | V66: 4 | W66: 0 | X66: 2 | Y66: 6 | Z66: 6.5 | AA66: 0 | AB66: 1 | AC66: Lecce | AD66: No | AE66: =ROUND(IF(P66="",5.5,R66*MIN(1,P66/25)+5.5*(1-MIN(1,P66/25))),2) -> 6.29 | AF66: Konè M. (ROM) | AG66: 6 | AH66: =RANK(H66,$H$4:$H$196) -> 88
A67: =RANK(B67,$B$4:$B$196) -> 64 | B67: =ROUND(Guida!$B$22*H67/Guida!$B$30+Guida!$B$23*MAX(0,MIN(1,(AE67-5.4)/1.6))+Guida!$B$24*0+Guida!$B$25*0,1) -> 18 | C67: Diouf | D67: Inter | E67: Esterno basso / Centrale | F67: 8 | G67: 9 | H67: 43 | I67: =MAX(1,ROUND(H67^Guida!$B$18*Guida!$F$13,0)) -> 17 | J67: =MAX(2,ROUND(I67*1.2,0)) -> 20 | K67: =IF(I67>=60,"Top",IF(I67>=30,"1a fascia",IF(I67>=15,"2a fascia",IF(I67>=7,"3a fascia",IF(I67>=3,"4a fascia","Scommessa"))))) -> 2a fascia | L67: Ballottaggio | M67: In ballottaggio (1/2) | N67: - | O67: - | P67: 10 | Q67: 6.15 | R67: 6.45 | S67: 1 | T67: 0 | U67: 0/0 | V67: 1 | W67: 0 | X67: 1 | Y67: 7 | Z67: 9 | AA67: 0 | AB67: 2 | AC67: Inter | AD67: No | AE67: =ROUND(IF(P67="",5.5,R67*MIN(1,P67/25)+5.5*(1-MIN(1,P67/25))),2) -> 5.88 | AF67: Saelemaekers (MIL) | AG67: 0 | AH67: =RANK(H67,$H$4:$H$196) -> 31
A68: =RANK(B68,$B$4:$B$196) -> 65 | B68: =ROUND(Guida!$B$22*H68/Guida!$B$30+Guida!$B$23*MAX(0,MIN(1,(AE68-5.4)/1.6))+Guida!$B$24*0+Guida!$B$25*0,1) -> 17.9 | C68: Fagioli | D68: Fiorentina | E68: Mediano / Centrale | F68: 8 | G68: 7 | H68: 20 | I68: =MAX(1,ROUND(H68^Guida!$B$18*Guida!$F$13,0)) -> 11 | J68: =MAX(2,ROUND(I68*1.2,0)) -> 13 | K68: =IF(I68>=60,"Top",IF(I68>=30,"1a fascia",IF(I68>=15,"2a fascia",IF(I68>=7,"3a fascia",IF(I68>=3,"4a fascia","Scommessa"))))) -> 3a fascia | L68: Ballottaggio | M68: In ballottaggio (2/2) | N68: - | O68: - | P68: 33 | Q68: 6.03 | R68: 6.23 | S68: 2 | T68: 3 | U68: 0/0 | V68: 5 | W68: 0 | X68: 2 | Y68: 5.5 | Z68: 5.25 | AA68: 0 | AB68: 0 | AC68: Fiorentina | AD68: No | AE68: =ROUND(IF(P68="",5.5,R68*MIN(1,P68/25)+5.5*(1-MIN(1,P68/25))),2) -> 6.23 | AF68: Rodriguez Je. (COM) | AG68: 6 | AH68: =RANK(H68,$H$4:$H$196) -> 76
A69: =RANK(B69,$B$4:$B$196) -> 66 | B69: =ROUND(Guida!$B$22*H69/Guida!$B$30+Guida!$B$23*MAX(0,MIN(1,(AE69-5.4)/1.6))+Guida!$B$24*0+Guida!$B$25*0,1) -> 17.6 | C69: Messias | D69: Genoa | E69: Esterno alto / Trequartista | F69: 3 | G69: 4 | H69: 8 | I69: =MAX(1,ROUND(H69^Guida!$B$18*Guida!$F$13,0)) -> 6 | J69: =MAX(2,ROUND(I69*1.2,0)) -> 7 | K69: =IF(I69>=60,"Top",IF(I69>=30,"1a fascia",IF(I69>=15,"2a fascia",IF(I69>=7,"3a fascia",IF(I69>=3,"4a fascia","Scommessa"))))) -> 4a fascia | L69: Riserva | M69: Riserva (2/2) | N69: - | O69: - | P69: 19 | Q69: 6.18 | R69: 6.68 | S69: 3 | T69: 1 | U69: 1/1 | V69: 1 | W69: 0 | X69: 2 | Y69: 6 | Z69: 6 | AA69: 0 | AB69: 0 | AC69: Genoa | AD69: No | AE69: =ROUND(IF(P69="",5.5,R69*MIN(1,P69/25)+5.5*(1-MIN(1,P69/25))),2) -> 6.4 | AF69: Locatelli (JUV) | AG69: 5 | AH69: =RANK(H69,$H$4:$H$196) -> 154
A70: =RANK(B70,$B$4:$B$196) -> 67 | B70: =ROUND(Guida!$B$22*H70/Guida!$B$30+Guida!$B$23*MAX(0,MIN(1,(AE70-5.4)/1.6))+Guida!$B$24*0+Guida!$B$25*0.6,1) -> 16.8 | C70: Mastantuono | D70: Fiorentina | E70: Esterno alto / Trequartista | F70: 12 | G70: 11 | H70: 50 | I70: =MAX(1,ROUND(H70^Guida!$B$18*Guida!$F$13,0)) -> 19 | J70: =MAX(2,ROUND(I70*1.2,0)) -> 23 | K70: =IF(I70>=60,"Top",IF(I70>=30,"1a fascia",IF(I70>=15,"2a fascia",IF(I70>=7,"3a fascia",IF(I70>=3,"4a fascia","Scommessa"))))) -> 2a fascia | L70: Titolare | M70: Nuovo - Titolare confermato (2/2) | N70: - | O70: 2o | X70: 2 | Y70: 5.25 | Z70: 5.25 | AA70: 0 | AB70: 0 | AC70: - | AD70: Si | AE70: =ROUND(IF(P70="",5.5,R70*MIN(1,P70/25)+5.5*(1-MIN(1,P70/25))),2) -> 5.5 | AF70: Rodriguez Je. (COM) | AG70: 6 | AH70: =RANK(H70,$H$4:$H$196) -> 21
A71: =RANK(B71,$B$4:$B$196) -> 67 | B71: =ROUND(Guida!$B$22*H71/Guida!$B$30+Guida!$B$23*MAX(0,MIN(1,(AE71-5.4)/1.6))+Guida!$B$24*0+Guida!$B$25*0,1) -> 16.8 | C71: Folorunsho | D71: Monza | E71: Centrale / Trequartista | F71: 4 | G71: 4 | H71: 17 | I71: =MAX(1,ROUND(H71^Guida!$B$18*Guida!$F$13,0)) -> 10 | J71: =MAX(2,ROUND(I71*1.2,0)) -> 12 | K71: =IF(I71>=60,"Top",IF(I71>=30,"1a fascia",IF(I71>=15,"2a fascia",IF(I71>=7,"3a fascia",IF(I71>=3,"4a fascia","Scommessa"))))) -> 3a fascia | L71: Ballottaggio | M71: Nuovo - In ballottaggio (1/2) | N71: - | O71: - | P71: 26 | Q71: 6.04 | R71: 6.21 | S71: 2 | T71: 0 | U71: 0/0 | V71: 3 | W71: 0 | X71: 1 | Y71: 6 | Z71: 6 | AA71: 0 | AB71: 0 | AC71: Cagliari | AD71: Si | AE71: =ROUND(IF(P71="",5.5,R71*MIN(1,P71/25)+5.5*(1-MIN(1,P71/25))),2) -> 6.21 | AF71: Berisha M. (LEC) | AG71: 6 | AH71: =RANK(H71,$H$4:$H$196) -> 88
A72: =RANK(B72,$B$4:$B$196) -> 69 | B72: =ROUND(Guida!$B$22*H72/Guida!$B$30+Guida!$B$23*MAX(0,MIN(1,(AE72-5.4)/1.6))+Guida!$B$24*0.6+Guida!$B$25*0.6,1) -> 16.7 | C72: Schmid | D72: Frosinone | E72: Esterno alto / Trequartista | F72: 8 | G72: 8 | H72: 25 | I72: =MAX(1,ROUND(H72^Guida!$B$18*Guida!$F$13,0)) -> 12 | J72: =MAX(2,ROUND(I72*1.2,0)) -> 14 | K72: =IF(I72>=60,"Top",IF(I72>=30,"1a fascia",IF(I72>=15,"2a fascia",IF(I72>=7,"3a fascia",IF(I72>=3,"4a fascia","Scommessa"))))) -> 3a fascia | L72: Titolare | M72: Nuovo - Titolare confermato (2/2) | N72: 2o | O72: 2o | X72: 2 | Y72: 5.75 | Z72: 5.5 | AA72: 0 | AB72: 0 | AC72: - | AD72: Si | AE72: =ROUND(IF(P72="",5.5,R72*MIN(1,P72/25)+5.5*(1-MIN(1,P72/25))),2) -> 5.5 | AF72: Gaetano (ATA) | AG72: 5 | AH72: =RANK(H72,$H$4:$H$196) -> 54
A73: =RANK(B73,$B$4:$B$196) -> 69 | B73: =ROUND(Guida!$B$22*H73/Guida!$B$30+Guida!$B$23*MAX(0,MIN(1,(AE73-5.4)/1.6))+Guida!$B$24*0+Guida!$B$25*1,1) -> 16.7 | C73: Pierotti | D73: Lecce | E73: Esterno alto | F73: 6 | G73: 6 | H73: 19 | I73: =MAX(1,ROUND(H73^Guida!$B$18*Guida!$F$13,0)) -> 11 | J73: =MAX(2,ROUND(I73*1.2,0)) -> 13 | K73: =IF(I73>=60,"Top",IF(I73>=30,"1a fascia",IF(I73>=15,"2a fascia",IF(I73>=7,"3a fascia",IF(I73>=3,"4a fascia","Scommessa"))))) -> 3a fascia | L73: Titolare | M73: Titolare confermato (2/2) | N73: - | O73: 1o | P73: 37 | Q73: 5.8 | R73: 5.85 | S73: 1 | T73: 1 | U73: 0/0 | V73: 4 | W73: 0 | X73: 2 | Y73: 5.75 | Z73: 5.75 | AA73: 0 | AB73: 0 | AC73: Lecce | AD73: No | AE73: =ROUND(IF(P73="",5.5,R73*MIN(1,P73/25)+5.5*(1-MIN(1,P73/25))),2) -> 5.85 | AF73: Mora (ROM) | AG73: 6 | AH73: =RANK(H73,$H$4:$H$196) -> 81
A74: =RANK(B74,$B$4:$B$196) -> 71 | B74: =ROUND(Guida!$B$22*H74/Guida!$B$30+Guida!$B$23*MAX(0,MIN(1,(AE74-5.4)/1.6))+Guida!$B$24*0+Guida!$B$25*0,1) -> 16.6 | C74: Lobotka | D74: Napoli | E74: Mediano / Centrale | F74: 7 | G74: 8 | H74: 23 | I74: =MAX(1,ROUND(H74^Guida!$B$18*Guida!$F$13,0)) -> 12 | J74: =MAX(2,ROUND(I74*1.2,0)) -> 14 | K74: =IF(I74>=60,"Top",IF(I74>=30,"1a fascia",IF(I74>=15,"2a fascia",IF(I74>=7,"3a fascia",IF(I74>=3,"4a fascia","Scommessa"))))) -> 3a fascia | L74: Ballottaggio | M74: In ballottaggio (2/2) | N74: - | O74: - | P74: 31 | Q74: 6.05 | R74: 6.1 | S74: 1 | T74: 0 | U74: 0/0 | V74: 3 | W74: 0 | X74: 2 | Y74: 6.25 | Z74: 6.25 | AA74: 0 | AB74: 0 | AC74: Napoli | AD74: No | AE74: =ROUND(IF(P74="",5.5,R74*MIN(1,P74/25)+5.5*(1-MIN(1,P74/25))),2) -> 6.1 | AF74: Mora (ROM) | AG74: 3 | AH74: =RANK(H74,$H$4:$H$196) -> 63
A75: =RANK(B75,$B$4:$B$196) -> 72 | B75: =ROUND(Guida!$B$22*H75/Guida!$B$30+Guida!$B$23*MAX(0,MIN(1,(AE75-5.4)/1.6))+Guida!$B$24*0+Guida!$B$25*0.6,1) -> 16 | C75: Nicolussi Caviglia | D75: Parma | E75: Mediano / Centrale | F75: 6 | G75: 6 | H75: 16 | I75: =MAX(1,ROUND(H75^Guida!$B$18*Guida!$F$13,0)) -> 10 | J75: =MAX(2,ROUND(I75*1.2,0)) -> 12 | K75: =IF(I75>=60,"Top",IF(I75>=30,"1a fascia",IF(I75>=15,"2a fascia",IF(I75>=7,"3a fascia",IF(I75>=3,"4a fascia","Scommessa"))))) -> 3a fascia | L75: Titolare | M75: INFORTUNATO (lungo stop) - presenze finora: 0/2 | N75: - | O75: 2o | P75: 23 | Q75: 5.89 | R75: 6.02 | S75: 0 | T75: 4 | U75: 0/0 | V75: 4 | W75: 0 | X75: 0 | AC75: Parma | AD75: No | AE75: =ROUND(IF(P75="",5.5,R75*MIN(1,P75/25)+5.5*(1-MIN(1,P75/25))),2) -> 5.98 | AF75: Konè I. (SAS) | AG75: 4 | AH75: =RANK(H75,$H$4:$H$196) -> 93 | AI75: Operato a fine agosto alla coscia destra. Ipotesi rientro da novembre.
A76: =RANK(B76,$B$4:$B$196) -> 73 | B76: =ROUND(Guida!$B$22*H76/Guida!$B$30+Guida!$B$23*MAX(0,MIN(1,(AE76-5.4)/1.6))+Guida!$B$24*0+Guida!$B$25*0,1) -> 15.9 | C76: Ndour | D76: Fiorentina | E76: Centrale | F76: 8 | G76: 7 | H76: 22 | I76: =MAX(1,ROUND(H76^Guida!$B$18*Guida!$F$13,0)) -> 12 | J76: =MAX(2,ROUND(I76*1.2,0)) -> 14 | K76: =IF(I76>=60,"Top",IF(I76>=30,"1a fascia",IF(I76>=15,"2a fascia",IF(I76>=7,"3a fascia",IF(I76>=3,"4a fascia","Scommessa"))))) -> 3a fascia | L76: Titolare | M76: Titolare confermato (2/2) | N76: - | O76: - | P76: 30 | Q76: 5.8 | R76: 6.07 | S76: 3 | T76: 0 | U76: 0/0 | V76: 2 | W76: 0 | X76: 2 | Y76: 5 | Z76: 5 | AA76: 0 | AB76: 0 | AC76: Fiorentina | AD76: No | AE76: =ROUND(IF(P76="",5.5,R76*MIN(1,P76/25)+5.5*(1-MIN(1,P76/25))),2) -> 6.07 | AF76: Taylor K. (LAZ) | AG76: 6 | AH76: =RANK(H76,$H$4:$H$196) -> 68
A77: =RANK(B77,$B$4:$B$196) -> 74 | B77: =ROUND(Guida!$B$22*H77/Guida!$B$30+Guida!$B$23*MAX(0,MIN(1,(AE77-5.4)/1.6))+Guida!$B$24*0+Guida!$B$25*0,1) -> 15.1 | C77: Vergara | D77: Napoli | E77: Esterno alto / Trequartista | F77: 8 | G77: 10 | H77: 35 | I77: =MAX(1,ROUND(H77^Guida!$B$18*Guida!$F$13,0)) -> 15 | J77: =MAX(2,ROUND(I77*1.2,0)) -> 18 | K77: =IF(I77>=60,"Top",IF(I77>=30,"1a fascia",IF(I77>=15,"2a fascia",IF(I77>=7,"3a fascia",IF(I77>=3,"4a fascia","Scommessa"))))) -> 2a fascia | L77: Titolare | M77: Rischia il posto (1/2) | N77: - | O77: - | P77: 8 | Q77: 6.25 | R77: 6.5 | S77: 1 | T77: 0 | U77: 0/0 | V77: 2 | W77: 0 | X77: 1 | Y77: 7.5 | Z77: 11.5 | AA77: 1 | AB77: 1 | AC77: Napoli | AD77: No | AE77: =ROUND(IF(P77="",5.5,R77*MIN(1,P77/25)+5.5*(1-MIN(1,P77/25))),2) -> 5.82 | AF77: Pellegrini Lo. (ROM) | AG77: 3 | AH77: =RANK(H77,$H$4:$H$196) -> 39
A78: =RANK(B78,$B$4:$B$196) -> 74 | B78: =ROUND(Guida!$B$22*H78/Guida!$B$30+Guida!$B$23*MAX(0,MIN(1,(AE78-5.4)/1.6))+Guida!$B$24*0+Guida!$B$25*0,1) -> 15.1 | C78: Ricci S. | D78: Como | E78: Mediano / Centrale | F78: 4 | G78: 4 | H78: 12 | I78: =MAX(1,ROUND(H78^Guida!$B$18*Guida!$F$13,0)) -> 8 | J78: =MAX(2,ROUND(I78*1.2,0)) -> 10 | K78: =IF(I78>=60,"Top",IF(I78>=30,"1a fascia",IF(I78>=15,"2a fascia",IF(I78>=7,"3a fascia",IF(I78>=3,"4a fascia","Scommessa"))))) -> 3a fascia | L78: Riserva | M78: Nuovo - Riserva (0/2) | N78: - | O78: - | P78: 28 | Q78: 6 | R78: 6.18 | S78: 1 | T78: 3 | U78: 0/0 | V78: 3 | W78: 0 | X78: 0 | AC78: Milan | AD78: Si | AE78: =ROUND(IF(P78="",5.5,R78*MIN(1,P78/25)+5.5*(1-MIN(1,P78/25))),2) -> 6.18 | AF78: Calò (FRO) | AG78: 6 | AH78: =RANK(H78,$H$4:$H$196) -> 118
A79: =RANK(B79,$B$4:$B$196) -> 76 | B79: =ROUND(Guida!$B$22*H79/Guida!$B$30+Guida!$B$23*MAX(0,MIN(1,(AE79-5.4)/1.6))+Guida!$B$24*0+Guida!$B$25*0.35,1) -> 14.8 | C79: Gandelman | D79: Lecce | E79: Centrale / Trequartista | F79: 5 | G79: 4 | H79: 10 | I79: =MAX(1,ROUND(H79^Guida!$B$18*Guida!$F$13,0)) -> 7 | J79: =MAX(2,ROUND(I79*1.2,0)) -> 8 | K79: =IF(I79>=60,"Top",IF(I79>=30,"1a fascia",IF(I79>=15,"2a fascia",IF(I79>=7,"3a fascia",IF(I79>=3,"4a fascia","Scommessa"))))) -> 3a fascia | L79: Ballottaggio | M79: In ballottaggio (0/2) | N79: - | O79: 3o | P79: 16 | Q79: 5.97 | R79: 6.41 | S79: 2 | T79: 1 | U79: 0/0 | V79: 0 | W79: 0 | X79: 0 | AC79: Lecce | AD79: No | AE79: =ROUND(IF(P79="",5.5,R79*MIN(1,P79/25)+5.5*(1-MIN(1,P79/25))),2) -> 6.08 | AF79: Pellegrini Lo. (ROM) | AG79: 6 | AH79: =RANK(H79,$H$4:$H$196) -> 143
A80: =RANK(B80,$B$4:$B$196) -> 77 | B80: =ROUND(Guida!$B$22*H80/Guida!$B$30+Guida!$B$23*MAX(0,MIN(1,(AE80-5.4)/1.6))+Guida!$B$24*0+Guida!$B$25*1,1) -> 14.7 | C80: Fazzini | D80: Cagliari | E80: Centrale / Trequartista | F80: 7 | G80: 6 | H80: 23 | I80: =MAX(1,ROUND(H80^Guida!$B$18*Guida!$F$13,0)) -> 12 | J80: =MAX(2,ROUND(I80*1.2,0)) -> 14 | K80: =IF(I80>=60,"Top",IF(I80>=30,"1a fascia",IF(I80>=15,"2a fascia",IF(I80>=7,"3a fascia",IF(I80>=3,"4a fascia","Scommessa"))))) -> 3a fascia | L80: Titolare | M80: Nuovo - Titolare confermato (2/2) | N80: - | O80: 1o | P80: 12 | Q80: 5.88 | R80: 5.83 | S80: 0 | T80: 0 | U80: 0/0 | V80: 2 | W80: 0 | X80: 2 | Y80: 5.5 | Z80: 5.25 | AA80: 0 | AB80: 0 | AC80: Fiorentina | AD80: Si | AE80: =ROUND(IF(P80="",5.5,R80*MIN(1,P80/25)+5.5*(1-MIN(1,P80/25))),2) -> 5.66 | AF80: Gaetano (ATA) | AG80: 6 | AH80: =RANK(H80,$H$4:$H$196) -> 63
A81: =RANK(B81,$B$4:$B$196) -> 77 | B81: =ROUND(Guida!$B$22*H81/Guida!$B$30+Guida!$B$23*MAX(0,MIN(1,(AE81-5.4)/1.6))+Guida!$B$24*0+Guida!$B$25*0,1) -> 14.7 | C81: Moro N. | D81: Bologna | E81: Mediano / Centrale | F81: 4 | G81: 4 | H81: 14 | I81: =MAX(1,ROUND(H81^Guida!$B$18*Guida!$F$13,0)) -> 9 | J81: =MAX(2,ROUND(I81*1.2,0)) -> 11 | K81: =IF(I81>=60,"Top",IF(I81>=30,"1a fascia",IF(I81>=15,"2a fascia",IF(I81>=7,"3a fascia",IF(I81>=3,"4a fascia","Scommessa"))))) -> 3a fascia | L81: Riserva | M81: Riserva (0/2) | N81: - | O81: - | P81: 28 | Q81: 5.93 | R81: 6.12 | S81: 2 | T81: 0 | U81: 0/0 | V81: 1 | W81: 0 | X81: 0 | AC81: Bologna | AD81: No | AE81: =ROUND(IF(P81="",5.5,R81*MIN(1,P81/25)+5.5*(1-MIN(1,P81/25))),2) -> 6.12 | AF81: Konè I. (SAS) | AG81: 6 | AH81: =RANK(H81,$H$4:$H$196) -> 110
